Workbook

Sheet Respuestas de formulario 1
A1: {=L:L&G:G} -> MARCA TEMPORALMÓVIL | B1: Marca temporal | C1: {=IFERROR(IF(B:B="","",TEXT(B:B,"dd")),"DIA")} -> Marca temporal | D1: {=IFERROR(IF(B:B="","",TEXT(B:B,"mm")),"MES")} -> Marca temporal | E1: {=IFERROR(IF(B:B="","",YEAR(B:B)),"AÑO")} -> AÑO | F1: {=B:B} -> Marca temporal | G1: MÓVIL | H1: CALIFIQUE QUE TAN SUCIO ESTABA EL VEHÍCULO ANTES DEL LAVADO. DONDE 1 ES MUY LIMPIO Y 5 ES MUY SUCIO. | I1: ¿CUANTAS PERSONAS PARTICIPARON EN LA INTERVENCIÓN? | J1: Califique el servicio prestado en el lavadero externo (espacio único para satélite Rionegro) | L1: {=UPPER(M:M)} -> MARCA TEMPORAL | M1: {=IF(B:B="","",TEXT(B:B,"MMMM"))} -> Marca temporal
A2: DICIEMBRE2563 | B2: 44915.41 | C2: 20 | D2: 12 | E2: 2022 | F2: 44915.41 | G2: 2563 | H2: VEHÍCULO APROPIADO PARA LAVADO | L2: DICIEMBRE | M2: diciembre | N2: =B2 -> 44915.41
A3: DICIEMBRE2628 | B3: 44915.41 | C3: 20 | D3: 12 | E3: 2022 | F3: 44915.41 | G3: 2628 | H3: VEHÍCULO APROPIADO PARA LAVADO | L3: DICIEMBRE | M3: diciembre
A4: DICIEMBRE2469 | B4: 44915.41 | C4: 20 | D4: 12 | E4: 2022 | F4: 44915.41 | G4: 2469 | H4: VEHÍCULO APROPIADO PARA LAVADO | L4: DICIEMBRE | M4: diciembre
A5: DICIEMBRE2677 | B5: 44915.41 | C5: 20 | D5: 12 | E5: 2022 | F5: 44915.41 | G5: 2677 | H5: VEHÍCULO APROPIADO PARA LAVADO | L5: DICIEMBRE | M5: diciembre
A6: DICIEMBRE2194 | B6: 44915.411 | C6: 20 | D6: 12 | E6: 2022 | F6: 44915.411 | G6: 2194 | H6: VEHÍCULO APROPIADO PARA LAVADO | L6: DICIEMBRE | M6: diciembre
A7: DICIEMBRE2460 | B7: 44915.411 | C7: 20 | D7: 12 | E7: 2022 | F7: 44915.411 | G7: 2460 | H7: VEHÍCULO APROPIADO PARA LAVADO | L7: DICIEMBRE | M7: diciembre
A8: DICIEMBRE2669 | B8: 44915.411 | C8: 20 | D8: 12 | E8: 2022 | F8: 44915.411 | G8: 2669 | H8: VEHÍCULO APROPIADO PARA LAVADO | L8: DICIEMBRE | M8: diciembre
A9: DICIEMBRE2189 | B9: 44915.411 | C9: 20 | D9: 12 | E9: 2022 | F9: 44915.411 | G9: 2189 | H9: VEHÍCULO APROPIADO PARA LAVADO | L9: DICIEMBRE | M9: diciembre
A10: DICIEMBRE2629 | B10: 44915.411 | C10: 20 | D10: 12 | E10: 2022 | F10: 44915.411 | G10: 2629 | H10: VEHÍCULO APROPIADO PARA LAVADO | L10: DICIEMBRE | M10: diciembre
A11: DICIEMBRE2367 | B11: 44915.411 | C11: 20 | D11: 12 | E11: 2022 | F11: 44915.411 | G11: 2367 | H11: VEHÍCULO APROPIADO PARA LAVADO | L11: DICIEMBRE | M11: diciembre
A12: DICIEMBRE2563 | B12: 44915.412 | C12: 20 | D12: 12 | E12: 2022 | F12: 44915.412 | G12: 2563 | H12: VEHÍCULO APROPIADO PARA LAVADO | L12: DICIEMBRE | M12: diciembre
A13: DICIEMBRE2400 | B13: 44916.271 | C13: 21 | D13: 12 | E13: 2022 | F13: 44916.271 | G13: 2400 | H13: VEHÍCULO APROPIADO PARA LAVADO | L13: DICIEMBRE | M13: diciembre
A14: DICIEMBRE2369 | B14: 44916.272 | C14: 21 | D14: 12 | E14: 2022 | F14: 44916.272 | G14: 2369 | H14: VEHÍCULO APROPIADO PARA LAVADO | L14: DICIEMBRE | M14: diciembre
... A78: ENERO2671 | B78: 44930.275 | C78: 04 | D78: 01 | E78: 2023 | F78: 44930.275 | G78: 2671 | H78: EL VEHÍCULO SE ENCONTRABA MUY SUCIO | L78: ENERO | M78: enero
A79: ENEROKHN937 | B79: 44930.601 | C79: 04 | D79: 01 | E79: 2023 | F79: 44930.601 | G79: KHN937 | H79: EL VEHÍCULO SE ENCONTRABA MUY SUCIO | L79: ENERO | M79: enero
A80: ENERO2460 | B80: 44930.97 | C80: 04 | D80: 01 | E80: 2023 | F80: 44930.97 | G80: 2460 | H80: VEHÍCULO APROPIADO PARA LAVADO | L80: ENERO | M80: enero
A81: ENERO2458 | B81: 44931.029 | C81: 05 | D81: 01 | E81: 2023 | F81: 44931.029 | G81: 2458 | H81: VEHÍCULO APROPIADO PARA LAVADO | L81: ENERO | M81: enero
A82: ENERO2659 | B82: 44931.064 | C82: 05 | D82: 01 | E82: 2023 | F82: 44931.064 | G82: 2659 | H82: VEHÍCULO APROPIADO PARA LAVADO | L82: ENERO | M82: enero
A83: ENERO2436 | B83: 44931.103 | C83: 05 | D83: 01 | E83: 2023 | F83: 44931.103 | G83: 2436 | H83: VEHÍCULO APROPIADO PARA LAVADO | L83: ENERO | M83: enero
A84: ENERO2339 | B84: 44931.158 | C84: 05 | D84: 01 | E84: 2023 | F84: 44931.158 | G84: 2339 | H84: VEHÍCULO APROPIADO PARA LAVADO | L84: ENERO | M84: enero
A85: ENERO2273 | B85: 44931.186 | C85: 05 | D85: 01 | E85: 2023 | F85: 44931.186 | G85: 2273 | H85: VEHÍCULO APROPIADO PARA LAVADO | L85: ENERO | M85: enero
A86: ENERO2456 | B86: 44931.221 | C86: 05 | D86: 01 | E86: 2023 | F86: 44931.221 | G86: 2456 | H86: VEHÍCULO APROPIADO PARA LAVADO | L86: ENERO | M86: enero
A87: ENERO2238 | B87: 44931.382 | C87: 05 | D87: 01 | E87: 2023 | F87: 44931.382 | G87: 2238 | H87: VEHÍCULO APROPIADO PARA LAVADO | L87: ENERO | M87: enero
A88: ENERO1798 | B88: 44931.464 | C88: 05 | D88: 01 | E88: 2023 | F88: 44931.464 | G88: 1798 | H88: VEHÍCULO APROPIADO PARA LAVADO | L88: ENERO | M88: enero
A89: ENERO2682 | B89: 44931.986 | C89: 05 | D89: 01 | E89: 2023 | F89: 44931.986 | G89: 2682 | H89: VEHÍCULO APROPIADO PARA LAVADO | L89: ENERO | M89: enero
A90: ENERO2663 | B90: 44932.021 | C90: 06 | D90: 01 | E90: 2023 | F90: 44932.021 | G90: 2663 | H90: VEHÍCULO APROPIADO PARA LAVADO | L90: ENERO | M90: enero
A91: ENERO2355 | B91: 44932.053 | C91: 06 | D91: 01 | E91: 2023 | F91: 44932.053 | G91: 2355 | H91: VEHÍCULO APROPIADO PARA LAVADO | L91: ENERO | M91: enero
... A190: ENERO2637 | B190: 44942.339 | C190: 16 | D190: 01 | E190: 2023 | F190: 44942.339 | G190: 2637 | H190: VEHÍCULO APROPIADO PARA LAVADO | L190: ENERO | M190: enero
A191: ENEROKHN152 | B191: 44942.356 | C191: 16 | D191: 01 | E191: 2023 | F191: 44942.356 | G191: KHN152 | H191: VEHÍCULO APROPIADO PARA LAVADO | L191: ENERO | M191: enero
A192: ENERO2666 | B192: 44942.38 | C192: 16 | D192: 01 | E192: 2023 | F192: 44942.38 | G192: 2666 | H192: EL VEHÍCULO SE ENCONTRABA MUY SUCIO | L192: ENERO | M192: enero
A193: ENEROIAZ451 | B193: 44942.395 | C193: 16 | D193: 01 | E193: 2023 | F193: 44942.395 | G193: IAZ451 | H193: VEHÍCULO APROPIADO PARA LAVADO | L193: ENERO | M193: enero
A194: ENEROJHU739 | B194: 44942.482 | C194: 16 | D194: 01 | E194: 2023 | F194: 44942.482 | G194: JHU739 | H194: VEHÍCULO APROPIADO PARA LAVADO | L194: ENERO | M194: enero
A195: ENEROMNK264 | B195: 44942.535 | C195: 16 | D195: 01 | E195: 2023 | F195: 44942.535 | G195: MNK264 | H195: VEHÍCULO APROPIADO PARA LAVADO | L195: ENERO | M195: enero
A196: ENERO2679 | B196: 44942.558 | C196: 16 | D196: 01 | E196: 2023 | F196: 44942.558 | G196: 2679 | H196: VEHÍCULO APROPIADO PARA LAVADO | L196: ENERO | M196: enero
A197: ENEROKHQ888 | B197: 44942.614 | C197: 16 | D197: 01 | E197: 2023 | F197: 44942.614 | G197: KHQ888 | H197: VEHÍCULO APROPIADO PARA LAVADO | L197: ENERO | M197: enero
A198: ENEROKHN937 | B198: 44942.64 | C198: 16 | D198: 01 | E198: 2023 | F198: 44942.64 | G198: KHN937 | H198: VEHÍCULO APROPIADO PARA LAVADO | L198: ENERO | M198: enero
A199: ENERO2630 | B199: 44942.95 | C199: 16 | D199: 01 | E199: 2023 | F199: 44942.95 | G199: 2630 | H199: VEHÍCULO APROPIADO PARA LAVADO | L199: ENERO | M199: enero
A200: ENERO2677 | B200: 44942.982 | C200: 16 | D200: 01 | E200: 2023 | F200: 44942.982 | G200: 2677 | H200: VEHÍCULO APROPIADO PARA LAVADO | L200: ENERO | M200: enero
A201: ENERO2206 | B201: 44943.013 | C201: 17 | D201: 01 | E201: 2023 | F201: 44943.013 | G201: 2206 | H201: VEHÍCULO APROPIADO PARA LAVADO | L201: ENERO | M201: enero
A202: ENERO2438 | B202: 44943.029 | C202: 17 | D202: 01 | E202: 2023 | F202: 44943.029 | G202: 2438 | H202: VEHÍCULO APROPIADO PARA LAVADO | L202: ENERO | M202: enero
A203: ENERO2275 | B203: 44943.058 | C203: 17 | D203: 01 | E203: 2023 | F203: 44943.058 | G203: 2275 | H203: VEHÍCULO APROPIADO PARA LAVADO | L203: ENERO | M203: enero
A204: ENERO2569 | B204: 44943.072 | C204: 17 | D204: 01 | E204: 2023 | F204: 44943.072 | G204: 2569 | H204: VEHÍCULO APROPIADO PARA LAVADO | L204: ENERO | M204: enero
A205: ENERO2570 | B205: 44943.108 | C205: 17 | D205: 01 | E205: 2023 | F205: 44943.108 | G205: 2570 | H205: VEHÍCULO APROPIADO PARA LAVADO | L205: ENERO | M205: enero
A206: ENERO2227 | B206: 44943.146 | C206: 17 | D206: 01 | E206: 2023 | F206: 44943.146 | G206: 2227 | H206: VEHÍCULO APROPIADO PARA LAVADO | L206: ENERO | M206: enero
A207: ENERO2244 | B207: 44943.166 | C207: 17 | D207: 01 | E207: 2023 | F207: 44943.166 | G207: 2244 | H207: VEHÍCULO APROPIADO PARA LAVADO | L207: ENERO | M207: enero
A208: ENERO2437 | B208: 44943.179 | C208: 17 | D208: 01 | E208: 2023 | F208: 44943.179 | G208: 2437 | H208: VEHÍCULO APROPIADO PARA LAVADO | L208: ENERO | M208: enero
A209: ENERO2252 | B209: 44943.193 | C209: 17 | D209: 01 | E209: 2023 | F209: 44943.193 | G209: 2252 | H209: VEHÍCULO APROPIADO PARA LAVADO | L209: ENERO | M209: enero
A210: ENERO2490 | B210: 44943.216 | C210: 17 | D210: 01 | E210: 2023 | F210: 44943.216 | G210: 2490 | H210: VEHÍCULO APROPIADO PARA LAVADO | L210: ENERO | M210: enero
A211: ENERO2216 | B211: 44943.227 | C211: 17 | D211: 01 | E211: 2023 | F211: 44943.227 | G211: 2216 | H211: VEHÍCULO APROPIADO PARA LAVADO | L211: ENERO | M211: enero
A212: ENEROITX257 | B212: 44943.305 | C212: 17 | D212: 01 | E212: 2023 | F212: 44943.305 | G212: ITX257 | H212: VEHÍCULO APROPIADO PARA LAVADO | L212: ENERO | M212: enero
A213: ENEROEWZ999 | B213: 44943.38 | C213: 17 | D213: 01 | E213: 2023 | F213: 44943.38 | G213: EWZ999 | H213: VEHÍCULO APROPIADO PARA LAVADO | L213: ENERO | M213: enero
A214: ENERO2380 | B214: 44943.954 | C214: 17 | D214: 01 | E214: 2023 | F214: 44943.954 | G214: 2380 | H214: VEHÍCULO APROPIADO PARA LAVADO | L214: ENERO | M214: enero
A215: ENERO2454 | B215: 44943.976 | C215: 17 | D215: 01 | E215: 2023 | F215: 44943.976 | G215: 2454 | H215: VEHÍCULO APROPIADO PARA LAVADO | L215: ENERO | M215: enero
A216: ENERO2359 | B216: 44944.002 | C216: 18 | D216: 01 | E216: 2023 | F216: 44944.002 | G216: 2359 | H216: VEHÍCULO APROPIADO PARA LAVADO | L216: ENERO | M216: enero
A217: ENERO2624 | B217: 44944.023 | C217: 18 | D217: 01 | E217: 2023 | F217: 44944.023 | G217: 2624 | H217: VEHÍCULO APROPIADO PARA LAVADO | L217: ENERO | M217: enero
A218: ENERO2573 | B218: 44944.05 | C218: 18 | D218: 01 | E218: 2023 | F218: 44944.05 | G218: 2573 | H218: VEHÍCULO APROPIADO PARA LAVADO | L218: ENERO | M218: enero
A219: ENERO2395 | B219: 44944.071 | C219: 18 | D219: 01 | E219: 2023 | F219: 44944.071 | G219: 2395 | H219: VEHÍCULO APROPIADO PARA LAVADO | L219: ENERO | M219: enero
A220: ENERO2466 | B220: 44944.1 | C220: 18 | D220: 01 | E220: 2023 | F220: 44944.1 | G220: 2466 | H220: VEHÍCULO APROPIADO PARA LAVADO | L220: ENERO | M220: enero
A221: ENERO2434 | B221: 44944.138 | C221: 18 | D221: 01 | E221: 2023 | F221: 44944.138 | G221: 2434 | H221: VEHÍCULO APROPIADO PARA LAVADO | L221: ENERO | M221: enero
A222: ENERO2576 | B222: 44944.162 | C222: 18 | D222: 01 | E222: 2023 | F222: 44944.162 | G222: 2576 | H222: VEHÍCULO APROPIADO PARA LAVADO | L222: ENERO | M222: enero
A223: ENERO2661 | B223: 44944.193 | C223: 18 | D223: 01 | E223: 2023 | F223: 44944.193 | G223: 2661 | H223: VEHÍCULO APROPIADO PARA LAVADO | L223: ENERO | M223: enero
A224: ENERO2670 | B224: 44944.209 | C224: 18 | D224: 01 | E224: 2023 | F224: 44944.209 | G224: 2670 | H224: VEHÍCULO APROPIADO PARA LAVADO | L224: ENERO | M224: enero
A225: ENERO2657 | B225: 44944.232 | C225: 18 | D225: 01 | E225: 2023 | F225: 44944.232 | G225: 2657 | H225: VEHÍCULO APROPIADO PARA LAVADO | L225: ENERO | M225: enero
A226: ENEROLKN753 | B226: 44944.304 | C226: 18 | D226: 01 | E226: 2023 | F226: 44944.304 | G226: LKN753 | H226: VEHÍCULO APROPIADO PARA LAVADO | L226: ENERO | M226: enero
A227: ENERO2204 | B227: 44944.316 | C227: 18 | D227: 01 | E227: 2023 | F227: 44944.316 | G227: 2204 | H227: VEHÍCULO APROPIADO PARA LAVADO | L227: ENERO | M227: enero
A228: ENERO2205 | B228: 44944.316 | C228: 18 | D228: 01 | E228: 2023 | F228: 44944.316 | G228: 2205 | H228: VEHÍCULO APROPIADO PARA LAVADO | L228: ENERO | M228: enero
A229: ENERO2389 | B229: 44944.317 | C229: 18 | D229: 01 | E229: 2023 | F229: 44944.317 | G229: 2389 | H229: VEHÍCULO APROPIADO PARA LAVADO | L229: ENERO | M229: enero
A230: ENERO2397 | B230: 44944.317 | C230: 18 | D230: 01 | E230: 2023 | F230: 44944.317 | G230: 2397 | H230: VEHÍCULO APROPIADO PARA LAVADO | L230: ENERO | M230: enero
A231: ENERO2398 | B231: 44944.317 | C231: 18 | D231: 01 | E231: 2023 | F231: 44944.317 | G231: 2398 | H231: VEHÍCULO APROPIADO PARA LAVADO | L231: ENERO | M231: enero
A232: ENERO2436 | B232: 44944.317 | C232: 18 | D232: 01 | E232: 2023 | F232: 44944.317 | G232: 2436 | H232: VEHÍCULO APROPIADO PARA LAVADO | L232: ENERO | M232: enero
A233: ENERO2516 | B233: 44944.317 | C233: 18 | D233: 01 | E233: 2023 | F233: 44944.317 | G233: 2516 | H233: VEHÍCULO APROPIADO PARA LAVADO | L233: ENERO | M233: enero
A234: ENERO2628 | B234: 44944.317 | C234: 18 | D234: 01 | E234: 2023 | F234: 44944.317 | G234: 2628 | H234: VEHÍCULO APROPIADO PARA LAVADO | L234: ENERO | M234: enero
A235: ENERO2638 | B235: 44944.317 | C235: 18 | D235: 01 | E235: 2023 | F235: 44944.317 | G235: 2638 | H235: VEHÍCULO APROPIADO PARA LAVADO | L235: ENERO | M235: enero
A236: ENERO2682 | B236: 44944.318 | C236: 18 | D236: 01 | E236: 2023 | F236: 44944.318 | G236: 2682 | H236: VEHÍCULO APROPIADO PARA LAVADO | L236: ENERO | M236: enero
A237: ENERO2683 | B237: 44944.318 | C237: 18 | D237: 01 | E237: 2023 | F237: 44944.318 | G237: 2683 | H237: VEHÍCULO APROPIADO PARA LAVADO | L237: ENERO | M237: enero
A238: ENERO472 | B238: 44944.352 | C238: 18 | D238: 01 | E238: 2023 | F238: 44944.352 | G238: 472 | H238: VEHÍCULO APROPIADO PARA LAVADO | L238: ENERO | M238: enero
A239: ENEROBSF857 | B239: 44944.606 | C239: 18 | D239: 01 | E239: 2023 | F239: 44944.606 | G239: BSF857 | H239: VEHÍCULO APROPIADO PARA LAVADO | L239: ENERO | M239: enero
A240: ENERO2638 | B240: 44944.955 | C240: 18 | D240: 01 | E240: 2023 | F240: 44944.955 | G240: 2638 | H240: VEHÍCULO APROPIADO PARA LAVADO | L240: ENERO | M240: enero
A241: ENERO1900 | B241: 44944.981 | C241: 18 | D241: 01 | E241: 2023 | F241: 44944.981 | G241: 1900 | H241: VEHÍCULO APROPIADO PARA LAVADO | L241: ENERO | M241: enero
A242: ENERO2563 | B242: 44945.004 | C242: 19 | D242: 01 | E242: 2023 | F242: 44945.004 | G242: 2563 | H242: VEHÍCULO APROPIADO PARA LAVADO | L242: ENERO | M242: enero
A243: ENERO2639 | B243: 44945.035 | C243: 19 | D243: 01 | E243: 2023 | F243: 44945.035 | G243: 2639 | H243: VEHÍCULO APROPIADO PARA LAVADO | L243: ENERO | M243: enero
A244: ENERO2217 | B244: 44945.055 | C244: 19 | D244: 01 | E244: 2023 | F244: 44945.055 | G244: 2217 | H244: VEHÍCULO APROPIADO PARA LAVADO | L244: ENERO | M244: enero
A245: ENERO461 | B245: 44945.079 | C245: 19 | D245: 01 | E245: 2023 | F245: 44945.079 | G245: 461 | H245: VEHÍCULO APROPIADO PARA LAVADO | L245: ENERO | M245: enero
A246: ENERO2633 | B246: 44945.101 | C246: 19 | D246: 01 | E246: 2023 | F246: 44945.101 | G246: 2633 | H246: VEHÍCULO APROPIADO PARA LAVADO | L246: ENERO | M246: enero
A247: ENERO2187 | B247: 44945.115 | C247: 19 | D247: 01 | E247: 2023 | F247: 44945.115 | G247: 2187 | H247: VEHÍCULO APROPIADO PARA LAVADO | L247: ENERO | M247: enero
A248: ENERO2625 | B248: 44945.136 | C248: 19 | D248: 01 | E248: 2023 | F248: 44945.136 | G248: 2625 | H248: VEHÍCULO APROPIADO PARA LAVADO | L248: ENERO | M248: enero
A249: ENERO2179 | B249: 44945.152 | C249: 19 | D249: 01 | E249: 2023 | F249: 44945.152 | G249: 2179 | H249: VEHÍCULO APROPIADO PARA LAVADO | L249: ENERO | M249: enero
A250: ENERO2680 | B250: 44945.178 | C250: 19 | D250: 01 | E250: 2023 | F250: 44945.178 | G250: 2680 | H250: VEHÍCULO APROPIADO PARA LAVADO | L250: ENERO | M250: enero
A251: ENERO951 | B251: 44945.202 | C251: 19 | D251: 01 | E251: 2023 | F251: 44945.202 | G251: 951 | H251: VEHÍCULO APROPIADO PARA LAVADO | L251: ENERO | M251: enero
... A253: ENERO2671 | B253: 44945.302 | C253: 19 | D253: 01 | E253: 2023 | F253: 44945.302 | G253: 2671 | H253: EL VEHÍCULO SE ENCONTRABA MUY SUCIO | L253: ENERO | M253: enero
A254: ENEROKHN831 | B254: 44945.356 | C254: 19 | D254: 01 | E254: 2023 | F254: 44945.356 | G254: KHN831 | H254: VEHÍCULO APROPIADO PARA LAVADO | L254: ENERO | M254: enero
A255: ENEROIAU243 | B255: 44945.37 | C255: 19 | D255: 01 | E255: 2023 | F255: 44945.37 | G255: IAU243 | H255: VEHÍCULO APROPIADO PARA LAVADO | L255: ENERO | M255: enero
A256: ENERO2663 | B256: 44945.398 | C256: 19 | D256: 01 | E256: 2023 | F256: 44945.398 | G256: 2663 | H256: EL VEHÍCULO SE ENCONTRABA MUY SUCIO | L256: ENERO | M256: enero
A257: ENEROJEN561 | B257: 44945.398 | C257: 19 | D257: 01 | E257: 2023 | F257: 44945.398 | G257: JEN561 | H257: VEHÍCULO APROPIADO PARA LAVADO | L257: ENERO | M257: enero
A258: ENEROJUZ290 | B258: 44945.443 | C258: 19 | D258: 01 | E258: 2023 | F258: 44945.443 | G258: JUZ290 | H258: VEHÍCULO APROPIADO PARA LAVADO | L258: ENERO | M258: enero
A259: ENERO481 | B259: 44945.448 | C259: 19 | D259: 01 | E259: 2023 | F259: 44945.448 | G259: 481 | H259: VEHÍCULO APROPIADO PARA LAVADO | L259: ENERO | M259: enero
A260: ENEROKHN937 | B260: 44945.594 | C260: 19 | D260: 01 | E260: 2023 | F260: 44945.594 | G260: KHN937 | H260: VEHÍCULO APROPIADO PARA LAVADO | L260: ENERO | M260: enero
A261: ENERO160 | B261: 44945.637 | C261: 19 | D261: 01 | E261: 2023 | F261: 44945.637 | G261: 160 | H261: Se le hizo el correcto lavado al trailer. por dentro . | L261: ENERO | M261: enero
A262: ENERO852 | B262: 44945.949 | C262: 19 | D262: 01 | E262: 2023 | F262: 44945.949 | G262: 852 | H262: VEHÍCULO APROPIADO PARA LAVADO | L262: ENERO | M262: enero
...

Sheet BASE T MPP
A1: =IFERROR(__xludf.DUMMYFUNCTION("QUERY(FORM!A:J,""SELECT B,A,C,D,J ORDER BY A DESC"",1)"),"#REF!") -> #REF!

Sheet RECURSO ACTUAL
A1: =IFERROR(__xludf.DUMMYFUNCTION("IMPORTRANGE(""https://docs.google.com/spreadsheets/d/1m7J6Y1SSBkQdcMVXl2Yj-j28gyJMAbS4UK0IL9qsiNA/edit?gid=0#gid=0"",""ANTIOQUIA!A:H"")"),"MOVIL") -> MOVIL | B1: =IFERROR(__xludf.DUMMYFUNCTION("""COMPUTED_VALUE"""),"POBLACIÓN") -> POBLACIÓN | C1: =IFERROR(__xludf.DUMMYFUNCTION("""COMPUTED_VALUE"""),"PLACA") -> PLACA | D1: =IFERROR(__xludf.DUMMYFUNCTION("""COMPUTED_VALUE"""),"LINEA") -> LINEA | E1: =IFERROR(__xludf.DUMMYFUNCTION("""COMPUTED_VALUE"""),"SOAT") -> SOAT | F1: =IFERROR(__xludf.DUMMYFUNCTION("""COMPUTED_VALUE"""),"RTM") -> RTM
A2: =IFERROR(__xludf.DUMMYFUNCTION("""COMPUTED_VALUE"""),3284.0) -> 3284 | B2: =IFERROR(__xludf.DUMMYFUNCTION("""COMPUTED_VALUE"""),"02-Medellin") -> 02-Medellin | C2: =IFERROR(__xludf.DUMMYFUNCTION("""COMPUTED_VALUE"""),"PVS650") -> PVS650 | D2: =IFERROR(__xludf.DUMMYFUNCTION("""COMPUTED_VALUE"""),"FURGON FOTON 1030") -> FURGON FOTON 1030 | E2: =IFERROR(__xludf.DUMMYFUNCTION("""COMPUTED_VALUE"""),46301.0) -> 46301 | F2: =IFERROR(__xludf.DUMMYFUNCTION("""COMPUTED_VALUE"""),46668.0) -> 46668
A3: =IFERROR(__xludf.DUMMYFUNCTION("""COMPUTED_VALUE"""),3283.0) -> 3283 | B3: =IFERROR(__xludf.DUMMYFUNCTION("""COMPUTED_VALUE"""),"02-Medellin") -> 02-Medellin | C3: =IFERROR(__xludf.DUMMYFUNCTION("""COMPUTED_VALUE"""),"PVS649") -> PVS649 | D3: =IFERROR(__xludf.DUMMYFUNCTION("""COMPUTED_VALUE"""),"FURGON FOTON 1030") -> FURGON FOTON 1030 | E3: =IFERROR(__xludf.DUMMYFUNCTION("""COMPUTED_VALUE"""),46301.0) -> 46301 | F3: =IFERROR(__xludf.DUMMYFUNCTION("""COMPUTED_VALUE"""),46668.0) -> 46668
A4: =IFERROR(__xludf.DUMMYFUNCTION("""COMPUTED_VALUE"""),3282.0) -> 3282 | B4: =IFERROR(__xludf.DUMMYFUNCTION("""COMPUTED_VALUE"""),"02-Medellin") -> 02-Medellin | C4: =IFERROR(__xludf.DUMMYFUNCTION("""COMPUTED_VALUE"""),"PVS648") -> PVS648 | D4: =IFERROR(__xludf.DUMMYFUNCTION("""COMPUTED_VALUE"""),"FURGON FOTON 1030") -> FURGON FOTON 1030 | E4: =IFERROR(__xludf.DUMMYFUNCTION("""COMPUTED_VALUE"""),46301.0) -> 46301 | F4: =IFERROR(__xludf.DUMMYFUNCTION("""COMPUTED_VALUE"""),46668.0) -> 46668
A5: =IFERROR(__xludf.DUMMYFUNCTION("""COMPUTED_VALUE"""),3281.0) -> 3281 | B5: =IFERROR(__xludf.DUMMYFUNCTION("""COMPUTED_VALUE"""),"02-Medellin") -> 02-Medellin | C5: =IFERROR(__xludf.DUMMYFUNCTION("""COMPUTED_VALUE"""),"PVS647") -> PVS647 | D5: =IFERROR(__xludf.DUMMYFUNCTION("""COMPUTED_VALUE"""),"FURGON FOTON 1030") -> FURGON FOTON 1030 | E5: =IFERROR(__xludf.DUMMYFUNCTION("""COMPUTED_VALUE"""),46301.0) -> 46301 | F5: =IFERROR(__xludf.DUMMYFUNCTION("""COMPUTED_VALUE"""),46668.0) -> 46668
A6: =IFERROR(__xludf.DUMMYFUNCTION("""COMPUTED_VALUE"""),3280.0) -> 3280 | B6: =IFERROR(__xludf.DUMMYFUNCTION("""COMPUTED_VALUE"""),"02-Medellin") -> 02-Medellin | C6: =IFERROR(__xludf.DUMMYFUNCTION("""COMPUTED_VALUE"""),"PVS646") -> PVS646 | D6: =IFERROR(__xludf.DUMMYFUNCTION("""COMPUTED_VALUE"""),"FURGON FOTON 1030") -> FURGON FOTON 1030 | E6: =IFERROR(__xludf.DUMMYFUNCTION("""COMPUTED_VALUE"""),46301.0) -> 46301 | F6: =IFERROR(__xludf.DUMMYFUNCTION("""COMPUTED_VALUE"""),46668.0) -> 46668
A7: =IFERROR(__xludf.DUMMYFUNCTION("""COMPUTED_VALUE"""),3279.0) -> 3279 | B7: =IFERROR(__xludf.DUMMYFUNCTION("""COMPUTED_VALUE"""),"02-Medellin") -> 02-Medellin | C7: =IFERROR(__xludf.DUMMYFUNCTION("""COMPUTED_VALUE"""),"PVS645") -> PVS645 | D7: =IFERROR(__xludf.DUMMYFUNCTION("""COMPUTED_VALUE"""),"FURGON FOTON 1030") -> FURGON FOTON 1030 | E7: =IFERROR(__xludf.DUMMYFUNCTION("""COMPUTED_VALUE"""),46301.0) -> 46301 | F7: =IFERROR(__xludf.DUMMYFUNCTION("""COMPUTED_VALUE"""),46668.0) -> 46668
A8: =IFERROR(__xludf.DUMMYFUNCTION("""COMPUTED_VALUE"""),3278.0) -> 3278 | B8: =IFERROR(__xludf.DUMMYFUNCTION("""COMPUTED_VALUE"""),"02-Medellin") -> 02-Medellin | C8: =IFERROR(__xludf.DUMMYFUNCTION("""COMPUTED_VALUE"""),"PVS644") -> PVS644 | D8: =IFERROR(__xludf.DUMMYFUNCTION("""COMPUTED_VALUE"""),"FURGON FOTON 1030") -> FURGON FOTON 1030 | E8: =IFERROR(__xludf.DUMMYFUNCTION("""COMPUTED_VALUE"""),46301.0) -> 46301 | F8: =IFERROR(__xludf.DUMMYFUNCTION("""COMPUTED_VALUE"""),46668.0) -> 46668
A9: =IFERROR(__xludf.DUMMYFUNCTION("""COMPUTED_VALUE"""),3275.0) -> 3275 | B9: =IFERROR(__xludf.DUMMYFUNCTION("""COMPUTED_VALUE"""),"02-Medellin") -> 02-Medellin | C9: =IFERROR(__xludf.DUMMYFUNCTION("""COMPUTED_VALUE"""),"PVS641") -> PVS641 | D9: =IFERROR(__xludf.DUMMYFUNCTION("""COMPUTED_VALUE"""),"FURGON FOTON 1030") -> FURGON FOTON 1030 | E9: =IFERROR(__xludf.DUMMYFUNCTION("""COMPUTED_VALUE"""),46301.0) -> 46301 | F9: =IFERROR(__xludf.DUMMYFUNCTION("""COMPUTED_VALUE"""),46668.0) -> 46668
A10: =IFERROR(__xludf.DUMMYFUNCTION("""COMPUTED_VALUE"""),3273.0) -> 3273 | B10: =IFERROR(__xludf.DUMMYFUNCTION("""COMPUTED_VALUE"""),"02-Medellin") -> 02-Medellin | C10: =IFERROR(__xludf.DUMMYFUNCTION("""COMPUTED_VALUE"""),"PVS639") -> PVS639 | D10: =IFERROR(__xludf.DUMMYFUNCTION("""COMPUTED_VALUE"""),"FURGON FOTON 1030") -> FURGON FOTON 1030 | E10: =IFERROR(__xludf.DUMMYFUNCTION("""COMPUTED_VALUE"""),46301.0) -> 46301 | F10: =IFERROR(__xludf.DUMMYFUNCTION("""COMPUTED_VALUE"""),46668.0) -> 46668
A11: =IFERROR(__xludf.DUMMYFUNCTION("""COMPUTED_VALUE"""),3271.0) -> 3271 | B11: =IFERROR(__xludf.DUMMYFUNCTION("""COMPUTED_VALUE"""),"02-Medellin") -> 02-Medellin | C11: =IFERROR(__xludf.DUMMYFUNCTION("""COMPUTED_VALUE"""),"PVS637") -> PVS637 | D11: =IFERROR(__xludf.DUMMYFUNCTION("""COMPUTED_VALUE"""),"FURGON FOTON 1030") -> FURGON FOTON 1030 | E11: =IFERROR(__xludf.DUMMYFUNCTION("""COMPUTED_VALUE"""),46301.0) -> 46301 | F11: =IFERROR(__xludf.DUMMYFUNCTION("""COMPUTED_VALUE"""),46668.0) -> 46668
A12: =IFERROR(__xludf.DUMMYFUNCTION("""COMPUTED_VALUE"""),3264.0) -> 3264 | B12: =IFERROR(__xludf.DUMMYFUNCTION("""COMPUTED_VALUE"""),"02-Medellin") -> 02-Medellin | C12: =IFERROR(__xludf.DUMMYFUNCTION("""COMPUTED_VALUE"""),"PVS630") -> PVS630 | D12: =IFERROR(__xludf.DUMMYFUNCTION("""COMPUTED_VALUE"""),"FURGON FOTON 1030") -> FURGON FOTON 1030 | E12: =IFERROR(__xludf.DUMMYFUNCTION("""COMPUTED_VALUE"""),46301.0) -> 46301 | F12: =IFERROR(__xludf.DUMMYFUNCTION("""COMPUTED_VALUE"""),46668.0) -> 46668
A13: =IFERROR(__xludf.DUMMYFUNCTION("""COMPUTED_VALUE"""),3256.0) -> 3256 | B13: =IFERROR(__xludf.DUMMYFUNCTION("""COMPUTED_VALUE"""),"02-Medellin") -> 02-Medellin | C13: =IFERROR(__xludf.DUMMYFUNCTION("""COMPUTED_VALUE"""),"PVS622") -> PVS622 | D13: =IFERROR(__xludf.DUMMYFUNCTION("""COMPUTED_VALUE"""),"FURGON FOTON 1030") -> FURGON FOTON 1030 | E13: =IFERROR(__xludf.DUMMYFUNCTION("""COMPUTED_VALUE"""),46301.0) -> 46301 | F13: =IFERROR(__xludf.DUMMYFUNCTION("""COMPUTED_VALUE"""),46668.0) -> 46668
A14: =IFERROR(__xludf.DUMMYFUNCTION("""COMPUTED_VALUE"""),3252.0) -> 3252 | B14: =IFERROR(__xludf.DUMMYFUNCTION("""COMPUTED_VALUE"""),"24-Rionegro") -> 24-Rionegro | C14: =IFERROR(__xludf.DUMMYFUNCTION("""COMPUTED_VALUE"""),"PVS619") -> PVS619 | D14: =IFERROR(__xludf.DUMMYFUNCTION("""COMPUTED_VALUE"""),"FURGON FOTON 1030") -> FURGON FOTON 1030 | E14: =IFERROR(__xludf.DUMMYFUNCTION("""COMPUTED_VALUE"""),46295.0) -> 46295 | F14: =IFERROR(__xludf.DUMMYFUNCTION("""COMPUTED_VALUE"""),46661.0) -> 46661
A15: =IFERROR(__xludf.DUMMYFUNCTION("""COMPUTED_VALUE"""),3251.0) -> 3251 | B15: =IFERROR(__xludf.DUMMYFUNCTION("""COMPUTED_VALUE"""),"24-Rionegro") -> 24-Rionegro | C15: =IFERROR(__xludf.DUMMYFUNCTION("""COMPUTED_VALUE"""),"PVS618") -> PVS618 | D15: =IFERROR(__xludf.DUMMYFUNCTION("""COMPUTED_VALUE"""),"FURGON FOTON 1030") -> FURGON FOTON 1030 | E15: =IFERROR(__xludf.DUMMYFUNCTION("""COMPUTED_VALUE"""),46295.0) -> 46295 | F15: =IFERROR(__xludf.DUMMYFUNCTION("""COMPUTED_VALUE"""),46661.0) -> 46661
A16: =IFERROR(__xludf.DUMMYFUNCTION("""COMPUTED_VALUE"""),3250.0) -> 3250 | B16: =IFERROR(__xludf.DUMMYFUNCTION("""COMPUTED_VALUE"""),"02-Medellin") -> 02-Medellin | C16: =IFERROR(__xludf.DUMMYFUNCTION("""COMPUTED_VALUE"""),"PVS617") -> PVS617 | D16: =IFERROR(__xludf.DUMMYFUNCTION("""COMPUTED_VALUE"""),"FURGON FOTON 1030") -> FURGON FOTON 1030 | E16: =IFERROR(__xludf.DUMMYFUNCTION("""COMPUTED_VALUE"""),46295.0) -> 46295 | F16: =IFERROR(__xludf.DUMMYFUNCTION("""COMPUTED_VALUE"""),46661.0) -> 46661
A17: =IFERROR(__xludf.DUMMYFUNCTION("""COMPUTED_VALUE"""),3249.0) -> 3249 | B17: =IFERROR(__xludf.DUMMYFUNCTION("""COMPUTED_VALUE"""),"02-Medellin") -> 02-Medellin | C17: =IFERROR(__xludf.DUMMYFUNCTION("""COMPUTED_VALUE"""),"PVS616") -> PVS616 | D17: =IFERROR(__xludf.DUMMYFUNCTION("""COMPUTED_VALUE"""),"FURGON FOTON 1030") -> FURGON FOTON 1030 | E17: =IFERROR(__xludf.DUMMYFUNCTION("""COMPUTED_VALUE"""),46295.0) -> 46295 | F17: =IFERROR(__xludf.DUMMYFUNCTION("""COMPUTED_VALUE"""),46661.0) -> 46661
A18: =IFERROR(__xludf.DUMMYFUNCTION("""COMPUTED_VALUE"""),3247.0) -> 3247 | B18: =IFERROR(__xludf.DUMMYFUNCTION("""COMPUTED_VALUE"""),"02-Medellin") -> 02-Medellin | C18: =IFERROR(__xludf.DUMMYFUNCTION("""COMPUTED_VALUE"""),"PVS614") -> PVS614 | D18: =IFERROR(__xludf.DUMMYFUNCTION("""COMPUTED_VALUE"""),"FURGON FOTON 1030") -> FURGON FOTON 1030 | E18: =IFERROR(__xludf.DUMMYFUNCTION("""COMPUTED_VALUE"""),46295.0) -> 46295 | F18: =IFERROR(__xludf.DUMMYFUNCTION("""COMPUTED_VALUE"""),46661.0) -> 46661
A19: =IFERROR(__xludf.DUMMYFUNCTION("""COMPUTED_VALUE"""),3246.0) -> 3246 | B19: =IFERROR(__xludf.DUMMYFUNCTION("""COMPUTED_VALUE"""),"02-Medellin") -> 02-Medellin | C19: =IFERROR(__xludf.DUMMYFUNCTION("""COMPUTED_VALUE"""),"PVS613") -> PVS613 | D19: =IFERROR(__xludf.DUMMYFUNCTION("""COMPUTED_VALUE"""),"FURGON FOTON 1030") -> FURGON FOTON 1030 | E19: =IFERROR(__xludf.DUMMYFUNCTION("""COMPUTED_VALUE"""),46295.0) -> 46295 | F19: =IFERROR(__xludf.DUMMYFUNCTION("""COMPUTED_VALUE"""),46661.0) -> 46661
A20: =IFERROR(__xludf.DUMMYFUNCTION("""COMPUTED_VALUE"""),3241.0) -> 3241 | B20: =IFERROR(__xludf.DUMMYFUNCTION("""COMPUTED_VALUE"""),"02-Medellin") -> 02-Medellin | C20: =IFERROR(__xludf.DUMMYFUNCTION("""COMPUTED_VALUE"""),"PVS608") -> PVS608 | D20: =IFERROR(__xludf.DUMMYFUNCTION("""COMPUTED_VALUE"""),"FURGON FOTON 1030") -> FURGON FOTON 1030 | E20: =IFERROR(__xludf.DUMMYFUNCTION("""COMPUTED_VALUE"""),46295.0) -> 46295 | F20: =IFERROR(__xludf.DUMMYFUNCTION("""COMPUTED_VALUE"""),46661.0) -> 46661
A21: =IFERROR(__xludf.DUMMYFUNCTION("""COMPUTED_VALUE"""),3231.0) -> 3231 | B21: =IFERROR(__xludf.DUMMYFUNCTION("""COMPUTED_VALUE"""),"02-Medellin") -> 02-Medellin | C21: =IFERROR(__xludf.DUMMYFUNCTION("""COMPUTED_VALUE"""),"PVS598") -> PVS598 | D21: =IFERROR(__xludf.DUMMYFUNCTION("""COMPUTED_VALUE"""),"FURGON FOTON 1030") -> FURGON FOTON 1030 | E21: =IFERROR(__xludf.DUMMYFUNCTION("""COMPUTED_VALUE"""),46294.0) -> 46294 | F21: =IFERROR(__xludf.DUMMYFUNCTION("""COMPUTED_VALUE"""),46660.0) -> 46660
A22: =IFERROR(__xludf.DUMMYFUNCTION("""COMPUTED_VALUE"""),3219.0) -> 3219 | B22: =IFERROR(__xludf.DUMMYFUNCTION("""COMPUTED_VALUE"""),"02-Medellin") -> 02-Medellin | C22: =IFERROR(__xludf.DUMMYFUNCTION("""COMPUTED_VALUE"""),"PVS579") -> PVS579 | D22: =IFERROR(__xludf.DUMMYFUNCTION("""COMPUTED_VALUE"""),"FURGON FOTON 1030") -> FURGON FOTON 1030 | E22: =IFERROR(__xludf.DUMMYFUNCTION("""COMPUTED_VALUE"""),46287.0) -> 46287 | F22: =IFERROR(__xludf.DUMMYFUNCTION("""COMPUTED_VALUE"""),46654.0) -> 46654
A23: =IFERROR(__xludf.DUMMYFUNCTION("""COMPUTED_VALUE"""),3216.0) -> 3216 | B23: =IFERROR(__xludf.DUMMYFUNCTION("""COMPUTED_VALUE"""),"02-Medellin") -> 02-Medellin | C23: =IFERROR(__xludf.DUMMYFUNCTION("""COMPUTED_VALUE"""),"PVS576") -> PVS576 | D23: =IFERROR(__xludf.DUMMYFUNCTION("""COMPUTED_VALUE"""),"FURGON FOTON 1030") -> FURGON FOTON 1030 | E23: =IFERROR(__xludf.DUMMYFUNCTION("""COMPUTED_VALUE"""),46287.0) -> 46287 | F23: =IFERROR(__xludf.DUMMYFUNCTION("""COMPUTED_VALUE"""),46654.0) -> 46654
A24: =IFERROR(__xludf.DUMMYFUNCTION("""COMPUTED_VALUE"""),3215.0) -> 3215 | B24: =IFERROR(__xludf.DUMMYFUNCTION("""COMPUTED_VALUE"""),"02-Medellin") -> 02-Medellin | C24: =IFERROR(__xludf.DUMMYFUNCTION("""COMPUTED_VALUE"""),"PVS575") -> PVS575 | D24: =IFERROR(__xludf.DUMMYFUNCTION("""COMPUTED_VALUE"""),"FURGON FOTON 1030") -> FURGON FOTON 1030 | E24: =IFERROR(__xludf.DUMMYFUNCTION("""COMPUTED_VALUE"""),46287.0) -> 46287 | F24: =IFERROR(__xludf.DUMMYFUNCTION("""COMPUTED_VALUE"""),46654.0) -> 46654
A25: =IFERROR(__xludf.DUMMYFUNCTION("""COMPUTED_VALUE"""),3214.0) -> 3214 | B25: =IFERROR(__xludf.DUMMYFUNCTION("""COMPUTED_VALUE"""),"02-Medellin") -> 02-Medellin | C25: =IFERROR(__xludf.DUMMYFUNCTION("""COMPUTED_VALUE"""),"PVS574") -> PVS574 | D25: =IFERROR(__xludf.DUMMYFUNCTION("""COMPUTED_VALUE"""),"FURGON FOTON 1030") -> FURGON FOTON 1030 | E25: =IFERROR(__xludf.DUMMYFUNCTION("""COMPUTED_VALUE"""),46287.0) -> 46287 | F25: =IFERROR(__xludf.DUMMYFUNCTION("""COMPUTED_VALUE"""),46654.0) -> 46654
A26: =IFERROR(__xludf.DUMMYFUNCTION("""COMPUTED_VALUE"""),3213.0) -> 3213 | B26: =IFERROR(__xludf.DUMMYFUNCTION("""COMPUTED_VALUE"""),"02-Medellin") -> 02-Medellin | C26: =IFERROR(__xludf.DUMMYFUNCTION("""COMPUTED_VALUE"""),"PVS573") -> PVS573 | D26: =IFERROR(__xludf.DUMMYFUNCTION("""COMPUTED_VALUE"""),"FURGON FOTON 1030") -> FURGON FOTON 1030 | E26: =IFERROR(__xludf.DUMMYFUNCTION("""COMPUTED_VALUE"""),46287.0) -> 46287 | F26: =IFERROR(__xludf.DUMMYFUNCTION("""COMPUTED_VALUE"""),46654.0) -> 46654
A27: =IFERROR(__xludf.DUMMYFUNCTION("""COMPUTED_VALUE"""),3212.0) -> 3212 | B27: =IFERROR(__xludf.DUMMYFUNCTION("""COMPUTED_VALUE"""),"02-Medellin") -> 02-Medellin | C27: =IFERROR(__xludf.DUMMYFUNCTION("""COMPUTED_VALUE"""),"PVS572") -> PVS572 | D27: =IFERROR(__xludf.DUMMYFUNCTION("""COMPUTED_VALUE"""),"FURGON FOTON 1030") -> FURGON FOTON 1030 | E27: =IFERROR(__xludf.DUMMYFUNCTION("""COMPUTED_VALUE"""),46287.0) -> 46287 | F27: =IFERROR(__xludf.DUMMYFUNCTION("""COMPUTED_VALUE"""),46654.0) -> 46654
A28: =IFERROR(__xludf.DUMMYFUNCTION("""COMPUTED_VALUE"""),3210.0) -> 3210 | B28: =IFERROR(__xludf.DUMMYFUNCTION("""COMPUTED_VALUE"""),"02-Medellin") -> 02-Medellin | C28: =IFERROR(__xludf.DUMMYFUNCTION("""COMPUTED_VALUE"""),"PVS567") -> PVS567 | D28: =IFERROR(__xludf.DUMMYFUNCTION("""COMPUTED_VALUE"""),"FURGON FOTON 1030") -> FURGON FOTON 1030 | E28: =IFERROR(__xludf.DUMMYFUNCTION("""COMPUTED_VALUE"""),46282.0) -> 46282 | F28: =IFERROR(__xludf.DUMMYFUNCTION("""COMPUTED_VALUE"""),46648.0) -> 46648
A29: =IFERROR(__xludf.DUMMYFUNCTION("""COMPUTED_VALUE"""),3209.0) -> 3209 | B29: =IFERROR(__xludf.DUMMYFUNCTION("""COMPUTED_VALUE"""),"02-Medellin") -> 02-Medellin | C29: =IFERROR(__xludf.DUMMYFUNCTION("""COMPUTED_VALUE"""),"PVS566") -> PVS566 | D29: =IFERROR(__xludf.DUMMYFUNCTION("""COMPUTED_VALUE"""),"FURGON FOTON 1030") -> FURGON FOTON 1030
A30: =IFERROR(__xludf.DUMMYFUNCTION("""COMPUTED_VALUE"""),3202.0) -> 3202 | B30: =IFERROR(__xludf.DUMMYFUNCTION("""COMPUTED_VALUE"""),"02-Medellin") -> 02-Medellin | C30: =IFERROR(__xludf.DUMMYFUNCTION("""COMPUTED_VALUE"""),"PVS559") -> PVS559 | D30: =IFERROR(__xludf.DUMMYFUNCTION("""COMPUTED_VALUE"""),"FURGON FOTON 1030") -> FURGON FOTON 1030 | E30: =IFERROR(__xludf.DUMMYFUNCTION("""COMPUTED_VALUE"""),46282.0) -> 46282 | F30: =IFERROR(__xludf.DUMMYFUNCTION("""COMPUTED_VALUE"""),46653.0) -> 46653
A31: =IFERROR(__xludf.DUMMYFUNCTION("""COMPUTED_VALUE"""),3201.0) -> 3201 | B31: =IFERROR(__xludf.DUMMYFUNCTION("""COMPUTED_VALUE"""),"02-Medellin") -> 02-Medellin | C31: =IFERROR(__xludf.DUMMYFUNCTION("""COMPUTED_VALUE"""),"PVS558") -> PVS558 | D31: =IFERROR(__xludf.DUMMYFUNCTION("""COMPUTED_VALUE"""),"FURGON FOTON 1030") -> FURGON FOTON 1030 | E31: =IFERROR(__xludf.DUMMYFUNCTION("""COMPUTED_VALUE"""),46282.0) -> 46282 | F31: =IFERROR(__xludf.DUMMYFUNCTION("""COMPUTED_VALUE"""),46654.0) -> 46654
A32: =IFERROR(__xludf.DUMMYFUNCTION("""COMPUTED_VALUE"""),3200.0) -> 3200 | B32: =IFERROR(__xludf.DUMMYFUNCTION("""COMPUTED_VALUE"""),"02-Medellin") -> 02-Medellin | C32: =IFERROR(__xludf.DUMMYFUNCTION("""COMPUTED_VALUE"""),"PVS557") -> PVS557 | D32: =IFERROR(__xludf.DUMMYFUNCTION("""COMPUTED_VALUE"""),"FURGON FOTON 1030") -> FURGON FOTON 1030 | E32: =IFERROR(__xludf.DUMMYFUNCTION("""COMPUTED_VALUE"""),46282.0) -> 46282 | F32: =IFERROR(__xludf.DUMMYFUNCTION("""COMPUTED_VALUE"""),46654.0) -> 46654
A33: =IFERROR(__xludf.DUMMYFUNCTION("""COMPUTED_VALUE"""),3198.0) -> 3198 | B33: =IFERROR(__xludf.DUMMYFUNCTION("""COMPUTED_VALUE"""),"31-Copacabana") -> 31-Copacabana | C33: =IFERROR(__xludf.DUMMYFUNCTION("""COMPUTED_VALUE"""),"PVS555") -> PVS555 | D33: =IFERROR(__xludf.DUMMYFUNCTION("""COMPUTED_VALUE"""),"FURGON FOTON 1030") -> FURGON FOTON 1030 | E33: =IFERROR(__xludf.DUMMYFUNCTION("""COMPUTED_VALUE"""),46282.0) -> 46282 | F33: =IFERROR(__xludf.DUMMYFUNCTION("""COMPUTED_VALUE"""),46654.0) -> 46654
A34: =IFERROR(__xludf.DUMMYFUNCTION("""COMPUTED_VALUE"""),3197.0) -> 3197 | B34: =IFERROR(__xludf.DUMMYFUNCTION("""COMPUTED_VALUE"""),"02-Medellin") -> 02-Medellin | C34: =IFERROR(__xludf.DUMMYFUNCTION("""COMPUTED_VALUE"""),"PVS554") -> PVS554 | D34: =IFERROR(__xludf.DUMMYFUNCTION("""COMPUTED_VALUE"""),"FURGON FOTON 1030") -> FURGON FOTON 1030 | E34: =IFERROR(__xludf.DUMMYFUNCTION("""COMPUTED_VALUE"""),46282.0) -> 46282 | F34: =IFERROR(__xludf.DUMMYFUNCTION("""COMPUTED_VALUE"""),46653.0) -> 46653
A35: =IFERROR(__xludf.DUMMYFUNCTION("""COMPUTED_VALUE"""),2927.0) -> 2927 | B35: =IFERROR(__xludf.DUMMYFUNCTION("""COMPUTED_VALUE"""),"02-Medellin") -> 02-Medellin | C35: =IFERROR(__xludf.DUMMYFUNCTION("""COMPUTED_VALUE"""),"NNZ367") -> NNZ367 | D35: =IFERROR(__xludf.DUMMYFUNCTION("""COMPUTED_VALUE"""),"FURGON JMC 1054 E VI") -> FURGON JMC 1054 E VI | E35: =IFERROR(__xludf.DUMMYFUNCTION("""COMPUTED_VALUE"""),46316.0) -> 46316 | F35: =IFERROR(__xludf.DUMMYFUNCTION("""COMPUTED_VALUE"""),46318.0) -> 46318
A36: =IFERROR(__xludf.DUMMYFUNCTION("""COMPUTED_VALUE"""),2926.0) -> 2926 | B36: =IFERROR(__xludf.DUMMYFUNCTION("""COMPUTED_VALUE"""),"31-Copacabana") -> 31-Copacabana | C36: =IFERROR(__xludf.DUMMYFUNCTION("""COMPUTED_VALUE"""),"NNZ366") -> NNZ366 | D36: =IFERROR(__xludf.DUMMYFUNCTION("""COMPUTED_VALUE"""),"FURGON JMC 1054 E VI") -> FURGON JMC 1054 E VI | E36: =IFERROR(__xludf.DUMMYFUNCTION("""COMPUTED_VALUE"""),46316.0) -> 46316 | F36: =IFERROR(__xludf.DUMMYFUNCTION("""COMPUTED_VALUE"""),46318.0) -> 46318
A37: =IFERROR(__xludf.DUMMYFUNCTION("""COMPUTED_VALUE"""),2925.0) -> 2925 | B37: =IFERROR(__xludf.DUMMYFUNCTION("""COMPUTED_VALUE"""),"02-Medellin") -> 02-Medellin | C37: =IFERROR(__xludf.DUMMYFUNCTION("""COMPUTED_VALUE"""),"NNZ365") -> NNZ365 | D37: =IFERROR(__xludf.DUMMYFUNCTION("""COMPUTED_VALUE"""),"FURGON JMC 1054 E VI") -> FURGON JMC 1054 E VI | E37: =IFERROR(__xludf.DUMMYFUNCTION("""COMPUTED_VALUE"""),46316.0) -> 46316 | F37: =IFERROR(__xludf.DUMMYFUNCTION("""COMPUTED_VALUE"""),46318.0) -> 46318
A38: =IFERROR(__xludf.DUMMYFUNCTION("""COMPUTED_VALUE"""),2924.0) -> 2924 | B38: =IFERROR(__xludf.DUMMYFUNCTION("""COMPUTED_VALUE"""),"02-Medellin") -> 02-Medellin | C38: =IFERROR(__xludf.DUMMYFUNCTION("""COMPUTED_VALUE"""),"NNZ364") -> NNZ364 | D38: =IFERROR(__xludf.DUMMYFUNCTION("""COMPUTED_VALUE"""),"FURGON JMC 1054 E VI") -> FURGON JMC 1054 E VI | E38: =IFERROR(__xludf.DUMMYFUNCTION("""COMPUTED_VALUE"""),46316.0) -> 46316 | F38: =IFERROR(__xludf.DUMMYFUNCTION("""COMPUTED_VALUE"""),46318.0) -> 46318
A39: =IFERROR(__xludf.DUMMYFUNCTION("""COMPUTED_VALUE"""),2923.0) -> 2923 | B39: =IFERROR(__xludf.DUMMYFUNCTION("""COMPUTED_VALUE"""),"BULTOS") -> BULTOS | C39: =IFERROR(__xludf.DUMMYFUNCTION("""COMPUTED_VALUE"""),"NNZ363") -> NNZ363 | D39: =IFERROR(__xludf.DUMMYFUNCTION("""COMPUTED_VALUE"""),"FURGON JMC 1054 E VI") -> FURGON JMC 1054 E VI | E39: =IFERROR(__xludf.DUMMYFUNCTION("""COMPUTED_VALUE"""),46316.0) -> 46316 | F39: =IFERROR(__xludf.DUMMYFUNCTION("""COMPUTED_VALUE"""),46318.0) -> 46318
A40: =IFERROR(__xludf.DUMMYFUNCTION("""COMPUTED_VALUE"""),2922.0) -> 2922 | B40: =IFERROR(__xludf.DUMMYFUNCTION("""COMPUTED_VALUE"""),"02-Medellin") -> 02-Medellin | C40: =IFERROR(__xludf.DUMMYFUNCTION("""COMPUTED_VALUE"""),"NNZ362") -> NNZ362 | D40: =IFERROR(__xludf.DUMMYFUNCTION("""COMPUTED_VALUE"""),"FURGON JMC 1054 E VI") -> FURGON JMC 1054 E VI | E40: =IFERROR(__xludf.DUMMYFUNCTION("""COMPUTED_VALUE"""),46316.0) -> 46316 | F40: =IFERROR(__xludf.DUMMYFUNCTION("""COMPUTED_VALUE"""),46318.0) -> 46318
A41: =IFERROR(__xludf.DUMMYFUNCTION("""COMPUTED_VALUE"""),2921.0) -> 2921 | B41: =IFERROR(__xludf.DUMMYFUNCTION("""COMPUTED_VALUE"""),"MAYORCA") -> MAYORCA | C41: =IFERROR(__xludf.DUMMYFUNCTION("""COMPUTED_VALUE"""),"NNZ361") -> NNZ361 | D41: =IFERROR(__xludf.DUMMYFUNCTION("""COMPUTED_VALUE"""),"FURGON JMC 1054 E VI") -> FURGON JMC 1054 E VI | E41: =IFERROR(__xludf.DUMMYFUNCTION("""COMPUTED_VALUE"""),46316.0) -> 46316 | F41: =IFERROR(__xludf.DUMMYFUNCTION("""COMPUTED_VALUE"""),46318.0) -> 46318
A42: =IFERROR(__xludf.DUMMYFUNCTION("""COMPUTED_VALUE"""),2920.0) -> 2920 | B42: =IFERROR(__xludf.DUMMYFUNCTION("""COMPUTED_VALUE"""),"31-Copacabana") -> 31-Copacabana | C42: =IFERROR(__xludf.DUMMYFUNCTION("""COMPUTED_VALUE"""),"NNZ360") -> NNZ360 | D42: =IFERROR(__xludf.DUMMYFUNCTION("""COMPUTED_VALUE"""),"FURGON FOTON 1065 E VI") -> FURGON FOTON 1065 E VI | E42: =IFERROR(__xludf.DUMMYFUNCTION("""COMPUTED_VALUE"""),46316.0) -> 46316 | F42: =IFERROR(__xludf.DUMMYFUNCTION("""COMPUTED_VALUE"""),46317.0) -> 46317
A43: =IFERROR(__xludf.DUMMYFUNCTION("""COMPUTED_VALUE"""),2919.0) -> 2919 | B43: =IFERROR(__xludf.DUMMYFUNCTION("""COMPUTED_VALUE"""),"MAYORCA") -> MAYORCA | C43: =IFERROR(__xludf.DUMMYFUNCTION("""COMPUTED_VALUE"""),"NNZ351") -> NNZ351 | D43: =IFERROR(__xludf.DUMMYFUNCTION("""COMPUTED_VALUE"""),"FURGON FOTON 1065 E VI") -> FURGON FOTON 1065 E VI | E43: =IFERROR(__xludf.DUMMYFUNCTION("""COMPUTED_VALUE"""),46302.0) -> 46302 | F43: =IFERROR(__xludf.DUMMYFUNCTION("""COMPUTED_VALUE"""),46303.0) -> 46303
A44: =IFERROR(__xludf.DUMMYFUNCTION("""COMPUTED_VALUE"""),2918.0) -> 2918 | B44: =IFERROR(__xludf.DUMMYFUNCTION("""COMPUTED_VALUE"""),"02-Medellin") -> 02-Medellin | C44: =IFERROR(__xludf.DUMMYFUNCTION("""COMPUTED_VALUE"""),"NNZ350") -> NNZ350 | D44: =IFERROR(__xludf.DUMMYFUNCTION("""COMPUTED_VALUE"""),"FURGON FOTON 1065 E VI") -> FURGON FOTON 1065 E VI | E44: =IFERROR(__xludf.DUMMYFUNCTION("""COMPUTED_VALUE"""),46302.0) -> 46302 | F44: =IFERROR(__xludf.DUMMYFUNCTION("""COMPUTED_VALUE"""),46303.0) -> 46303
A45: =IFERROR(__xludf.DUMMYFUNCTION("""COMPUTED_VALUE"""),2911.0) -> 2911 | B45: =IFERROR(__xludf.DUMMYFUNCTION("""COMPUTED_VALUE"""),"31-Copacabana") -> 31-Copacabana | C45: =IFERROR(__xludf.DUMMYFUNCTION("""COMPUTED_VALUE"""),"NNZ339") -> NNZ339 | D45: =IFERROR(__xludf.DUMMYFUNCTION("""COMPUTED_VALUE"""),"FURGON FOTON 1045 E VI") -> FURGON FOTON 1045 E VI | E45: =IFERROR(__xludf.DUMMYFUNCTION("""COMPUTED_VALUE"""),46274.0) -> 46274 | F45: =IFERROR(__xludf.DUMMYFUNCTION("""COMPUTED_VALUE"""),46275.0) -> 46275
A46: =IFERROR(__xludf.DUMMYFUNCTION("""COMPUTED_VALUE"""),2910.0) -> 2910 | B46: =IFERROR(__xludf.DUMMYFUNCTION("""COMPUTED_VALUE"""),"24-Rionegro") -> 24-Rionegro | C46: =IFERROR(__xludf.DUMMYFUNCTION("""COMPUTED_VALUE"""),"NNZ338") -> NNZ338 | D46: =IFERROR(__xludf.DUMMYFUNCTION("""COMPUTED_VALUE"""),"FURGON FOTON 1045 E VI") -> FURGON FOTON 1045 E VI | E46: =IFERROR(__xludf.DUMMYFUNCTION("""COMPUTED_VALUE"""),46274.0) -> 46274 | F46: =IFERROR(__xludf.DUMMYFUNCTION("""COMPUTED_VALUE"""),46275.0) -> 46275
A47: =IFERROR(__xludf.DUMMYFUNCTION("""COMPUTED_VALUE"""),2909.0) -> 2909 | B47: =IFERROR(__xludf.DUMMYFUNCTION("""COMPUTED_VALUE"""),"02-Medellin") -> 02-Medellin | C47: =IFERROR(__xludf.DUMMYFUNCTION("""COMPUTED_VALUE"""),"NNZ336") -> NNZ336 | D47: =IFERROR(__xludf.DUMMYFUNCTION("""COMPUTED_VALUE"""),"FURGON FOTON 1045 E VI") -> FURGON FOTON 1045 E VI | E47: =IFERROR(__xludf.DUMMYFUNCTION("""COMPUTED_VALUE"""),46274.0) -> 46274 | F47: =IFERROR(__xludf.DUMMYFUNCTION("""COMPUTED_VALUE"""),46275.0) -> 46275
A48: =IFERROR(__xludf.DUMMYFUNCTION("""COMPUTED_VALUE"""),2908.0) -> 2908 | B48: =IFERROR(__xludf.DUMMYFUNCTION("""COMPUTED_VALUE"""),"24-Rionegro") -> 24-Rionegro | C48: =IFERROR(__xludf.DUMMYFUNCTION("""COMPUTED_VALUE"""),"NNZ335") -> NNZ335 | D48: =IFERROR(__xludf.DUMMYFUNCTION("""COMPUTED_VALUE"""),"FURGON FOTON 1045 E VI") -> FURGON FOTON 1045 E VI | E48: =IFERROR(__xludf.DUMMYFUNCTION("""COMPUTED_VALUE"""),46274.0) -> 46274 | F48: =IFERROR(__xludf.DUMMYFUNCTION("""COMPUTED_VALUE"""),46275.0) -> 46275
A49: =IFERROR(__xludf.DUMMYFUNCTION("""COMPUTED_VALUE"""),2907.0) -> 2907 | B49: =IFERROR(__xludf.DUMMYFUNCTION("""COMPUTED_VALUE"""),"38-La ceja") -> 38-La ceja | C49: =IFERROR(__xludf.DUMMYFUNCTION("""COMPUTED_VALUE"""),"NNZ334") -> NNZ334 | D49: =IFERROR(__xludf.DUMMYFUNCTION("""COMPUTED_VALUE"""),"FURGON FOTON 1045 E VI") -> FURGON FOTON 1045 E VI | E49: =IFERROR(__xludf.DUMMYFUNCTION("""COMPUTED_VALUE"""),46274.0) -> 46274 | F49: =IFERROR(__xludf.DUMMYFUNCTION("""COMPUTED_VALUE"""),46275.0) -> 46275
A50: =IFERROR(__xludf.DUMMYFUNCTION("""COMPUTED_VALUE"""),2906.0) -> 2906 | B50: =IFERROR(__xludf.DUMMYFUNCTION("""COMPUTED_VALUE"""),"02-Medellin") -> 02-Medellin | C50: =IFERROR(__xludf.DUMMYFUNCTION("""COMPUTED_VALUE"""),"NNZ333") -> NNZ333 | D50: =IFERROR(__xludf.DUMMYFUNCTION("""COMPUTED_VALUE"""),"FURGON FOTON 1045 E VI") -> FURGON FOTON 1045 E VI | E50: =IFERROR(__xludf.DUMMYFUNCTION("""COMPUTED_VALUE"""),46274.0) -> 46274 | F50: =IFERROR(__xludf.DUMMYFUNCTION("""COMPUTED_VALUE"""),46275.0) -> 46275
A51: =IFERROR(__xludf.DUMMYFUNCTION("""COMPUTED_VALUE"""),2905.0) -> 2905 | B51: =IFERROR(__xludf.DUMMYFUNCTION("""COMPUTED_VALUE"""),"02-Medellin") -> 02-Medellin | C51: =IFERROR(__xludf.DUMMYFUNCTION("""COMPUTED_VALUE"""),"NNZ331") -> NNZ331 | D51: =IFERROR(__xludf.DUMMYFUNCTION("""COMPUTED_VALUE"""),"FURGON FOTON 1045 E VI") -> FURGON FOTON 1045 E VI | E51: =IFERROR(__xludf.DUMMYFUNCTION("""COMPUTED_VALUE"""),46274.0) -> 46274 | F51: =IFERROR(__xludf.DUMMYFUNCTION("""COMPUTED_VALUE"""),46275.0) -> 46275
A52: =IFERROR(__xludf.DUMMYFUNCTION("""COMPUTED_VALUE"""),2904.0) -> 2904 | B52: =IFERROR(__xludf.DUMMYFUNCTION("""COMPUTED_VALUE"""),"02-Medellin") -> 02-Medellin | C52: =IFERROR(__xludf.DUMMYFUNCTION("""COMPUTED_VALUE"""),"NNZ330") -> NNZ330 | D52: =IFERROR(__xludf.DUMMYFUNCTION("""COMPUTED_VALUE"""),"FURGON FOTON 1045 E VI") -> FURGON FOTON 1045 E VI | E52: =IFERROR(__xludf.DUMMYFUNCTION("""COMPUTED_VALUE"""),46274.0) -> 46274 | F52: =IFERROR(__xludf.DUMMYFUNCTION("""COMPUTED_VALUE"""),46275.0) -> 46275
A53: =IFERROR(__xludf.DUMMYFUNCTION("""COMPUTED_VALUE"""),2903.0) -> 2903 | B53: =IFERROR(__xludf.DUMMYFUNCTION("""COMPUTED_VALUE"""),"02-Medellin") -> 02-Medellin | C53: =IFERROR(__xludf.DUMMYFUNCTION("""COMPUTED_VALUE"""),"NNZ329") -> NNZ329 | D53: =IFERROR(__xludf.DUMMYFUNCTION("""COMPUTED_VALUE"""),"FURGON FOTON 1045 E VI") -> FURGON FOTON 1045 E VI | E53: =IFERROR(__xludf.DUMMYFUNCTION("""COMPUTED_VALUE"""),46274.0) -> 46274 | F53: =IFERROR(__xludf.DUMMYFUNCTION("""COMPUTED_VALUE"""),46275.0) -> 46275
A54: =IFERROR(__xludf.DUMMYFUNCTION("""COMPUTED_VALUE"""),2898.0) -> 2898 | B54: =IFERROR(__xludf.DUMMYFUNCTION("""COMPUTED_VALUE"""),"31-Copacabana") -> 31-Copacabana | C54: =IFERROR(__xludf.DUMMYFUNCTION("""COMPUTED_VALUE"""),"NNZ319") -> NNZ319 | D54: =IFERROR(__xludf.DUMMYFUNCTION("""COMPUTED_VALUE"""),"FURGON FOTON 1045 E VI") -> FURGON FOTON 1045 E VI | E54: =IFERROR(__xludf.DUMMYFUNCTION("""COMPUTED_VALUE"""),46239.0) -> 46239 | F54: =IFERROR(__xludf.DUMMYFUNCTION("""COMPUTED_VALUE"""),46242.0) -> 46242
A55: =IFERROR(__xludf.DUMMYFUNCTION("""COMPUTED_VALUE"""),2897.0) -> 2897 | B55: =IFERROR(__xludf.DUMMYFUNCTION("""COMPUTED_VALUE"""),"31-Copacabana QUIMICOS") -> 31-Copacabana QUIMICOS | C55: =IFERROR(__xludf.DUMMYFUNCTION("""COMPUTED_VALUE"""),"NNZ318") -> NNZ318 | D55: =IFERROR(__xludf.DUMMYFUNCTION("""COMPUTED_VALUE"""),"FURGON FOTON 1045 E VI") -> FURGON FOTON 1045 E VI | E55: =IFERROR(__xludf.DUMMYFUNCTION("""COMPUTED_VALUE"""),46239.0) -> 46239 | F55: =IFERROR(__xludf.DUMMYFUNCTION("""COMPUTED_VALUE"""),46242.0) -> 46242
A56: =IFERROR(__xludf.DUMMYFUNCTION("""COMPUTED_VALUE"""),2896.0) -> 2896 | B56: =IFERROR(__xludf.DUMMYFUNCTION("""COMPUTED_VALUE"""),"02-Medellin") -> 02-Medellin | C56: =IFERROR(__xludf.DUMMYFUNCTION("""COMPUTED_VALUE"""),"NNZ317") -> NNZ317 | D56: =IFERROR(__xludf.DUMMYFUNCTION("""COMPUTED_VALUE"""),"FURGON FOTON 1045 E VI") -> FURGON FOTON 1045 E VI | E56: =IFERROR(__xludf.DUMMYFUNCTION("""COMPUTED_VALUE"""),46239.0) -> 46239 | F56: =IFERROR(__xludf.DUMMYFUNCTION("""COMPUTED_VALUE"""),46242.0) -> 46242
A57: =IFERROR(__xludf.DUMMYFUNCTION("""COMPUTED_VALUE"""),2895.0) -> 2895 | B57: =IFERROR(__xludf.DUMMYFUNCTION("""COMPUTED_VALUE"""),"31-Copacabana") -> 31-Copacabana | C57: =IFERROR(__xludf.DUMMYFUNCTION("""COMPUTED_VALUE"""),"NNZ316") -> NNZ316 | D57: =IFERROR(__xludf.DUMMYFUNCTION("""COMPUTED_VALUE"""),"FURGON FOTON 1045 E VI") -> FURGON FOTON 1045 E VI | E57: =IFERROR(__xludf.DUMMYFUNCTION("""COMPUTED_VALUE"""),46239.0) -> 46239 | F57: =IFERROR(__xludf.DUMMYFUNCTION("""COMPUTED_VALUE"""),46242.0) -> 46242
A58: =IFERROR(__xludf.DUMMYFUNCTION("""COMPUTED_VALUE"""),2894.0) -> 2894 | B58: =IFERROR(__xludf.DUMMYFUNCTION("""COMPUTED_VALUE"""),"02-Medellin") -> 02-Medellin | C58: =IFERROR(__xludf.DUMMYFUNCTION("""COMPUTED_VALUE"""),"NNZ315") -> NNZ315 | D58: =IFERROR(__xludf.DUMMYFUNCTION("""COMPUTED_VALUE"""),"FURGON FOTON 1045 E VI") -> FURGON FOTON 1045 E VI | E58: =IFERROR(__xludf.DUMMYFUNCTION("""COMPUTED_VALUE"""),46239.0) -> 46239 | F58: =IFERROR(__xludf.DUMMYFUNCTION("""COMPUTED_VALUE"""),46242.0) -> 46242
A59: =IFERROR(__xludf.DUMMYFUNCTION("""COMPUTED_VALUE"""),2893.0) -> 2893 | B59: =IFERROR(__xludf.DUMMYFUNCTION("""COMPUTED_VALUE"""),"31-Copacabana") -> 31-Copacabana | C59: =IFERROR(__xludf.DUMMYFUNCTION("""COMPUTED_VALUE"""),"NNZ314") -> NNZ314 | D59: =IFERROR(__xludf.DUMMYFUNCTION("""COMPUTED_VALUE"""),"FURGON FOTON 1045 E VI") -> FURGON FOTON 1045 E VI | E59: =IFERROR(__xludf.DUMMYFUNCTION("""COMPUTED_VALUE"""),46239.0) -> 46239 | F59: =IFERROR(__xludf.DUMMYFUNCTION("""COMPUTED_VALUE"""),46242.0) -> 46242
A60: =IFERROR(__xludf.DUMMYFUNCTION("""COMPUTED_VALUE"""),2892.0) -> 2892 | B60: =IFERROR(__xludf.DUMMYFUNCTION("""COMPUTED_VALUE"""),"24-Rionegro") -> 24-Rionegro | C60: =IFERROR(__xludf.DUMMYFUNCTION("""COMPUTED_VALUE"""),"NNZ313") -> NNZ313 | D60: =IFERROR(__xludf.DUMMYFUNCTION("""COMPUTED_VALUE"""),"FURGON FOTON 1045 E VI") -> FURGON FOTON 1045 E VI | E60: =IFERROR(__xludf.DUMMYFUNCTION("""COMPUTED_VALUE"""),46239.0) -> 46239 | F60: =IFERROR(__xludf.DUMMYFUNCTION("""COMPUTED_VALUE"""),46242.0) -> 46242
A61: =IFERROR(__xludf.DUMMYFUNCTION("""COMPUTED_VALUE"""),2891.0) -> 2891 | B61: =IFERROR(__xludf.DUMMYFUNCTION("""COMPUTED_VALUE"""),"31-Copacabana") -> 31-Copacabana | C61: =IFERROR(__xludf.DUMMYFUNCTION("""COMPUTED_VALUE"""),"NNZ312") -> NNZ312 | D61: =IFERROR(__xludf.DUMMYFUNCTION("""COMPUTED_VALUE"""),"FURGON FOTON 1045 E VI") -> FURGON FOTON 1045 E VI | E61: =IFERROR(__xludf.DUMMYFUNCTION("""COMPUTED_VALUE"""),46239.0) -> 46239 | F61: =IFERROR(__xludf.DUMMYFUNCTION("""COMPUTED_VALUE"""),46242.0) -> 46242
A62: =IFERROR(__xludf.DUMMYFUNCTION("""COMPUTED_VALUE"""),2890.0) -> 2890 | B62: =IFERROR(__xludf.DUMMYFUNCTION("""COMPUTED_VALUE"""),"02-Medellin") -> 02-Medellin | C62: =IFERROR(__xludf.DUMMYFUNCTION("""COMPUTED_VALUE"""),"NNZ308") -> NNZ308 | D62: =IFERROR(__xludf.DUMMYFUNCTION("""COMPUTED_VALUE"""),"FURGON FOTON 1065 E VI") -> FURGON FOTON 1065 E VI | E62: =IFERROR(__xludf.DUMMYFUNCTION("""COMPUTED_VALUE"""),46232.0) -> 46232 | F62: =IFERROR(__xludf.DUMMYFUNCTION("""COMPUTED_VALUE"""),46233.0) -> 46233
A63: =IFERROR(__xludf.DUMMYFUNCTION("""COMPUTED_VALUE"""),2889.0) -> 2889 | B63: =IFERROR(__xludf.DUMMYFUNCTION("""COMPUTED_VALUE"""),"31-Copacabana") -> 31-Copacabana | C63: =IFERROR(__xludf.DUMMYFUNCTION("""COMPUTED_VALUE"""),"NNZ307") -> NNZ307 | D63: =IFERROR(__xludf.DUMMYFUNCTION("""COMPUTED_VALUE"""),"FURGON FOTON 1065 E VI") -> FURGON FOTON 1065 E VI | E63: =IFERROR(__xludf.DUMMYFUNCTION("""COMPUTED_VALUE"""),46232.0) -> 46232 | F63: =IFERROR(__xludf.DUMMYFUNCTION("""COMPUTED_VALUE"""),46233.0) -> 46233
A64: =IFERROR(__xludf.DUMMYFUNCTION("""COMPUTED_VALUE"""),2888.0) -> 2888 | B64: =IFERROR(__xludf.DUMMYFUNCTION("""COMPUTED_VALUE"""),"24-Rionegro") -> 24-Rionegro | C64: =IFERROR(__xludf.DUMMYFUNCTION("""COMPUTED_VALUE"""),"NNZ306") -> NNZ306 | D64: =IFERROR(__xludf.DUMMYFUNCTION("""COMPUTED_VALUE"""),"FURGON FOTON 1065 E VI") -> FURGON FOTON 1065 E VI | E64: =IFERROR(__xludf.DUMMYFUNCTION("""COMPUTED_VALUE"""),46232.0) -> 46232 | F64: =IFERROR(__xludf.DUMMYFUNCTION("""COMPUTED_VALUE"""),46233.0) -> 46233
A65: =IFERROR(__xludf.DUMMYFUNCTION("""COMPUTED_VALUE"""),2887.0) -> 2887 | B65: =IFERROR(__xludf.DUMMYFUNCTION("""COMPUTED_VALUE"""),"02-Medellin") -> 02-Medellin | C65: =IFERROR(__xludf.DUMMYFUNCTION("""COMPUTED_VALUE"""),"NNZ305") -> NNZ305 | D65: =IFERROR(__xludf.DUMMYFUNCTION("""COMPUTED_VALUE"""),"FURGON FOTON 1065 E VI") -> FURGON FOTON 1065 E VI | E65: =IFERROR(__xludf.DUMMYFUNCTION("""COMPUTED_VALUE"""),46232.0) -> 46232 | F65: =IFERROR(__xludf.DUMMYFUNCTION("""COMPUTED_VALUE"""),46233.0) -> 46233
A66: =IFERROR(__xludf.DUMMYFUNCTION("""COMPUTED_VALUE"""),2886.0) -> 2886 | B66: =IFERROR(__xludf.DUMMYFUNCTION("""COMPUTED_VALUE"""),"02-Medellin") -> 02-Medellin | C66: =IFERROR(__xludf.DUMMYFUNCTION("""COMPUTED_VALUE"""),"NNZ304") -> NNZ304 | D66: =IFERROR(__xludf.DUMMYFUNCTION("""COMPUTED_VALUE"""),"FURGON FOTON 1065 E VI") -> FURGON FOTON 1065 E VI | E66: =IFERROR(__xludf.DUMMYFUNCTION("""COMPUTED_VALUE"""),46232.0) -> 46232 | F66: =IFERROR(__xludf.DUMMYFUNCTION("""COMPUTED_VALUE"""),46233.0) -> 46233
A67: =IFERROR(__xludf.DUMMYFUNCTION("""COMPUTED_VALUE"""),2885.0) -> 2885 | B67: =IFERROR(__xludf.DUMMYFUNCTION("""COMPUTED_VALUE"""),"MAYORCA") -> MAYORCA | C67: =IFERROR(__xludf.DUMMYFUNCTION("""COMPUTED_VALUE"""),"NNZ303") -> NNZ303 | D67: =IFERROR(__xludf.DUMMYFUNCTION("""COMPUTED_VALUE"""),"FURGON FOTON 1065 E VI") -> FURGON FOTON 1065 E VI | E67: =IFERROR(__xludf.DUMMYFUNCTION("""COMPUTED_VALUE"""),46232.0) -> 46232 | F67: =IFERROR(__xludf.DUMMYFUNCTION("""COMPUTED_VALUE"""),46233.0) -> 46233
A68: =IFERROR(__xludf.DUMMYFUNCTION("""COMPUTED_VALUE"""),2884.0) -> 2884 | B68: =IFERROR(__xludf.DUMMYFUNCTION("""COMPUTED_VALUE"""),"24-Rionegro") -> 24-Rionegro | C68: =IFERROR(__xludf.DUMMYFUNCTION("""COMPUTED_VALUE"""),"NNZ302") -> NNZ302 | D68: =IFERROR(__xludf.DUMMYFUNCTION("""COMPUTED_VALUE"""),"FURGON FOTON 1065 E VI") -> FURGON FOTON 1065 E VI | E68: =IFERROR(__xludf.DUMMYFUNCTION("""COMPUTED_VALUE"""),46232.0) -> 46232 | F68: =IFERROR(__xludf.DUMMYFUNCTION("""COMPUTED_VALUE"""),46233.0) -> 46233
A69: =IFERROR(__xludf.DUMMYFUNCTION("""COMPUTED_VALUE"""),2883.0) -> 2883 | B69: =IFERROR(__xludf.DUMMYFUNCTION("""COMPUTED_VALUE"""),"MAYORCA") -> MAYORCA | C69: =IFERROR(__xludf.DUMMYFUNCTION("""COMPUTED_VALUE"""),"NNZ301") -> NNZ301 | D69: =IFERROR(__xludf.DUMMYFUNCTION("""COMPUTED_VALUE"""),"FURGON FOTON 1065 E VI") -> FURGON FOTON 1065 E VI | E69: =IFERROR(__xludf.DUMMYFUNCTION("""COMPUTED_VALUE"""),46232.0) -> 46232 | F69: =IFERROR(__xludf.DUMMYFUNCTION("""COMPUTED_VALUE"""),46233.0) -> 46233
A70: =IFERROR(__xludf.DUMMYFUNCTION("""COMPUTED_VALUE"""),2882.0) -> 2882 | B70: =IFERROR(__xludf.DUMMYFUNCTION("""COMPUTED_VALUE"""),"38-La ceja") -> 38-La ceja | C70: =IFERROR(__xludf.DUMMYFUNCTION("""COMPUTED_VALUE"""),"NNZ300") -> NNZ300 | D70: =IFERROR(__xludf.DUMMYFUNCTION("""COMPUTED_VALUE"""),"FURGON FOTON 1065 E VI") -> FURGON FOTON 1065 E VI | E70: =IFERROR(__xludf.DUMMYFUNCTION("""COMPUTED_VALUE"""),46232.0) -> 46232 | F70: =IFERROR(__xludf.DUMMYFUNCTION("""COMPUTED_VALUE"""),46233.0) -> 46233
A71: =IFERROR(__xludf.DUMMYFUNCTION("""COMPUTED_VALUE"""),2881.0) -> 2881 | B71: =IFERROR(__xludf.DUMMYFUNCTION("""COMPUTED_VALUE"""),"02-Medellin") -> 02-Medellin | C71: =IFERROR(__xludf.DUMMYFUNCTION("""COMPUTED_VALUE"""),"NNZ296") -> NNZ296 | D71: =IFERROR(__xludf.DUMMYFUNCTION("""COMPUTED_VALUE"""),"CAMION FOTON BJ1128 E VI") -> CAMION FOTON BJ1128 E VI | E71: =IFERROR(__xludf.DUMMYFUNCTION("""COMPUTED_VALUE"""),46221.0) -> 46221 | F71: =IFERROR(__xludf.DUMMYFUNCTION("""COMPUTED_VALUE"""),46226.0) -> 46226
A72: =IFERROR(__xludf.DUMMYFUNCTION("""COMPUTED_VALUE"""),2880.0) -> 2880 | B72: =IFERROR(__xludf.DUMMYFUNCTION("""COMPUTED_VALUE"""),"MAYORCA") -> MAYORCA | C72: =IFERROR(__xludf.DUMMYFUNCTION("""COMPUTED_VALUE"""),"NNZ295") -> NNZ295 | D72: =IFERROR(__xludf.DUMMYFUNCTION("""COMPUTED_VALUE"""),"CAMION FOTON BJ1128 E VI") -> CAMION FOTON BJ1128 E VI | E72: =IFERROR(__xludf.DUMMYFUNCTION("""COMPUTED_VALUE"""),46221.0) -> 46221 | F72: =IFERROR(__xludf.DUMMYFUNCTION("""COMPUTED_VALUE"""),46226.0) -> 46226
A73: =IFERROR(__xludf.DUMMYFUNCTION("""COMPUTED_VALUE"""),2879.0) -> 2879 | B73: =IFERROR(__xludf.DUMMYFUNCTION("""COMPUTED_VALUE"""),"02-Medellin") -> 02-Medellin | C73: =IFERROR(__xludf.DUMMYFUNCTION("""COMPUTED_VALUE"""),"NNZ294") -> NNZ294 | D73: =IFERROR(__xludf.DUMMYFUNCTION("""COMPUTED_VALUE"""),"CAMION FOTON BJ1128 E VI") -> CAMION FOTON BJ1128 E VI | E73: =IFERROR(__xludf.DUMMYFUNCTION("""COMPUTED_VALUE"""),46221.0) -> 46221 | F73: =IFERROR(__xludf.DUMMYFUNCTION("""COMPUTED_VALUE"""),46226.0) -> 46226
A74: =IFERROR(__xludf.DUMMYFUNCTION("""COMPUTED_VALUE"""),2878.0) -> 2878 | B74: =IFERROR(__xludf.DUMMYFUNCTION("""COMPUTED_VALUE"""),"02-Medellin") -> 02-Medellin | C74: =IFERROR(__xludf.DUMMYFUNCTION("""COMPUTED_VALUE"""),"NNZ293") -> NNZ293 | D74: =IFERROR(__xludf.DUMMYFUNCTION("""COMPUTED_VALUE"""),"CAMION FOTON BJ1128 E VI") -> CAMION FOTON BJ1128 E VI | E74: =IFERROR(__xludf.DUMMYFUNCTION("""COMPUTED_VALUE"""),46221.0) -> 46221 | F74: =IFERROR(__xludf.DUMMYFUNCTION("""COMPUTED_VALUE"""),46226.0) -> 46226
A75: =IFERROR(__xludf.DUMMYFUNCTION("""COMPUTED_VALUE"""),2877.0) -> 2877 | B75: =IFERROR(__xludf.DUMMYFUNCTION("""COMPUTED_VALUE"""),"MAYORCA") -> MAYORCA | C75: =IFERROR(__xludf.DUMMYFUNCTION("""COMPUTED_VALUE"""),"NNZ292") -> NNZ292 | D75: =IFERROR(__xludf.DUMMYFUNCTION("""COMPUTED_VALUE"""),"CAMION FOTON BJ1128 E VI") -> CAMION FOTON BJ1128 E VI | E75: =IFERROR(__xludf.DUMMYFUNCTION("""COMPUTED_VALUE"""),46221.0) -> 46221 | F75: =IFERROR(__xludf.DUMMYFUNCTION("""COMPUTED_VALUE"""),46226.0) -> 46226
A76: =IFERROR(__xludf.DUMMYFUNCTION("""COMPUTED_VALUE"""),2876.0) -> 2876 | B76: =IFERROR(__xludf.DUMMYFUNCTION("""COMPUTED_VALUE"""),"02-Medellin") -> 02-Medellin | C76: =IFERROR(__xludf.DUMMYFUNCTION("""COMPUTED_VALUE"""),"NNZ291") -> NNZ291 | D76: =IFERROR(__xludf.DUMMYFUNCTION("""COMPUTED_VALUE"""),"CAMION FOTON BJ1128 E VI") -> CAMION FOTON BJ1128 E VI | E76: =IFERROR(__xludf.DUMMYFUNCTION("""COMPUTED_VALUE"""),46221.0) -> 46221 | F76: =IFERROR(__xludf.DUMMYFUNCTION("""COMPUTED_VALUE"""),46226.0) -> 46226
A77: =IFERROR(__xludf.DUMMYFUNCTION("""COMPUTED_VALUE"""),2875.0) -> 2875 | B77: =IFERROR(__xludf.DUMMYFUNCTION("""COMPUTED_VALUE"""),"02-Medellin") -> 02-Medellin | C77: =IFERROR(__xludf.DUMMYFUNCTION("""COMPUTED_VALUE"""),"NNZ290") -> NNZ290 | D77: =IFERROR(__xludf.DUMMYFUNCTION("""COMPUTED_VALUE"""),"CAMION FOTON BJ1128 E VI") -> CAMION FOTON BJ1128 E VI | E77: =IFERROR(__xludf.DUMMYFUNCTION("""COMPUTED_VALUE"""),46221.0) -> 46221 | F77: =IFERROR(__xludf.DUMMYFUNCTION("""COMPUTED_VALUE"""),46226.0) -> 46226
A78: =IFERROR(__xludf.DUMMYFUNCTION("""COMPUTED_VALUE"""),2867.0) -> 2867 | B78: =IFERROR(__xludf.DUMMYFUNCTION("""COMPUTED_VALUE"""),"02-Medellin") -> 02-Medellin | C78: =IFERROR(__xludf.DUMMYFUNCTION("""COMPUTED_VALUE"""),"NNZ282") -> NNZ282 | D78: =IFERROR(__xludf.DUMMYFUNCTION("""COMPUTED_VALUE"""),"FURGON FOTON 1030") -> FURGON FOTON 1030 | E78: =IFERROR(__xludf.DUMMYFUNCTION("""COMPUTED_VALUE"""),46220.0) -> 46220 | F78: =IFERROR(__xludf.DUMMYFUNCTION("""COMPUTED_VALUE"""),46226.0) -> 46226
A79: =IFERROR(__xludf.DUMMYFUNCTION("""COMPUTED_VALUE"""),2866.0) -> 2866 | B79: =IFERROR(__xludf.DUMMYFUNCTION("""COMPUTED_VALUE"""),"02-Medellin") -> 02-Medellin | C79: =IFERROR(__xludf.DUMMYFUNCTION("""COMPUTED_VALUE"""),"NNZ281") -> NNZ281 | D79: =IFERROR(__xludf.DUMMYFUNCTION("""COMPUTED_VALUE"""),"FURGON FOTON 1030") -> FURGON FOTON 1030 | E79: =IFERROR(__xludf.DUMMYFUNCTION("""COMPUTED_VALUE"""),46219.0) -> 46219 | F79: =IFERROR(__xludf.DUMMYFUNCTION("""COMPUTED_VALUE"""),46221.0) -> 46221
A80: =IFERROR(__xludf.DUMMYFUNCTION("""COMPUTED_VALUE"""),2862.0) -> 2862 | B80: =IFERROR(__xludf.DUMMYFUNCTION("""COMPUTED_VALUE"""),"02-Medellin") -> 02-Medellin | C80: =IFERROR(__xludf.DUMMYFUNCTION("""COMPUTED_VALUE"""),"NNZ276") -> NNZ276 | D80: =IFERROR(__xludf.DUMMYFUNCTION("""COMPUTED_VALUE"""),"FURGON FOTON 1030") -> FURGON FOTON 1030 | E80: =IFERROR(__xludf.DUMMYFUNCTION("""COMPUTED_VALUE"""),46219.0) -> 46219 | F80: =IFERROR(__xludf.DUMMYFUNCTION("""COMPUTED_VALUE"""),46221.0) -> 46221
A81: =IFERROR(__xludf.DUMMYFUNCTION("""COMPUTED_VALUE"""),2861.0) -> 2861 | B81: =IFERROR(__xludf.DUMMYFUNCTION("""COMPUTED_VALUE"""),"02-Medellin") -> 02-Medellin | C81: =IFERROR(__xludf.DUMMYFUNCTION("""COMPUTED_VALUE"""),"NNZ275") -> NNZ275 | D81: =IFERROR(__xludf.DUMMYFUNCTION("""COMPUTED_VALUE"""),"FURGON FOTON 1030") -> FURGON FOTON 1030 | E81: =IFERROR(__xludf.DUMMYFUNCTION("""COMPUTED_VALUE"""),46220.0) -> 46220 | F81: =IFERROR(__xludf.DUMMYFUNCTION("""COMPUTED_VALUE"""),46226.0) -> 46226
A82: =IFERROR(__xludf.DUMMYFUNCTION("""COMPUTED_VALUE"""),2860.0) -> 2860 | B82: =IFERROR(__xludf.DUMMYFUNCTION("""COMPUTED_VALUE"""),"02-Medellin") -> 02-Medellin | C82: =IFERROR(__xludf.DUMMYFUNCTION("""COMPUTED_VALUE"""),"NNZ274") -> NNZ274 | D82: =IFERROR(__xludf.DUMMYFUNCTION("""COMPUTED_VALUE"""),"FURGON FOTON 1030") -> FURGON FOTON 1030 | E82: =IFERROR(__xludf.DUMMYFUNCTION("""COMPUTED_VALUE"""),46219.0) -> 46219 | F82: =IFERROR(__xludf.DUMMYFUNCTION("""COMPUTED_VALUE"""),46221.0) -> 46221
A83: =IFERROR(__xludf.DUMMYFUNCTION("""COMPUTED_VALUE"""),2859.0) -> 2859 | B83: =IFERROR(__xludf.DUMMYFUNCTION("""COMPUTED_VALUE"""),"MAYORCA") -> MAYORCA | C83: =IFERROR(__xludf.DUMMYFUNCTION("""COMPUTED_VALUE"""),"NNZ273") -> NNZ273 | D83: =IFERROR(__xludf.DUMMYFUNCTION("""COMPUTED_VALUE"""),"FURGON FOTON 1030") -> FURGON FOTON 1030 | E83: =IFERROR(__xludf.DUMMYFUNCTION("""COMPUTED_VALUE"""),46220.0) -> 46220 | F83: =IFERROR(__xludf.DUMMYFUNCTION("""COMPUTED_VALUE"""),46226.0) -> 46226
A84: =IFERROR(__xludf.DUMMYFUNCTION("""COMPUTED_VALUE"""),2858.0) -> 2858 | B84: =IFERROR(__xludf.DUMMYFUNCTION("""COMPUTED_VALUE"""),"MAYORCA") -> MAYORCA | C84: =IFERROR(__xludf.DUMMYFUNCTION("""COMPUTED_VALUE"""),"NNZ272") -> NNZ272 | D84: =IFERROR(__xludf.DUMMYFUNCTION("""COMPUTED_VALUE"""),"FURGON FOTON 1065 E VI") -> FURGON FOTON 1065 E VI | E84: =IFERROR(__xludf.DUMMYFUNCTION("""COMPUTED_VALUE"""),46577.0) -> 46577 | F84: =IFERROR(__xludf.DUMMYFUNCTION("""COMPUTED_VALUE"""),46215.0) -> 46215
A85: =IFERROR(__xludf.DUMMYFUNCTION("""COMPUTED_VALUE"""),2857.0) -> 2857 | B85: =IFERROR(__xludf.DUMMYFUNCTION("""COMPUTED_VALUE"""),"24-Rionegro") -> 24-Rionegro | C85: =IFERROR(__xludf.DUMMYFUNCTION("""COMPUTED_VALUE"""),"NNZ271") -> NNZ271 | D85: =IFERROR(__xludf.DUMMYFUNCTION("""COMPUTED_VALUE"""),"FURGON FOTON 1065 E VI") -> FURGON FOTON 1065 E VI | E85: =IFERROR(__xludf.DUMMYFUNCTION("""COMPUTED_VALUE"""),46577.0) -> 46577 | F85: =IFERROR(__xludf.DUMMYFUNCTION("""COMPUTED_VALUE"""),46215.0) -> 46215
A86: =IFERROR(__xludf.DUMMYFUNCTION("""COMPUTED_VALUE"""),2856.0) -> 2856 | B86: =IFERROR(__xludf.DUMMYFUNCTION("""COMPUTED_VALUE"""),"MAYORCA") -> MAYORCA | C86: =IFERROR(__xludf.DUMMYFUNCTION("""COMPUTED_VALUE"""),"NNZ267") -> NNZ267 | D86: =IFERROR(__xludf.DUMMYFUNCTION("""COMPUTED_VALUE"""),"FURGON FOTON 1065 E VI") -> FURGON FOTON 1065 E VI | E86: =IFERROR(__xludf.DUMMYFUNCTION("""COMPUTED_VALUE"""),46578.0) -> 46578 | F86: =IFERROR(__xludf.DUMMYFUNCTION("""COMPUTED_VALUE"""),46215.0) -> 46215
A87: =IFERROR(__xludf.DUMMYFUNCTION("""COMPUTED_VALUE"""),2855.0) -> 2855 | B87: =IFERROR(__xludf.DUMMYFUNCTION("""COMPUTED_VALUE"""),"02-Medellin") -> 02-Medellin | C87: =IFERROR(__xludf.DUMMYFUNCTION("""COMPUTED_VALUE"""),"NNZ265") -> NNZ265 | D87: =IFERROR(__xludf.DUMMYFUNCTION("""COMPUTED_VALUE"""),"FURGON FOTON 1065 E VI") -> FURGON FOTON 1065 E VI | E87: =IFERROR(__xludf.DUMMYFUNCTION("""COMPUTED_VALUE"""),46566.0) -> 46566 | F87: =IFERROR(__xludf.DUMMYFUNCTION("""COMPUTED_VALUE"""),46575.0) -> 46575
A88: =IFERROR(__xludf.DUMMYFUNCTION("""COMPUTED_VALUE"""),2854.0) -> 2854 | B88: =IFERROR(__xludf.DUMMYFUNCTION("""COMPUTED_VALUE"""),"02-Medellin") -> 02-Medellin | C88: =IFERROR(__xludf.DUMMYFUNCTION("""COMPUTED_VALUE"""),"NNZ270") -> NNZ270 | D88: =IFERROR(__xludf.DUMMYFUNCTION("""COMPUTED_VALUE"""),"FURGON FOTON 1065 E VI") -> FURGON FOTON 1065 E VI | E88: =IFERROR(__xludf.DUMMYFUNCTION("""COMPUTED_VALUE"""),46573.0) -> 46573 | F88: =IFERROR(__xludf.DUMMYFUNCTION("""COMPUTED_VALUE"""),46575.0) -> 46575
A89: =IFERROR(__xludf.DUMMYFUNCTION("""COMPUTED_VALUE"""),2853.0) -> 2853 | B89: =IFERROR(__xludf.DUMMYFUNCTION("""COMPUTED_VALUE"""),"BULTOS") -> BULTOS | C89: =IFERROR(__xludf.DUMMYFUNCTION("""COMPUTED_VALUE"""),"NNZ269") -> NNZ269 | D89: =IFERROR(__xludf.DUMMYFUNCTION("""COMPUTED_VALUE"""),"FURGON FOTON 1065 E VI") -> FURGON FOTON 1065 E VI | E89: =IFERROR(__xludf.DUMMYFUNCTION("""COMPUTED_VALUE"""),46573.0) -> 46573 | F89: =IFERROR(__xludf.DUMMYFUNCTION("""COMPUTED_VALUE"""),46576.0) -> 46576
A90: =IFERROR(__xludf.DUMMYFUNCTION("""COMPUTED_VALUE"""),2852.0) -> 2852 | B90: =IFERROR(__xludf.DUMMYFUNCTION("""COMPUTED_VALUE"""),"24-Rionegro") -> 24-Rionegro | C90: =IFERROR(__xludf.DUMMYFUNCTION("""COMPUTED_VALUE"""),"NNZ268") -> NNZ268 | D90: =IFERROR(__xludf.DUMMYFUNCTION("""COMPUTED_VALUE"""),"FURGON FOTON 1065 E VI") -> FURGON FOTON 1065 E VI | E90: =IFERROR(__xludf.DUMMYFUNCTION("""COMPUTED_VALUE"""),46573.0) -> 46573 | F90: =IFERROR(__xludf.DUMMYFUNCTION("""COMPUTED_VALUE"""),46576.0) -> 46576
A91: =IFERROR(__xludf.DUMMYFUNCTION("""COMPUTED_VALUE"""),2851.0) -> 2851 | B91: =IFERROR(__xludf.DUMMYFUNCTION("""COMPUTED_VALUE"""),"02-Medellin") -> 02-Medellin | C91: =IFERROR(__xludf.DUMMYFUNCTION("""COMPUTED_VALUE"""),"NNZ264") -> NNZ264 | D91: =IFERROR(__xludf.DUMMYFUNCTION("""COMPUTED_VALUE"""),"FURGON FOTON 1065 E VI") -> FURGON FOTON 1065 E VI | E91: =IFERROR(__xludf.DUMMYFUNCTION("""COMPUTED_VALUE"""),46566.0) -> 46566 | F91: =IFERROR(__xludf.DUMMYFUNCTION("""COMPUTED_VALUE"""),46569.0) -> 46569
A92: =IFERROR(__xludf.DUMMYFUNCTION("""COMPUTED_VALUE"""),2850.0) -> 2850 | B92: =IFERROR(__xludf.DUMMYFUNCTION("""COMPUTED_VALUE"""),"MAYORCA") -> MAYORCA | C92: =IFERROR(__xludf.DUMMYFUNCTION("""COMPUTED_VALUE"""),"NNZ262") -> NNZ262 | D92: =IFERROR(__xludf.DUMMYFUNCTION("""COMPUTED_VALUE"""),"FURGON FOTON 1065 E VI") -> FURGON FOTON 1065 E VI | E92: =IFERROR(__xludf.DUMMYFUNCTION("""COMPUTED_VALUE"""),46566.0) -> 46566 | F92: =IFERROR(__xludf.DUMMYFUNCTION("""COMPUTED_VALUE"""),46570.0) -> 46570
A93: =IFERROR(__xludf.DUMMYFUNCTION("""COMPUTED_VALUE"""),2849.0) -> 2849 | B93: =IFERROR(__xludf.DUMMYFUNCTION("""COMPUTED_VALUE"""),"24-Rionegro") -> 24-Rionegro | C93: =IFERROR(__xludf.DUMMYFUNCTION("""COMPUTED_VALUE"""),"NNZ261") -> NNZ261 | D93: =IFERROR(__xludf.DUMMYFUNCTION("""COMPUTED_VALUE"""),"FURGON FOTON 1065 E VI") -> FURGON FOTON 1065 E VI | E93: =IFERROR(__xludf.DUMMYFUNCTION("""COMPUTED_VALUE"""),46566.0) -> 46566 | F93: =IFERROR(__xludf.DUMMYFUNCTION("""COMPUTED_VALUE"""),46570.0) -> 46570
A94: =IFERROR(__xludf.DUMMYFUNCTION("""COMPUTED_VALUE"""),2848.0) -> 2848 | B94: =IFERROR(__xludf.DUMMYFUNCTION("""COMPUTED_VALUE"""),"02-Medellin") -> 02-Medellin | C94: =IFERROR(__xludf.DUMMYFUNCTION("""COMPUTED_VALUE"""),"NNZ259") -> NNZ259 | D94: =IFERROR(__xludf.DUMMYFUNCTION("""COMPUTED_VALUE"""),"FURGON FOTON 1065 E VI") -> FURGON FOTON 1065 E VI | E94: =IFERROR(__xludf.DUMMYFUNCTION("""COMPUTED_VALUE"""),46559.0) -> 46559 | F94: =IFERROR(__xludf.DUMMYFUNCTION("""COMPUTED_VALUE"""),46561.0) -> 46561
A95: =IFERROR(__xludf.DUMMYFUNCTION("""COMPUTED_VALUE"""),2847.0) -> 2847 | B95: =IFERROR(__xludf.DUMMYFUNCTION("""COMPUTED_VALUE"""),"31-Copacabana") -> 31-Copacabana | C95: =IFERROR(__xludf.DUMMYFUNCTION("""COMPUTED_VALUE"""),"NNZ258") -> NNZ258 | D95: =IFERROR(__xludf.DUMMYFUNCTION("""COMPUTED_VALUE"""),"FURGON FOTON 1065 E VI") -> FURGON FOTON 1065 E VI | E95: =IFERROR(__xludf.DUMMYFUNCTION("""COMPUTED_VALUE"""),46559.0) -> 46559 | F95: =IFERROR(__xludf.DUMMYFUNCTION("""COMPUTED_VALUE"""),46559.0) -> 46559
A96: =IFERROR(__xludf.DUMMYFUNCTION("""COMPUTED_VALUE"""),2846.0) -> 2846 | B96: =IFERROR(__xludf.DUMMYFUNCTION("""COMPUTED_VALUE"""),"38-La ceja") -> 38-La ceja | C96: =IFERROR(__xludf.DUMMYFUNCTION("""COMPUTED_VALUE"""),"NNZ257") -> NNZ257 | D96: =IFERROR(__xludf.DUMMYFUNCTION("""COMPUTED_VALUE"""),"FURGON FOTON 1065 E VI") -> FURGON FOTON 1065 E VI | E96: =IFERROR(__xludf.DUMMYFUNCTION("""COMPUTED_VALUE"""),46559.0) -> 46559 | F96: =IFERROR(__xludf.DUMMYFUNCTION("""COMPUTED_VALUE"""),46561.0) -> 46561
A97: =IFERROR(__xludf.DUMMYFUNCTION("""COMPUTED_VALUE"""),2845.0) -> 2845 | B97: =IFERROR(__xludf.DUMMYFUNCTION("""COMPUTED_VALUE"""),"02-Medellin") -> 02-Medellin | C97: =IFERROR(__xludf.DUMMYFUNCTION("""COMPUTED_VALUE"""),"NNZ256") -> NNZ256 | D97: =IFERROR(__xludf.DUMMYFUNCTION("""COMPUTED_VALUE"""),"FURGON FOTON 1065 E VI") -> FURGON FOTON 1065 E VI | E97: =IFERROR(__xludf.DUMMYFUNCTION("""COMPUTED_VALUE"""),46559.0) -> 46559 | F97: =IFERROR(__xludf.DUMMYFUNCTION("""COMPUTED_VALUE"""),46561.0) -> 46561
A98: =IFERROR(__xludf.DUMMYFUNCTION("""COMPUTED_VALUE"""),2844.0) -> 2844 | B98: =IFERROR(__xludf.DUMMYFUNCTION("""COMPUTED_VALUE"""),"02-Medellin") -> 02-Medellin | C98: =IFERROR(__xludf.DUMMYFUNCTION("""COMPUTED_VALUE"""),"NNZ254") -> NNZ254 | D98: =IFERROR(__xludf.DUMMYFUNCTION("""COMPUTED_VALUE"""),"FURGON FOTON 1065 E VI") -> FURGON FOTON 1065 E VI | E98: =IFERROR(__xludf.DUMMYFUNCTION("""COMPUTED_VALUE"""),46559.0) -> 46559 | F98: =IFERROR(__xludf.DUMMYFUNCTION("""COMPUTED_VALUE"""),46562.0) -> 46562
A99: =IFERROR(__xludf.DUMMYFUNCTION("""COMPUTED_VALUE"""),2843.0) -> 2843 | B99: =IFERROR(__xludf.DUMMYFUNCTION("""COMPUTED_VALUE"""),"31-Copacabana") -> 31-Copacabana | C99: =IFERROR(__xludf.DUMMYFUNCTION("""COMPUTED_VALUE"""),"NNZ253") -> NNZ253 | D99: =IFERROR(__xludf.DUMMYFUNCTION("""COMPUTED_VALUE"""),"FURGON FOTON 1065 E VI") -> FURGON FOTON 1065 E VI | E99: =IFERROR(__xludf.DUMMYFUNCTION("""COMPUTED_VALUE"""),46559.0) -> 46559 | F99: =IFERROR(__xludf.DUMMYFUNCTION("""COMPUTED_VALUE"""),46562.0) -> 46562
A100: =IFERROR(__xludf.DUMMYFUNCTION("""COMPUTED_VALUE"""),2842.0) -> 2842 | B100: =IFERROR(__xludf.DUMMYFUNCTION("""COMPUTED_VALUE"""),"24-Rionegro") -> 24-Rionegro | C100: =IFERROR(__xludf.DUMMYFUNCTION("""COMPUTED_VALUE"""),"NNZ251") -> NNZ251 | D100: =IFERROR(__xludf.DUMMYFUNCTION("""COMPUTED_VALUE"""),"FURGON FOTON 1065 E VI") -> FURGON FOTON 1065 E VI | E100: =IFERROR(__xludf.DUMMYFUNCTION("""COMPUTED_VALUE"""),46559.0) -> 46559 | F100: =IFERROR(__xludf.DUMMYFUNCTION("""COMPUTED_VALUE"""),46562.0) -> 46562
...

Sheet Q LUB
A1: Móvil | B1: Linea Vehículo | C1: Terminal | D1: Frecuencia KM | E1: Frecuencia Días | F1: Diferencia Días | G1: Diferencia KMs | H1: Fecha de Terminación de la Orden | I1: Fecha Actual | J1: Estado | K1: Orden de Trabajo | L1: KMs último LUB | M1: Última Ubicación
A2: 451 | B2: Tractomula International Eagle 9400 | C2: 98. Ruta Nacional | D2: 30000 | E2: 120 | F2: 1 | G2: 0 | H2: 46211 | I2: 46212 | J2: Vigente | K2: 1162175 | L2: 2235015.8 | M2: 2. Medellin
A3: 461 | B3: Tractomula International Eagle 9400 | C3: 2. Medellin | D3: 30000 | E3: 180 | F3: 119 | G3: 9761.5 | H3: 46093 | I3: 46212 | J3: Vigente | K3: 1152495 | L3: 1275107.8 | M3: 31. Copacabana
A4: 463 | B4: Tractomula International Eagle 9400 | C4: 98. Ruta Nacional | D4: 30000 | E4: 120 | F4: 104 | G4: 29578.6 | H4: 46108 | I4: 46212 | J4: Vigente | K4: 1154436 | L4: 1831940.3 | M4: 2. Medellin
A5: 464 | B5: Tractomula International Eagle 9400 | C5: 2. Medellin | D5: 30000 | E5: 120 | F5: 113 | G5: 6353.4 | H5: 46099 | I5: 46212 | J5: Vigente | K5: 1153642 | L5: 1495074.8 | M5: 24. Rionegro
A6: 467 | B6: Tractomula International Eagle 9400 | C6: 98. Ruta Nacional | D6: 30000 | E6: 120 | F6: 28 | G6: 10279.9 | H6: 46184 | I6: 46212 | J6: Vigente | K6: 1161770 | L6: 1648403.4 | M6: 1. Bogota
A7: 471 | B7: Tractomula International Eagle 9400 | C7: 98. Ruta Nacional | D7: 30000 | E7: 120 | F7: 121 | G7: 40886.2 | H7: 46091 | I7: 46212 | J7: Pasado | K7: 1152656 | L7: 1664739.1 | M7: 6. Bucaramanga
A8: 472 | B8: Tractomula International Eagle 9400 | C8: 2. Medellin | D8: 30000 | E8: 180 | F8: 66 | G8: 7494.5 | H8: 46146 | I8: 46212 | J8: Vigente | K8: 1158352 | L8: 1590122.9 | M8: 24. Rionegro
A9: 473 | B9: Tractomula International Eagle 9400 | C9: 98. Ruta Nacional | D9: 30000 | E9: 120 | F9: 93 | G9: 895 | H9: 46119 | I9: 46212 | J9: Vigente | K9: 1155268 | L9: 1701870.4 | M9: 2. Medellin
A10: 475 | B10: Tractomula International Eagle 9400 | C10: 98. Ruta Nacional | D10: 30000 | E10: 120 | F10: 80 | G10: 17594.3 | H10: 46132 | I10: 46212 | J10: Vigente | K10: 1156745 | L10: 1624460.2 | M10: 4. Pereira
A11: 477 | B11: Tractomula International Eagle 9400 | C11: 98. Ruta Nacional | D11: 30000 | E11: 120 | F11: 35 | G11: 8993.9 | H11: 46177 | I11: 46212 | J11: Vigente | K11: 1161596 | L11: 1587565.9 | M11: 1. Bogota
A12: 478 | B12: Tractomula International Eagle 9400 | C12: 98. Ruta Nacional | D12: 30000 | E12: 120 | F12: 28 | G12: 9439.1 | H12: 46184 | I12: 46212 | J12: Vigente | K12: 1161769 | L12: 1461686.1 | M12: 1. Bogota
A13: 481 | B13: Tractomula International Eagle 9400 | C13: 2. Medellin | D13: 30000 | E13: 180 | F13: 176 | G13: 17198.2 | H13: 46036 | I13: 46212 | J13: Vigente | K13: 1146210 | L13: 1128050.1 | M13: 2. Medellin
... A435: 3284 | B435: Furgon Foton 1030 | C435: 2. Medellin | D435: 5000 | E435: 180 | F435: 134 | G435: 5187 | H435: 46078 | I435: 46212 | J435: Pasado | K435: 1151104 | L435: 4559 | M435: Sin Última Ubicación
A436: 222129 | B436: Tractomula Dongfeng Dfh4250c7 | C436: 98. Ruta Nacional | D436: 0 | E436: 0 | F436: 0 | G436: 0 | H436: - | I436: 46212 | J436: Pendiente | K436: - | L436: 0 | M436: 31. Copacabana
A437: 222134 | B437: Van Citroen Berlingo | C437: 2. Medellin | D437: 0 | E437: 0 | F437: 0 | G437: 0 | H437: - | I437: 46212 | J437: Pendiente | K437: - | L437: 0 | M437: Sin Última Ubicación

Sheet BD LUB
A1: MÓVIL | B1: DESCRIPCIÓN | C1: POBLACIÓN | D1: F ULTIMA LUBRICACIÒN MOTOR | E1: TIEMPO DEL ACEITE | F1: KM DEL ACEITE | G1: FRECUENCIA DIAS | H1: FRECUENCIA KM | I1: PRIORIDAD TIEMPO | J1: PRIORIDAD KM | K1: ESTADO TIEMPO | L1: ESTADO KM | M1: TIEMPO DE PRÓXIMO | N1: KM DE PRÓXIMO
A2: ='RECURSO ACTUAL'!A2 -> 3284 | B2: ='RECURSO ACTUAL'!F2 -> 46668 | C2: ='RECURSO ACTUAL'!B2 -> 02-Medellin | D2: =VLOOKUP(A2,'Q LUB'!A:L,8,FALSE) -> 46078 | E2: =ABS(D2-TODAY()) -> 138 | F2: =VLOOKUP(A2,'Q LUB'!A:L,7,FALSE) -> 5187 | G2: =VLOOKUP(A2,'Q LUB'!A:L,5,FALSE) -> 180 | H2: =VLOOKUP(A2,'Q LUB'!A:L,4,FALSE) -> 5000 | I2: =G2-E2 -> 42 | J2: =H2-F2 -> -187 | K2: =IF(E2>G2,"PASADO",(IF(AND(E2>=G2-$M$2,E2<=G2),"PRÓXIMO","VIGENTE"))) -> VIGENTE | L2: =IF(F2>H2,"PASADO",(IF(AND(F2>=H2-$N$2,F2<=H2),"PRÓXIMO","VIGENTE"))) -> PASADO | M2: 10 | N2: 700
A3: ='RECURSO ACTUAL'!A3 -> 3283 | B3: ='RECURSO ACTUAL'!F3 -> 46668 | C3: ='RECURSO ACTUAL'!B3 -> 02-Medellin | D3: =VLOOKUP(A3,'Q LUB'!A:L,8,FALSE) -> 46062 | E3: =ABS(D3-TODAY()) -> 154 | F3: =VLOOKUP(A3,'Q LUB'!A:L,7,FALSE) -> 6291 | G3: =VLOOKUP(A3,'Q LUB'!A:L,5,FALSE) -> 180 | H3: =VLOOKUP(A3,'Q LUB'!A:L,4,FALSE) -> 5000 | I3: =G3-E3 -> 26 | J3: =H3-F3 -> -1291 | K3: =IF(E3>G3,"PASADO",(IF(AND(E3>=G3-$M$2,E3<=G3),"PRÓXIMO","VIGENTE"))) -> VIGENTE | L3: =IF(F3>H3,"PASADO",(IF(AND(F3>=H3-$N$2,F3<=H3),"PRÓXIMO","VIGENTE"))) -> PASADO
A4: ='RECURSO ACTUAL'!A4 -> 3282 | B4: ='RECURSO ACTUAL'!F4 -> 46668 | C4: ='RECURSO ACTUAL'!B4 -> 02-Medellin | D4: =VLOOKUP(A4,'Q LUB'!A:L,8,FALSE) -> 46086 | E4: =ABS(D4-TODAY()) -> 130 | F4: =VLOOKUP(A4,'Q LUB'!A:L,7,FALSE) -> 5790 | G4: =VLOOKUP(A4,'Q LUB'!A:L,5,FALSE) -> 180 | H4: =VLOOKUP(A4,'Q LUB'!A:L,4,FALSE) -> 5000 | I4: =G4-E4 -> 50 | J4: =H4-F4 -> -790 | K4: =IF(E4>G4,"PASADO",(IF(AND(E4>=G4-$M$2,E4<=G4),"PRÓXIMO","VIGENTE"))) -> VIGENTE | L4: =IF(F4>H4,"PASADO",(IF(AND(F4>=H4-$N$2,F4<=H4),"PRÓXIMO","VIGENTE"))) -> PASADO
A5: ='RECURSO ACTUAL'!A5 -> 3281 | B5: ='RECURSO ACTUAL'!F5 -> 46668 | C5: ='RECURSO ACTUAL'!B5 -> 02-Medellin | D5: =VLOOKUP(A5,'Q LUB'!A:L,8,FALSE) -> 46078 | E5: =ABS(D5-TODAY()) -> 138 | F5: =VLOOKUP(A5,'Q LUB'!A:L,7,FALSE) -> 5415 | G5: =VLOOKUP(A5,'Q LUB'!A:L,5,FALSE) -> 180 | H5: =VLOOKUP(A5,'Q LUB'!A:L,4,FALSE) -> 5000 | I5: =G5-E5 -> 42 | J5: =H5-F5 -> -415 | K5: =IF(E5>G5,"PASADO",(IF(AND(E5>=G5-$M$2,E5<=G5),"PRÓXIMO","VIGENTE"))) -> VIGENTE | L5: =IF(F5>H5,"PASADO",(IF(AND(F5>=H5-$N$2,F5<=H5),"PRÓXIMO","VIGENTE"))) -> PASADO
A6: ='RECURSO ACTUAL'!A6 -> 3280 | B6: ='RECURSO ACTUAL'!F6 -> 46668 | C6: ='RECURSO ACTUAL'!B6 -> 02-Medellin | D6: =VLOOKUP(A6,'Q LUB'!A:L,8,FALSE) -> 46087 | E6: =ABS(D6-TODAY()) -> 129 | F6: =VLOOKUP(A6,'Q LUB'!A:L,7,FALSE) -> 5847 | G6: =VLOOKUP(A6,'Q LUB'!A:L,5,FALSE) -> 180 | H6: =VLOOKUP(A6,'Q LUB'!A:L,4,FALSE) -> 5000 | I6: =G6-E6 -> 51 | J6: =H6-F6 -> -847 | K6: =IF(E6>G6,"PASADO",(IF(AND(E6>=G6-$M$2,E6<=G6),"PRÓXIMO","VIGENTE"))) -> VIGENTE | L6: =IF(F6>H6,"PASADO",(IF(AND(F6>=H6-$N$2,F6<=H6),"PRÓXIMO","VIGENTE"))) -> PASADO
A7: ='RECURSO ACTUAL'!A7 -> 3279 | B7: ='RECURSO ACTUAL'!F7 -> 46668 | C7: ='RECURSO ACTUAL'!B7 -> 02-Medellin | D7: =VLOOKUP(A7,'Q LUB'!A:L,8,FALSE) -> 46126 | E7: =ABS(D7-TODAY()) -> 90 | F7: =VLOOKUP(A7,'Q LUB'!A:L,7,FALSE) -> 3342 | G7: =VLOOKUP(A7,'Q LUB'!A:L,5,FALSE) -> 180 | H7: =VLOOKUP(A7,'Q LUB'!A:L,4,FALSE) -> 5000 | I7: =G7-E7 -> 90 | J7: =H7-F7 -> 1658 | K7: =IF(E7>G7,"PASADO",(IF(AND(E7>=G7-$M$2,E7<=G7),"PRÓXIMO","VIGENTE"))) -> VIGENTE | L7: =IF(F7>H7,"PASADO",(IF(AND(F7>=H7-$N$2,F7<=H7),"PRÓXIMO","VIGENTE"))) -> VIGENTE
A8: ='RECURSO ACTUAL'!A8 -> 3278 | B8: ='RECURSO ACTUAL'!F8 -> 46668 | C8: ='RECURSO ACTUAL'!B8 -> 02-Medellin | D8: =VLOOKUP(A8,'Q LUB'!A:L,8,FALSE) -> 46150 | E8: =ABS(D8-TODAY()) -> 66 | F8: =VLOOKUP(A8,'Q LUB'!A:L,7,FALSE) -> 2440 | G8: =VLOOKUP(A8,'Q LUB'!A:L,5,FALSE) -> 180 | H8: =VLOOKUP(A8,'Q LUB'!A:L,4,FALSE) -> 5000 | I8: =G8-E8 -> 114 | J8: =H8-F8 -> 2560 | K8: =IF(E8>G8,"PASADO",(IF(AND(E8>=G8-$M$2,E8<=G8),"PRÓXIMO","VIGENTE"))) -> VIGENTE | L8: =IF(F8>H8,"PASADO",(IF(AND(F8>=H8-$N$2,F8<=H8),"PRÓXIMO","VIGENTE"))) -> VIGENTE
A9: ='RECURSO ACTUAL'!A9 -> 3275 | B9: ='RECURSO ACTUAL'!F9 -> 46668 | C9: ='RECURSO ACTUAL'!B9 -> 02-Medellin | D9: =VLOOKUP(A9,'Q LUB'!A:L,8,FALSE) -> 46070 | E9: =ABS(D9-TODAY()) -> 146 | F9: =VLOOKUP(A9,'Q LUB'!A:L,7,FALSE) -> 4607 | G9: =VLOOKUP(A9,'Q LUB'!A:L,5,FALSE) -> 180 | H9: =VLOOKUP(A9,'Q LUB'!A:L,4,FALSE) -> 5000 | I9: =G9-E9 -> 34 | J9: =H9-F9 -> 393 | K9: =IF(E9>G9,"PASADO",(IF(AND(E9>=G9-$M$2,E9<=G9),"PRÓXIMO","VIGENTE"))) -> VIGENTE | L9: =IF(F9>H9,"PASADO",(IF(AND(F9>=H9-$N$2,F9<=H9),"PRÓXIMO","VIGENTE"))) -> PRÓXIMO
A10: ='RECURSO ACTUAL'!A10 -> 3273 | B10: ='RECURSO ACTUAL'!F10 -> 46668 | C10: ='RECURSO ACTUAL'!B10 -> 02-Medellin | D10: =VLOOKUP(A10,'Q LUB'!A:L,8,FALSE) -> 46070 | E10: =ABS(D10-TODAY()) -> 146 | F10: =VLOOKUP(A10,'Q LUB'!A:L,7,FALSE) -> 4563 | G10: =VLOOKUP(A10,'Q LUB'!A:L,5,FALSE) -> 180 | H10: =VLOOKUP(A10,'Q LUB'!A:L,4,FALSE) -> 5000 | I10: =G10-E10 -> 34 | J10: =H10-F10 -> 437 | K10: =IF(E10>G10,"PASADO",(IF(AND(E10>=G10-$M$2,E10<=G10),"PRÓXIMO","VIGENTE"))) -> VIGENTE | L10: =IF(F10>H10,"PASADO",(IF(AND(F10>=H10-$N$2,F10<=H10),"PRÓXIMO","VIGENTE"))) -> PRÓXIMO
A11: ='RECURSO ACTUAL'!A11 -> 3271 | B11: ='RECURSO ACTUAL'!F11 -> 46668 | C11: ='RECURSO ACTUAL'!B11 -> 02-Medellin | D11: =VLOOKUP(A11,'Q LUB'!A:L,8,FALSE) -> 46097 | E11: =ABS(D11-TODAY()) -> 119 | F11: =VLOOKUP(A11,'Q LUB'!A:L,7,FALSE) -> 4954 | G11: =VLOOKUP(A11,'Q LUB'!A:L,5,FALSE) -> 180 | H11: =VLOOKUP(A11,'Q LUB'!A:L,4,FALSE) -> 5000 | I11: =G11-E11 -> 61 | J11: =H11-F11 -> 46 | K11: =IF(E11>G11,"PASADO",(IF(AND(E11>=G11-$M$2,E11<=G11),"PRÓXIMO","VIGENTE"))) -> VIGENTE | L11: =IF(F11>H11,"PASADO",(IF(AND(F11>=H11-$N$2,F11<=H11),"PRÓXIMO","VIGENTE"))) -> PRÓXIMO
A12: ='RECURSO ACTUAL'!A12 -> 3264 | B12: ='RECURSO ACTUAL'!F12 -> 46668 | C12: ='RECURSO ACTUAL'!B12 -> 02-Medellin | D12: =VLOOKUP(A12,'Q LUB'!A:L,8,FALSE) -> 46106 | E12: =ABS(D12-TODAY()) -> 110 | F12: =VLOOKUP(A12,'Q LUB'!A:L,7,FALSE) -> 3474 | G12: =VLOOKUP(A12,'Q LUB'!A:L,5,FALSE) -> 180 | H12: =VLOOKUP(A12,'Q LUB'!A:L,4,FALSE) -> 5000 | I12: =G12-E12 -> 70 | J12: =H12-F12 -> 1526 | K12: =IF(E12>G12,"PASADO",(IF(AND(E12>=G12-$M$2,E12<=G12),"PRÓXIMO","VIGENTE"))) -> VIGENTE | L12: =IF(F12>H12,"PASADO",(IF(AND(F12>=H12-$N$2,F12<=H12),"PRÓXIMO","VIGENTE"))) -> VIGENTE
A13: ='RECURSO ACTUAL'!A13 -> 3256 | B13: ='RECURSO ACTUAL'!F13 -> 46668 | C13: ='RECURSO ACTUAL'!B13 -> 02-Medellin | D13: =VLOOKUP(A13,'Q LUB'!A:L,8,FALSE) -> 46128 | E13: =ABS(D13-TODAY()) -> 88 | F13: =VLOOKUP(A13,'Q LUB'!A:L,7,FALSE) -> 3397 | G13: =VLOOKUP(A13,'Q LUB'!A:L,5,FALSE) -> 180 | H13: =VLOOKUP(A13,'Q LUB'!A:L,4,FALSE) -> 5000 | I13: =G13-E13 -> 92 | J13: =H13-F13 -> 1603 | K13: =IF(E13>G13,"PASADO",(IF(AND(E13>=G13-$M$2,E13<=G13),"PRÓXIMO","VIGENTE"))) -> VIGENTE | L13: =IF(F13>H13,"PASADO",(IF(AND(F13>=H13-$N$2,F13<=H13),"PRÓXIMO","VIGENTE"))) -> VIGENTE
A14: ='RECURSO ACTUAL'!A14 -> 3252 | B14: ='RECURSO ACTUAL'!F14 -> 46661 | C14: ='RECURSO ACTUAL'!B14 -> 24-Rionegro | D14: =VLOOKUP(A14,'Q LUB'!A:L,8,FALSE) -> 46161 | E14: =ABS(D14-TODAY()) -> 55 | F14: =VLOOKUP(A14,'Q LUB'!A:L,7,FALSE) -> 2288 | G14: =VLOOKUP(A14,'Q LUB'!A:L,5,FALSE) -> 180 | H14: =VLOOKUP(A14,'Q LUB'!A:L,4,FALSE) -> 5000 | I14: =G14-E14 -> 125 | J14: =H14-F14 -> 2712 | K14: =IF(E14>G14,"PASADO",(IF(AND(E14>=G14-$M$2,E14<=G14),"PRÓXIMO","VIGENTE"))) -> VIGENTE | L14: =IF(F14>H14,"PASADO",(IF(AND(F14>=H14-$N$2,F14<=H14),"PRÓXIMO","VIGENTE"))) -> VIGENTE
... A28: ='RECURSO ACTUAL'!A28 -> 3210 | B28: ='RECURSO ACTUAL'!F28 -> 46648 | C28: ='RECURSO ACTUAL'!B28 -> 02-Medellin | D28: =VLOOKUP(A28,'Q LUB'!A:L,8,FALSE) -> 46147 | E28: =ABS(D28-TODAY()) -> 69 | F28: =VLOOKUP(A28,'Q LUB'!A:L,7,FALSE) -> 2955 | G28: =VLOOKUP(A28,'Q LUB'!A:L,5,FALSE) -> 180 | H28: =VLOOKUP(A28,'Q LUB'!A:L,4,FALSE) -> 5000 | I28: =G28-E28 -> 111 | J28: =H28-F28 -> 2045 | K28: =IF(E28>G28,"PASADO",(IF(AND(E28>=G28-$M$2,E28<=G28),"PRÓXIMO","VIGENTE"))) -> VIGENTE | L28: =IF(F28>H28,"PASADO",(IF(AND(F28>=H28-$N$2,F28<=H28),"PRÓXIMO","VIGENTE"))) -> VIGENTE
A29: ='RECURSO ACTUAL'!A30 -> 3202 | B29: ='RECURSO ACTUAL'!F30 -> 46653 | C29: ='RECURSO ACTUAL'!B30 -> 02-Medellin | D29: =VLOOKUP(A29,'Q LUB'!A:L,8,FALSE) -> 46112 | E29: =ABS(D29-TODAY()) -> 104 | F29: =VLOOKUP(A29,'Q LUB'!A:L,7,FALSE) -> 5377 | G29: =VLOOKUP(A29,'Q LUB'!A:L,5,FALSE) -> 180 | H29: =VLOOKUP(A29,'Q LUB'!A:L,4,FALSE) -> 5000 | I29: =G29-E29 -> 76 | J29: =H29-F29 -> -377 | K29: =IF(E29>G29,"PASADO",(IF(AND(E29>=G29-$M$2,E29<=G29),"PRÓXIMO","VIGENTE"))) -> VIGENTE | L29: =IF(F29>H29,"PASADO",(IF(AND(F29>=H29-$N$2,F29<=H29),"PRÓXIMO","VIGENTE"))) -> PASADO
A30: ='RECURSO ACTUAL'!A31 -> 3201 | B30: ='RECURSO ACTUAL'!F31 -> 46654 | C30: ='RECURSO ACTUAL'!B31 -> 02-Medellin | D30: =VLOOKUP(A30,'Q LUB'!A:L,8,FALSE) -> 46097 | E30: =ABS(D30-TODAY()) -> 119 | F30: =VLOOKUP(A30,'Q LUB'!A:L,7,FALSE) -> 3840 | G30: =VLOOKUP(A30,'Q LUB'!A:L,5,FALSE) -> 180 | H30: =VLOOKUP(A30,'Q LUB'!A:L,4,FALSE) -> 5000 | I30: =G30-E30 -> 61 | J30: =H30-F30 -> 1160 | K30: =IF(E30>G30,"PASADO",(IF(AND(E30>=G30-$M$2,E30<=G30),"PRÓXIMO","VIGENTE"))) -> VIGENTE | L30: =IF(F30>H30,"PASADO",(IF(AND(F30>=H30-$N$2,F30<=H30),"PRÓXIMO","VIGENTE"))) -> VIGENTE
A31: ='RECURSO ACTUAL'!A32 -> 3200 | B31: ='RECURSO ACTUAL'!F32 -> 46654 | C31: ='RECURSO ACTUAL'!B32 -> 02-Medellin | D31: =VLOOKUP(A31,'Q LUB'!A:L,8,FALSE) -> 46091 | E31: =ABS(D31-TODAY()) -> 125 | F31: =VLOOKUP(A31,'Q LUB'!A:L,7,FALSE) -> 4976 | G31: =VLOOKUP(A31,'Q LUB'!A:L,5,FALSE) -> 180 | H31: =VLOOKUP(A31,'Q LUB'!A:L,4,FALSE) -> 5000 | I31: =G31-E31 -> 55 | J31: =H31-F31 -> 24 | K31: =IF(E31>G31,"PASADO",(IF(AND(E31>=G31-$M$2,E31<=G31),"PRÓXIMO","VIGENTE"))) -> VIGENTE | L31: =IF(F31>H31,"PASADO",(IF(AND(F31>=H31-$N$2,F31<=H31),"PRÓXIMO","VIGENTE"))) -> PRÓXIMO
A32: ='RECURSO ACTUAL'!A33 -> 3198 | B32: ='RECURSO ACTUAL'!F33 -> 46654 | C32: ='RECURSO ACTUAL'!B33 -> 31-Copacabana | D32: =VLOOKUP(A32,'Q LUB'!A:L,8,FALSE) -> 46062 | E32: =ABS(D32-TODAY()) -> 154 | F32: =VLOOKUP(A32,'Q LUB'!A:L,7,FALSE) -> 5962 | G32: =VLOOKUP(A32,'Q LUB'!A:L,5,FALSE) -> 180 | H32: =VLOOKUP(A32,'Q LUB'!A:L,4,FALSE) -> 5000 | I32: =G32-E32 -> 26 | J32: =H32-F32 -> -962 | K32: =IF(E32>G32,"PASADO",(IF(AND(E32>=G32-$M$2,E32<=G32),"PRÓXIMO","VIGENTE"))) -> VIGENTE | L32: =IF(F32>H32,"PASADO",(IF(AND(F32>=H32-$N$2,F32<=H32),"PRÓXIMO","VIGENTE"))) -> PASADO
A33: ='RECURSO ACTUAL'!A34 -> 3197 | B33: ='RECURSO ACTUAL'!F34 -> 46653 | C33: ='RECURSO ACTUAL'!B34 -> 02-Medellin | D33: =VLOOKUP(A33,'Q LUB'!A:L,8,FALSE) -> 46078 | E33: =ABS(D33-TODAY()) -> 138 | F33: =VLOOKUP(A33,'Q LUB'!A:L,7,FALSE) -> 4369 | G33: =VLOOKUP(A33,'Q LUB'!A:L,5,FALSE) -> 180 | H33: =VLOOKUP(A33,'Q LUB'!A:L,4,FALSE) -> 5000 | I33: =G33-E33 -> 42 | J33: =H33-F33 -> 631 | K33: =IF(E33>G33,"PASADO",(IF(AND(E33>=G33-$M$2,E33<=G33),"PRÓXIMO","VIGENTE"))) -> VIGENTE | L33: =IF(F33>H33,"PASADO",(IF(AND(F33>=H33-$N$2,F33<=H33),"PRÓXIMO","VIGENTE"))) -> PRÓXIMO
A34: ='RECURSO ACTUAL'!A35 -> 2927 | B34: ='RECURSO ACTUAL'!F35 -> 46318 | C34: ='RECURSO ACTUAL'!B35 -> 02-Medellin | D34: =VLOOKUP(A34,'Q LUB'!A:L,8,FALSE) -> 46070 | E34: =ABS(D34-TODAY()) -> 146 | F34: =VLOOKUP(A34,'Q LUB'!A:L,7,FALSE) -> 4990 | G34: =VLOOKUP(A34,'Q LUB'!A:L,5,FALSE) -> 180 | H34: =VLOOKUP(A34,'Q LUB'!A:L,4,FALSE) -> 5000 | I34: =G34-E34 -> 34 | J34: =H34-F34 -> 10 | K34: =IF(E34>G34,"PASADO",(IF(AND(E34>=G34-$M$2,E34<=G34),"PRÓXIMO","VIGENTE"))) -> VIGENTE | L34: =IF(F34>H34,"PASADO",(IF(AND(F34>=H34-$N$2,F34<=H34),"PRÓXIMO","VIGENTE"))) -> PRÓXIMO
A35: ='RECURSO ACTUAL'!A36 -> 2926 | B35: ='RECURSO ACTUAL'!F36 -> 46318 | C35: ='RECURSO ACTUAL'!B36 -> 31-Copacabana | D35: =VLOOKUP(A35,'Q LUB'!A:L,8,FALSE) -> 46101 | E35: =ABS(D35-TODAY()) -> 115 | F35: =VLOOKUP(A35,'Q LUB'!A:L,7,FALSE) -> 4791 | G35: =VLOOKUP(A35,'Q LUB'!A:L,5,FALSE) -> 180 | H35: =VLOOKUP(A35,'Q LUB'!A:L,4,FALSE) -> 5000 | I35: =G35-E35 -> 65 | J35: =H35-F35 -> 209 | K35: =IF(E35>G35,"PASADO",(IF(AND(E35>=G35-$M$2,E35<=G35),"PRÓXIMO","VIGENTE"))) -> VIGENTE | L35: =IF(F35>H35,"PASADO",(IF(AND(F35>=H35-$N$2,F35<=H35),"PRÓXIMO","VIGENTE"))) -> PRÓXIMO
A36: ='RECURSO ACTUAL'!A37 -> 2925 | B36: ='RECURSO ACTUAL'!F37 -> 46318 | C36: ='RECURSO ACTUAL'!B37 -> 02-Medellin | D36: =VLOOKUP(A36,'Q LUB'!A:L,8,FALSE) -> 46087 | E36: =ABS(D36-TODAY()) -> 129 | F36: =VLOOKUP(A36,'Q LUB'!A:L,7,FALSE) -> 5412 | G36: =VLOOKUP(A36,'Q LUB'!A:L,5,FALSE) -> 180 | H36: =VLOOKUP(A36,'Q LUB'!A:L,4,FALSE) -> 5000 | I36: =G36-E36 -> 51 | J36: =H36-F36 -> -412 | K36: =IF(E36>G36,"PASADO",(IF(AND(E36>=G36-$M$2,E36<=G36),"PRÓXIMO","VIGENTE"))) -> VIGENTE | L36: =IF(F36>H36,"PASADO",(IF(AND(F36>=H36-$N$2,F36<=H36),"PRÓXIMO","VIGENTE"))) -> PASADO
A37: ='RECURSO ACTUAL'!A38 -> 2924 | B37: ='RECURSO ACTUAL'!F38 -> 46318 | C37: ='RECURSO ACTUAL'!B38 -> 02-Medellin | D37: =VLOOKUP(A37,'Q LUB'!A:L,8,FALSE) -> 46155 | E37: =ABS(D37-TODAY()) -> 61 | F37: =VLOOKUP(A37,'Q LUB'!A:L,7,FALSE) -> 2198 | G37: =VLOOKUP(A37,'Q LUB'!A:L,5,FALSE) -> 180 | H37: =VLOOKUP(A37,'Q LUB'!A:L,4,FALSE) -> 5000 | I37: =G37-E37 -> 119 | J37: =H37-F37 -> 2802 | K37: =IF(E37>G37,"PASADO",(IF(AND(E37>=G37-$M$2,E37<=G37),"PRÓXIMO","VIGENTE"))) -> VIGENTE | L37: =IF(F37>H37,"PASADO",(IF(AND(F37>=H37-$N$2,F37<=H37),"PRÓXIMO","VIGENTE"))) -> VIGENTE
A38: ='RECURSO ACTUAL'!A39 -> 2923 | B38: ='RECURSO ACTUAL'!F39 -> 46318 | C38: ='RECURSO ACTUAL'!B39 -> BULTOS | D38: =VLOOKUP(A38,'Q LUB'!A:L,8,FALSE) -> 46135 | E38: =ABS(D38-TODAY()) -> 81 | F38: =VLOOKUP(A38,'Q LUB'!A:L,7,FALSE) -> 5969 | G38: =VLOOKUP(A38,'Q LUB'!A:L,5,FALSE) -> 180 | H38: =VLOOKUP(A38,'Q LUB'!A:L,4,FALSE) -> 5000 | I38: =G38-E38 -> 99 | J38: =H38-F38 -> -969 | K38: =IF(E38>G38,"PASADO",(IF(AND(E38>=G38-$M$2,E38<=G38),"PRÓXIMO","VIGENTE"))) -> VIGENTE | L38: =IF(F38>H38,"PASADO",(IF(AND(F38>=H38-$N$2,F38<=H38),"PRÓXIMO","VIGENTE"))) -> PASADO
A39: ='RECURSO ACTUAL'!A40 -> 2922 | B39: ='RECURSO ACTUAL'!F40 -> 46318 | C39: ='RECURSO ACTUAL'!B40 -> 02-Medellin | D39: =VLOOKUP(A39,'Q LUB'!A:L,8,FALSE) -> 46062 | E39: =ABS(D39-TODAY()) -> 154 | F39: =VLOOKUP(A39,'Q LUB'!A:L,7,FALSE) -> 4383 | G39: =VLOOKUP(A39,'Q LUB'!A:L,5,FALSE) -> 180 | H39: =VLOOKUP(A39,'Q LUB'!A:L,4,FALSE) -> 5000 | I39: =G39-E39 -> 26 | J39: =H39-F39 -> 617 | K39: =IF(E39>G39,"PASADO",(IF(AND(E39>=G39-$M$2,E39<=G39),"PRÓXIMO","VIGENTE"))) -> VIGENTE | L39: =IF(F39>H39,"PASADO",(IF(AND(F39>=H39-$N$2,F39<=H39),"PRÓXIMO","VIGENTE"))) -> PRÓXIMO
A40: ='RECURSO ACTUAL'!A41 -> 2921 | B40: ='RECURSO ACTUAL'!F41 -> 46318 | C40: ='RECURSO ACTUAL'!B41 -> MAYORCA | D40: =VLOOKUP(A40,'Q LUB'!A:L,8,FALSE) -> 46056 | E40: =ABS(D40-TODAY()) -> 160 | F40: =VLOOKUP(A40,'Q LUB'!A:L,7,FALSE) -> 4653 | G40: =VLOOKUP(A40,'Q LUB'!A:L,5,FALSE) -> 180 | H40: =VLOOKUP(A40,'Q LUB'!A:L,4,FALSE) -> 5000 | I40: =G40-E40 -> 20 | J40: =H40-F40 -> 347 | K40: =IF(E40>G40,"PASADO",(IF(AND(E40>=G40-$M$2,E40<=G40),"PRÓXIMO","VIGENTE"))) -> VIGENTE | L40: =IF(F40>H40,"PASADO",(IF(AND(F40>=H40-$N$2,F40<=H40),"PRÓXIMO","VIGENTE"))) -> PRÓXIMO
... A223: ='RECURSO ACTUAL'!A224 | B223: ='RECURSO ACTUAL'!F224 | C223: ='RECURSO ACTUAL'!B224 | D223: =VLOOKUP(A223,'Q LUB'!A:L,8,FALSE) -> #N/A | E223: =ABS(D223-TODAY()) -> #N/A | F223: =VLOOKUP(A223,'Q LUB'!A:L,7,FALSE) -> #N/A | G223: =VLOOKUP(A223,'Q LUB'!A:L,5,FALSE) -> #N/A | H223: =VLOOKUP(A223,'Q LUB'!A:L,4,FALSE) -> #N/A | I223: =G223-E223 -> #N/A | J223: =H223-F223 -> #N/A | K223: =IF(E223>G223,"PASADO",(IF(AND(E223>=G223-$M$2,E223<=G223),"PRÓXIMO","VIGENTE"))) -> #N/A | L223: =IF(F223>H223,"PASADO",(IF(AND(F223>=H223-$N$2,F223<=H223),"PRÓXIMO","VIGENTE"))) -> #N/A
A224: ='RECURSO ACTUAL'!A226
A225: ='RECURSO ACTUAL'!A227
A226: ='RECURSO ACTUAL'!A228
A227: ='RECURSO ACTUAL'!A229
A228: ='RECURSO ACTUAL'!A230
A229: ='RECURSO ACTUAL'!A231
A230: ='RECURSO ACTUAL'!A232
A231: ='RECURSO ACTUAL'!A233
A232: ='RECURSO ACTUAL'!A234
A233: ='RECURSO ACTUAL'!A235
A234: ='RECURSO ACTUAL'!A236
A235: ='RECURSO ACTUAL'!A237
... A248: ='RECURSO ACTUAL'!A250

Sheet Q MPP
A1: Móvil | B1: Linea Vehículo | C1: Terminal | D1: Frecuencia KM | E1: Frecuencia Días | F1: Diferencia Días | G1: Diferencia KMs | H1: Fecha de Terminación de la Orden | I1: Fecha Actual | J1: Estado | K1: Orden de Trabajo | L1: KMs último MPP | M1: Última Ubicación
A2: 451 | B2: Tractomula International Eagle 9400 | C2: 98. Ruta Nacional | D2: 10000 | E2: 90 | F2: 23 | G2: 8810.3 | H2: 46189 | I2: 46212 | J2: Vigente | K2: 1161824 | L2: 2226205.5 | M2: 2. Medellin
A3: 461 | B3: Tractomula International Eagle 9400 | C3: 2. Medellin | D3: 10000 | E3: 90 | F3: 86 | G3: 8013.7 | H3: 46126 | I3: 46212 | J3: Vigente | K3: 1156100 | L3: 1276855.6 | M3: 31. Copacabana
A4: 463 | B4: Tractomula International Eagle 9400 | C4: 98. Ruta Nacional | D4: 10000 | E4: 60 | F4: 56 | G4: 15920.8 | H4: 46156 | I4: 46212 | J4: Pasado | K4: 1159885 | L4: 1845598 | M4: 2. Medellin
A5: 464 | B5: Tractomula International Eagle 9400 | C5: 2. Medellin | D5: 10000 | E5: 90 | F5: 142 | G5: 8507.3 | H5: 46070 | I5: 46212 | J5: Pasado | K5: 1150098 | L5: 1492920.9 | M5: 24. Rionegro
A6: 467 | B6: Tractomula International Eagle 9400 | C6: 98. Ruta Nacional | D6: 10000 | E6: 60 | F6: 87 | G6: 32986.2 | H6: 46125 | I6: 46212 | J6: Pasado | K6: 1155919 | L6: 1625697.1 | M6: 1. Bogota
A7: 471 | B7: Tractomula International Eagle 9400 | C7: 98. Ruta Nacional | D7: 10000 | E7: 60 | F7: 21 | G7: 7086 | H7: 46191 | I7: 46212 | J7: Vigente | K7: 1161863 | L7: 1698539.3 | M7: 6. Bucaramanga
A8: 472 | B8: Tractomula International Eagle 9400 | C8: 2. Medellin | D8: 10000 | E8: 90 | F8: 55 | G8: 5692.9 | H8: 46157 | I8: 46212 | J8: Vigente | K8: 1159975 | L8: 1591924.5 | M8: 24. Rionegro
A9: 473 | B9: Tractomula International Eagle 9400 | C9: 98. Ruta Nacional | D9: 10000 | E9: 60 | F9: 147 | G9: 18755.9 | H9: 46065 | I9: 46212 | J9: Pasado | K9: 1149531 | L9: 1684009.6 | M9: 2. Medellin
A10: 475 | B10: Tractomula International Eagle 9400 | C10: 98. Ruta Nacional | D10: 10000 | E10: 60 | F10: 84 | G10: 19149.4 | H10: 46128 | I10: 46212 | J10: Pasado | K10: 1156406 | L10: 1622905.2 | M10: 4. Pereira
A11: 477 | B11: Tractomula International Eagle 9400 | C11: 98. Ruta Nacional | D11: 10000 | E11: 60 | F11: 16 | G11: 4156.7 | H11: 46196 | I11: 46212 | J11: Vigente | K11: 1161933 | L11: 1592403.1 | M11: 1. Bogota
A12: 478 | B12: Tractomula International Eagle 9400 | C12: 98. Ruta Nacional | D12: 10000 | E12: 60 | F12: 30 | G12: 10476.6 | H12: 46182 | I12: 46212 | J12: Pasado | K12: 1161695 | L12: 1460648.6 | M12: 1. Bogota
A13: 481 | B13: Tractomula International Eagle 9400 | C13: 2. Medellin | D13: 10000 | E13: 90 | F13: 56 | G13: 5912.6 | H13: 46156 | I13: 46212 | J13: Vigente | K13: 1159896 | L13: 1139335.7 | M13: 2. Medellin
... A435: 3284 | B435: Furgon Foton 1030 | C435: 2. Medellin | D435: 5000 | E435: 90 | F435: 65 | G435: 2493 | H435: 46147 | I435: 46212 | J435: Vigente | K435: 1158481 | L435: 7253 | M435: Sin Última Ubicación
A436: 222129 | B436: Tractomula Dongfeng Dfh4250c7 | C436: 98. Ruta Nacional | D436: 0 | E436: 0 | F436: 0 | G436: 0 | H436: - | I436: 46212 | J436: Pendiente | K436: - | L436: 0 | M436: 31. Copacabana
A437: 222134 | B437: Van Citroen Berlingo | C437: 2. Medellin | D437: 0 | E437: 0 | F437: 0 | G437: 0 | H437: - | I437: 46212 | J437: Pendiente | K437: - | L437: 0 | M437: Sin Última Ubicación

Sheet LUBRICACION
B2: LUBRICACIÒN MOTOR POR TIEMPO | K2: LUBRICACIÒN MOTOR POR KM | T2: GESTIÓN LUB | AJ2: LUBRICACIÒN CAJA Y TRA POR TIEMPO | AP2: LUBRICACIÒN CAJA Y TRA POR KM | AV2: LUBRICACIÒN CAJA Y TRA POR TIEMPO
B3: ORDEN | C3: MÓVIL | D3: DESCRIPCIÓN | E3: POBLACIÓN | F3: FECHA ULT LUB | G3: ORDEN PRIORIDAD | H3: ESTADO | I3: ESTADO GESTIÓN | K3: ORDEN | L3: MÓVIL | M3: DESCRIPCIÓN | N3: POBLACIÓN | O3: FECHA ULT LUB | P3: ORDEN PRIORIDAD | Q3: ESTADO | R3: ESTADO GESTIÓN | T3: HECHOS | U3: PEDIDOS | W3: PROPORCIÓN | AJ3: ORDEN | AK3: =IFERROR(__xludf.DUMMYFUNCTION("QUERY('BD LUB'!A1:S58,""SELECT B,C,E,N ORDER BY E DESC"",1)"),"DESCRIPCIÓN") -> DESCRIPCIÓN | AL3: =IFERROR(__xludf.DUMMYFUNCTION("""COMPUTED_VALUE"""),"POBLACIÓN") -> POBLACIÓN | AM3: =IFERROR(__xludf.DUMMYFUNCTION("""COMPUTED_VALUE"""),"TIEMPO DEL ACEITE") -> TIEMPO DEL ACEITE | AN3: =IFERROR(__xludf.DUMMYFUNCTION("""COMPUTED_VALUE"""),"KM DE PRÓXIMO") -> KM DE PRÓXIMO | AP3: ORDEN | AQ3: =IFERROR(__xludf.DUMMYFUNCTION("QUERY('BD LUB'!A1:S58,""SELECT B,C,E,N ORDER BY E DESC"",1)"),"DESCRIPCIÓN") -> DESCRIPCIÓN | AR3: =IFERROR(__xludf.DUMMYFUNCTION("""COMPUTED_VALUE"""),"POBLACIÓN") -> POBLACIÓN | AS3: =IFERROR(__xludf.DUMMYFUNCTION("""COMPUTED_VALUE"""),"TIEMPO DEL ACEITE") -> TIEMPO DEL ACEITE | AT3: =IFERROR(__xludf.DUMMYFUNCTION("""COMPUTED_VALUE"""),"KM DE PRÓXIMO") -> KM DE PRÓXIMO | AV3: ORDEN | AW3: =IFERROR(__xludf.DUMMYFUNCTION("QUERY('BD LUB'!R1:AE58,""SELECT B,C,E,N ORDER BY E DESC"",1)"),"#VALUE!") -> #VALUE!
B4: 1 | C4: =IFERROR(__xludf.DUMMYFUNCTION("QUERY('BD LUB'!$A$2:$L$223,""SELECT A,B,C,D,I,K ORDER BY I ASC"")"),982.0) -> 982 | D4: =IFERROR(__xludf.DUMMYFUNCTION("""COMPUTED_VALUE"""),46551.0) -> 46551 | E4: =IFERROR(__xludf.DUMMYFUNCTION("""COMPUTED_VALUE"""),"02-Medellin") -> 02-Medellin | H4: =IFERROR(__xludf.DUMMYFUNCTION("""COMPUTED_VALUE"""),"#N/A") -> #N/A | I4: =IF(OR(H4="PASADO",H4="PRÓXIMO"), IF(AND(NOT(ISERROR(MATCH(C4,$T$4:$T$195,0))),NOT(ISERROR(MATCH(C4,$U$4:$U$195,0)))),"HECHO",IF(NOT(ISERROR(MATCH(C4,$U$4:$U$195,0))),"PEDIDO","NO PEDIDO")),"-") -> - | K4: 1 | L4: =IFERROR(__xludf.DUMMYFUNCTION("QUERY('BD LUB'!$A$2:$L$223,""SELECT A,B,C,D,J,L ORDER BY J ASC"")"),982.0) -> 982 | M4: =IFERROR(__xludf.DUMMYFUNCTION("""COMPUTED_VALUE"""),46551.0) -> 46551 | N4: =IFERROR(__xludf.DUMMYFUNCTION("""COMPUTED_VALUE"""),"02-Medellin") -> 02-Medellin | Q4: =IFERROR(__xludf.DUMMYFUNCTION("""COMPUTED_VALUE"""),"#N/A") -> #N/A | T4: =CALENDARIO!D16 -> 2425 | U4: =CALENDARIO!C16 -> 2880 | W4: =IFERROR(__xludf.DUMMYFUNCTION("FLATTEN(QUERY(LUBRICACION!C8:I225,""SELECT C WHERE I='NO PEDIDO' ""),QUERY(LUBRICACION!L8:R225,""SELECT L WHERE R='NO PEDIDO'""))"),495.0) -> 495 | X4: =(VLOOKUP(W4,'BD LUB'!$A$2:$L$223,5,FALSE)/VLOOKUP(W4,'BD LUB'!$A$2:$L$223,7,FALSE))+(VLOOKUP(W4,'BD LUB'!$A$2:$L$223,6,FALSE)/VLOOKUP(W4,'BD LUB'!$A$2:$L$223,8,FALSE)) -> 1.5310456 | Y4: =IF(AND(VLOOKUP(W4,'BD LUB'!$A$2:$L$223,11,FALSE)="PASADO",VLOOKUP(W4,'BD LUB'!$A$2:$L$223,12,FALSE)="PASADO"),1,IF(OR(AND(VLOOKUP(W4,'BD LUB'!$A$2:$L$223,11,FALSE)="PASADO",VLOOKUP(W4,'BD LUB'!$A$2:$L$223,12,FALSE)="PRÓXIMO"),AND(VLOOKUP(W4,'BD LUB'!$A$2:$L$223,11,FALSE)="PRÓXIMO",VLOOKUP(W4,'BD LUB'!$A$2:$L$223,12,FALSE)="PASADO")),2,IF(OR(AND(VLOOKUP(W4,'BD LUB'!$A$2:$L$223,11,FALSE)="PASADO",VLOOKUP(W4,'BD LUB'!$A$2:$L$223,12,FALSE)="VIGENTE"),AND(VLOOKUP(W4,'BD LUB'!$A$2:$L$223,11,FALSE)="VIGENTE",VLOOKUP(W4,'BD LUB'!$A$2:$L$223,12,FALSE)="PASADO")),3,IF(AND(VLOOKUP(W4,'BD LUB'!$A$2:$L$223,11,FALSE)="PRÓXIMO",VLOOKUP(W4,'BD LUB'!$A$2:$L$223,12,FALSE)="PRÓXIMO"),4,IF(OR(AND(VLOOKUP(W4,'BD LUB'!$A$2:$L$223,11,FALSE)="PRÓXIMO",VLOOKUP(W4,'BD LUB'!$A$2:$L$223,12,FALSE)="VIGENTE"),AND(VLOOKUP(W4,'BD LUB'!$A$2:$L$223,11,FALSE)="VIGENTE",VLOOKUP(W4,'BD LUB'!$A$2:$L$223,12,FALSE)="PRÓXIMO")),5,IF(AND(VLOOKUP(W4,'BD LUB'!$A$2:$L$223,11,FALSE)="VIGENTE",VLOOKUP(W4,'BD LUB'!$A$2:$L$223,12,FALSE)="VIGENTE"),6,"No definido")))))) -> 3 | Z4: =IFERROR(__xludf.DUMMYFUNCTION("FLATTEN(QUERY(LUBRICACION!C8:I226,""SELECT C WHERE (H='PASADO' OR H='PRÓXIMO') AND (I='PEDIDO' OR I='NO PEDIDO')""),QUERY(LUBRICACION!L8:R226,""SELECT L WHERE (Q='PASADO' OR Q='PRÓXIMO') AND (R='PEDIDO' OR R='NO PEDIDO')""))"),2392.0) -> 2392 | AA4: =(VLOOKUP(Z4,'BD LUB'!$A$2:$L$223,5,FALSE)/VLOOKUP(Z4,'BD LUB'!$A$2:$L$223,7,FALSE))+(VLOOKUP(Z4,'BD LUB'!$A$2:$L$223,6,FALSE)/VLOOKUP(Z4,'BD LUB'!$A$2:$L$223,8,FALSE)) -> 2.1406811 | AB4: =IF(AND(VLOOKUP(Z4,'BD LUB'!$A$2:$L$223,11,FALSE)="PASADO",VLOOKUP(Z4,'BD LUB'!$A$2:$L$223,12,FALSE)="PASADO"),1,IF(OR(AND(VLOOKUP(Z4,'BD LUB'!$A$2:$L$223,11,FALSE)="PASADO",VLOOKUP(Z4,'BD LUB'!$A$2:$L$223,12,FALSE)="PRÓXIMO"),AND(VLOOKUP(Z4,'BD LUB'!$A$2:$L$223,11,FALSE)="PRÓXIMO",VLOOKUP(Z4,'BD LUB'!$A$2:$L$223,12,FALSE)="PASADO")),2,IF(OR(AND(VLOOKUP(Z4,'BD LUB'!$A$2:$L$223,11,FALSE)="PASADO",VLOOKUP(Z4,'BD LUB'!$A$2:$L$223,12,FALSE)="VIGENTE"),AND(VLOOKUP(Z4,'BD LUB'!$A$2:$L$223,11,FALSE)="VIGENTE",VLOOKUP(Z4,'BD LUB'!$A$2:$L$223,12,FALSE)="PASADO")),3,IF(AND(VLOOKUP(Z4,'BD LUB'!$A$2:$L$223,11,FALSE)="PRÓXIMO",VLOOKUP(Z4,'BD LUB'!$A$2:$L$223,12,FALSE)="PRÓXIMO"),4,IF(OR(AND(VLOOKUP(Z4,'BD LUB'!$A$2:$L$223,11,FALSE)="PRÓXIMO",VLOOKUP(Z4,'BD LUB'!$A$2:$L$223,12,FALSE)="VIGENTE"),AND(VLOOKUP(Z4,'BD LUB'!$A$2:$L$223,11,FALSE)="VIGENTE",VLOOKUP(Z4,'BD LUB'!$A$2:$L$223,12,FALSE)="PRÓXIMO")),5,IF(AND(VLOOKUP(Z4,'BD LUB'!$A$2:$L$223,11,FALSE)="VIGENTE",VLOOKUP(Z4,'BD LUB'!$A$2:$L$223,12,FALSE)="VIGENTE"),6,"No definido")))))) -> 3 | AC4: =IFERROR(__xludf.DUMMYFUNCTION("UNIQUE(QUERY(LUBRICACION!Z4:AB226,""SELECT Z ORDER BY AA DESC, AB ASC""))"),2671.0) -> 2671 | AD4: =IF(VLOOKUP(AC4,'BD LUB'!$A$2:$C$223,3,FALSE)=$AH$20,AC4&" MED",IF(VLOOKUP(AC4,'BD LUB'!$A$2:$C$223,3,FALSE)=$AH$19,AC4&" MAY",IF(VLOOKUP(AC4,'BD LUB'!$A$2:$C$223,3,FALSE)=$AH$18,AC4&" RN",IF(VLOOKUP(AC4,'BD LUB'!$A$2:$C$223,3,FALSE)=$AH$17,AC4&" COPQUI",IF(VLOOKUP(AC4,'BD LUB'!$A$2:$C$223,3,FALSE)=$AH$16,AC4&" CEJ",IF(VLOOKUP(AC4,'BD LUB'!$A$2:$C$223,3,FALSE)=$AH$15,AC4&" BULT",IF(VLOOKUP(AC4,'BD LUB'!$A$2:$C$223,3,FALSE)=$AH$14,AC4&" COP",IF(VLOOKUP(AC4,'BD LUB'!$A$2:$C$223,3,FALSE)=$AH$13,AC4&" RIO",IF(VLOOKUP(AC4,'BD LUB'!$A$2:$C$223,3,FALSE)=$AH$21,AC4&" APART","Dato no encontrado"))))))))) -> 2671 MAY | AJ4: 1 | AK4: =IFERROR(__xludf.DUMMYFUNCTION("""COMPUTED_VALUE"""),46661.0) -> 46661 | AL4: =IFERROR(__xludf.DUMMYFUNCTION("""COMPUTED_VALUE"""),"02-Medellin") -> 02-Medellin | AM4: =IFERROR(__xludf.DUMMYFUNCTION("""COMPUTED_VALUE"""),174.0) -> 174 | AP4: 1 | AQ4: =IFERROR(__xludf.DUMMYFUNCTION("""COMPUTED_VALUE"""),46661.0) -> 46661 | AR4: =IFERROR(__xludf.DUMMYFUNCTION("""COMPUTED_VALUE"""),"02-Medellin") -> 02-Medellin | AS4: =IFERROR(__xludf.DUMMYFUNCTION("""COMPUTED_VALUE"""),174.0) -> 174 | AV4: 1
B5: 2 | C5: =IFERROR(__xludf.DUMMYFUNCTION("""COMPUTED_VALUE"""),962.0) -> 962 | D5: =IFERROR(__xludf.DUMMYFUNCTION("""COMPUTED_VALUE"""),46500.0) -> 46500 | E5: =IFERROR(__xludf.DUMMYFUNCTION("""COMPUTED_VALUE"""),"02-Medellin") -> 02-Medellin | H5: =IFERROR(__xludf.DUMMYFUNCTION("""COMPUTED_VALUE"""),"#N/A") -> #N/A | I5: =IF(OR(H5="PASADO",H5="PRÓXIMO"), IF(AND(NOT(ISERROR(MATCH(C5,$T$4:$T$195,0))),NOT(ISERROR(MATCH(C5,$U$4:$U$195,0)))),"HECHO",IF(NOT(ISERROR(MATCH(C5,$U$4:$U$195,0))),"PEDIDO","NO PEDIDO")),"-") -> - | K5: 2 | L5: =IFERROR(__xludf.DUMMYFUNCTION("""COMPUTED_VALUE"""),962.0) -> 962 | M5: =IFERROR(__xludf.DUMMYFUNCTION("""COMPUTED_VALUE"""),46500.0) -> 46500 | N5: =IFERROR(__xludf.DUMMYFUNCTION("""COMPUTED_VALUE"""),"02-Medellin") -> 02-Medellin | Q5: =IFERROR(__xludf.DUMMYFUNCTION("""COMPUTED_VALUE"""),"#N/A") -> #N/A | T5: =CALENDARIO!D17 -> 2201 | U5: =CALENDARIO!C17 -> 2392 | W5: =IFERROR(__xludf.DUMMYFUNCTION("""COMPUTED_VALUE"""),2640.0) -> 2640 | X5: =(VLOOKUP(W5,'BD LUB'!$A$2:$L$223,5,FALSE)/VLOOKUP(W5,'BD LUB'!$A$2:$L$223,7,FALSE))+(VLOOKUP(W5,'BD LUB'!$A$2:$L$223,6,FALSE)/VLOOKUP(W5,'BD LUB'!$A$2:$L$223,8,FALSE)) -> 1.4219444 | Y5: =IF(AND(VLOOKUP(W5,'BD LUB'!$A$2:$L$223,11,FALSE)="PASADO",VLOOKUP(W5,'BD LUB'!$A$2:$L$223,12,FALSE)="PASADO"),1,IF(OR(AND(VLOOKUP(W5,'BD LUB'!$A$2:$L$223,11,FALSE)="PASADO",VLOOKUP(W5,'BD LUB'!$A$2:$L$223,12,FALSE)="PRÓXIMO"),AND(VLOOKUP(W5,'BD LUB'!$A$2:$L$223,11,FALSE)="PRÓXIMO",VLOOKUP(W5,'BD LUB'!$A$2:$L$223,12,FALSE)="PASADO")),2,IF(OR(AND(VLOOKUP(W5,'BD LUB'!$A$2:$L$223,11,FALSE)="PASADO",VLOOKUP(W5,'BD LUB'!$A$2:$L$223,12,FALSE)="VIGENTE"),AND(VLOOKUP(W5,'BD LUB'!$A$2:$L$223,11,FALSE)="VIGENTE",VLOOKUP(W5,'BD LUB'!$A$2:$L$223,12,FALSE)="PASADO")),3,IF(AND(VLOOKUP(W5,'BD LUB'!$A$2:$L$223,11,FALSE)="PRÓXIMO",VLOOKUP(W5,'BD LUB'!$A$2:$L$223,12,FALSE)="PRÓXIMO"),4,IF(OR(AND(VLOOKUP(W5,'BD LUB'!$A$2:$L$223,11,FALSE)="PRÓXIMO",VLOOKUP(W5,'BD LUB'!$A$2:$L$223,12,FALSE)="VIGENTE"),AND(VLOOKUP(W5,'BD LUB'!$A$2:$L$223,11,FALSE)="VIGENTE",VLOOKUP(W5,'BD LUB'!$A$2:$L$223,12,FALSE)="PRÓXIMO")),5,IF(AND(VLOOKUP(W5,'BD LUB'!$A$2:$L$223,11,FALSE)="VIGENTE",VLOOKUP(W5,'BD LUB'!$A$2:$L$223,12,FALSE)="VIGENTE"),6,"No definido")))))) -> 5 | Z5: =IFERROR(__xludf.DUMMYFUNCTION("""COMPUTED_VALUE"""),2276.0) -> 2276 | AA5: =(VLOOKUP(Z5,'BD LUB'!$A$2:$L$223,5,FALSE)/VLOOKUP(Z5,'BD LUB'!$A$2:$L$223,7,FALSE))+(VLOOKUP(Z5,'BD LUB'!$A$2:$L$223,6,FALSE)/VLOOKUP(Z5,'BD LUB'!$A$2:$L$223,8,FALSE)) -> 2.1728644 | AB5: =IF(AND(VLOOKUP(Z5,'BD LUB'!$A$2:$L$223,11,FALSE)="PASADO",VLOOKUP(Z5,'BD LUB'!$A$2:$L$223,12,FALSE)="PASADO"),1,IF(OR(AND(VLOOKUP(Z5,'BD LUB'!$A$2:$L$223,11,FALSE)="PASADO",VLOOKUP(Z5,'BD LUB'!$A$2:$L$223,12,FALSE)="PRÓXIMO"),AND(VLOOKUP(Z5,'BD LUB'!$A$2:$L$223,11,FALSE)="PRÓXIMO",VLOOKUP(Z5,'BD LUB'!$A$2:$L$223,12,FALSE)="PASADO")),2,IF(OR(AND(VLOOKUP(Z5,'BD LUB'!$A$2:$L$223,11,FALSE)="PASADO",VLOOKUP(Z5,'BD LUB'!$A$2:$L$223,12,FALSE)="VIGENTE"),AND(VLOOKUP(Z5,'BD LUB'!$A$2:$L$223,11,FALSE)="VIGENTE",VLOOKUP(Z5,'BD LUB'!$A$2:$L$223,12,FALSE)="PASADO")),3,IF(AND(VLOOKUP(Z5,'BD LUB'!$A$2:$L$223,11,FALSE)="PRÓXIMO",VLOOKUP(Z5,'BD LUB'!$A$2:$L$223,12,FALSE)="PRÓXIMO"),4,IF(OR(AND(VLOOKUP(Z5,'BD LUB'!$A$2:$L$223,11,FALSE)="PRÓXIMO",VLOOKUP(Z5,'BD LUB'!$A$2:$L$223,12,FALSE)="VIGENTE"),AND(VLOOKUP(Z5,'BD LUB'!$A$2:$L$223,11,FALSE)="VIGENTE",VLOOKUP(Z5,'BD LUB'!$A$2:$L$223,12,FALSE)="PRÓXIMO")),5,IF(AND(VLOOKUP(Z5,'BD LUB'!$A$2:$L$223,11,FALSE)="VIGENTE",VLOOKUP(Z5,'BD LUB'!$A$2:$L$223,12,FALSE)="VIGENTE"),6,"No definido")))))) -> 2 | AC5: =IFERROR(__xludf.DUMMYFUNCTION("""COMPUTED_VALUE"""),2681.0) -> 2681 | AD5: =IF(VLOOKUP(AC5,'BD LUB'!$A$2:$C$223,3,FALSE)=$AH$20,AC5&" MED",IF(VLOOKUP(AC5,'BD LUB'!$A$2:$C$223,3,FALSE)=$AH$19,AC5&" MAY",IF(VLOOKUP(AC5,'BD LUB'!$A$2:$C$223,3,FALSE)=$AH$18,AC5&" RN",IF(VLOOKUP(AC5,'BD LUB'!$A$2:$C$223,3,FALSE)=$AH$17,AC5&" COPQUI",IF(VLOOKUP(AC5,'BD LUB'!$A$2:$C$223,3,FALSE)=$AH$16,AC5&" CEJ",IF(VLOOKUP(AC5,'BD LUB'!$A$2:$C$223,3,FALSE)=$AH$15,AC5&" BULT",IF(VLOOKUP(AC5,'BD LUB'!$A$2:$C$223,3,FALSE)=$AH$14,AC5&" COP",IF(VLOOKUP(AC5,'BD LUB'!$A$2:$C$223,3,FALSE)=$AH$13,AC5&" RIO",IF(VLOOKUP(AC5,'BD LUB'!$A$2:$C$223,3,FALSE)=$AH$21,AC5&" APART","Dato no encontrado"))))))))) -> 2681 APART | AJ5: 2 | AK5: =IFERROR(__xludf.DUMMYFUNCTION("""COMPUTED_VALUE"""),46275.0) -> 46275 | AL5: =IFERROR(__xludf.DUMMYFUNCTION("""COMPUTED_VALUE"""),"02-Medellin") -> 02-Medellin | AM5: =IFERROR(__xludf.DUMMYFUNCTION("""COMPUTED_VALUE"""),174.0) -> 174 | AP5: 2 | AQ5: =IFERROR(__xludf.DUMMYFUNCTION("""COMPUTED_VALUE"""),46275.0) -> 46275 | AR5: =IFERROR(__xludf.DUMMYFUNCTION("""COMPUTED_VALUE"""),"02-Medellin") -> 02-Medellin | AS5: =IFERROR(__xludf.DUMMYFUNCTION("""COMPUTED_VALUE"""),174.0) -> 174 | AV5: 2
B6: 3 | C6: =IFERROR(__xludf.DUMMYFUNCTION("""COMPUTED_VALUE"""),975.0) -> 975 | D6: =IFERROR(__xludf.DUMMYFUNCTION("""COMPUTED_VALUE"""),46214.0) -> 46214 | E6: =IFERROR(__xludf.DUMMYFUNCTION("""COMPUTED_VALUE"""),"02-Medellin") -> 02-Medellin | H6: =IFERROR(__xludf.DUMMYFUNCTION("""COMPUTED_VALUE"""),"#N/A") -> #N/A | I6: =IF(OR(H6="PASADO",H6="PRÓXIMO"), IF(AND(NOT(ISERROR(MATCH(C6,$T$4:$T$195,0))),NOT(ISERROR(MATCH(C6,$U$4:$U$195,0)))),"HECHO",IF(NOT(ISERROR(MATCH(C6,$U$4:$U$195,0))),"PEDIDO","NO PEDIDO")),"-") -> - | K6: 3 | L6: =IFERROR(__xludf.DUMMYFUNCTION("""COMPUTED_VALUE"""),975.0) -> 975 | M6: =IFERROR(__xludf.DUMMYFUNCTION("""COMPUTED_VALUE"""),46214.0) -> 46214 | N6: =IFERROR(__xludf.DUMMYFUNCTION("""COMPUTED_VALUE"""),"02-Medellin") -> 02-Medellin | Q6: =IFERROR(__xludf.DUMMYFUNCTION("""COMPUTED_VALUE"""),"#N/A") -> #N/A | T6: =CALENDARIO!D18 -> 3083 | U6: =CALENDARIO!C18 -> 2425 | W6: =IFERROR(__xludf.DUMMYFUNCTION("""COMPUTED_VALUE"""),496.0) -> 496 | X6: =(VLOOKUP(W6,'BD LUB'!$A$2:$L$223,5,FALSE)/VLOOKUP(W6,'BD LUB'!$A$2:$L$223,7,FALSE))+(VLOOKUP(W6,'BD LUB'!$A$2:$L$223,6,FALSE)/VLOOKUP(W6,'BD LUB'!$A$2:$L$223,8,FALSE)) -> 1.4086289 | Y6: =IF(AND(VLOOKUP(W6,'BD LUB'!$A$2:$L$223,11,FALSE)="PASADO",VLOOKUP(W6,'BD LUB'!$A$2:$L$223,12,FALSE)="PASADO"),1,IF(OR(AND(VLOOKUP(W6,'BD LUB'!$A$2:$L$223,11,FALSE)="PASADO",VLOOKUP(W6,'BD LUB'!$A$2:$L$223,12,FALSE)="PRÓXIMO"),AND(VLOOKUP(W6,'BD LUB'!$A$2:$L$223,11,FALSE)="PRÓXIMO",VLOOKUP(W6,'BD LUB'!$A$2:$L$223,12,FALSE)="PASADO")),2,IF(OR(AND(VLOOKUP(W6,'BD LUB'!$A$2:$L$223,11,FALSE)="PASADO",VLOOKUP(W6,'BD LUB'!$A$2:$L$223,12,FALSE)="VIGENTE"),AND(VLOOKUP(W6,'BD LUB'!$A$2:$L$223,11,FALSE)="VIGENTE",VLOOKUP(W6,'BD LUB'!$A$2:$L$223,12,FALSE)="PASADO")),3,IF(AND(VLOOKUP(W6,'BD LUB'!$A$2:$L$223,11,FALSE)="PRÓXIMO",VLOOKUP(W6,'BD LUB'!$A$2:$L$223,12,FALSE)="PRÓXIMO"),4,IF(OR(AND(VLOOKUP(W6,'BD LUB'!$A$2:$L$223,11,FALSE)="PRÓXIMO",VLOOKUP(W6,'BD LUB'!$A$2:$L$223,12,FALSE)="VIGENTE"),AND(VLOOKUP(W6,'BD LUB'!$A$2:$L$223,11,FALSE)="VIGENTE",VLOOKUP(W6,'BD LUB'!$A$2:$L$223,12,FALSE)="PRÓXIMO")),5,IF(AND(VLOOKUP(W6,'BD LUB'!$A$2:$L$223,11,FALSE)="VIGENTE",VLOOKUP(W6,'BD LUB'!$A$2:$L$223,12,FALSE)="VIGENTE"),6,"No definido")))))) -> 5 | Z6: =IFERROR(__xludf.DUMMYFUNCTION("""COMPUTED_VALUE"""),2671.0) -> 2671 | AA6: =(VLOOKUP(Z6,'BD LUB'!$A$2:$L$223,5,FALSE)/VLOOKUP(Z6,'BD LUB'!$A$2:$L$223,7,FALSE))+(VLOOKUP(Z6,'BD LUB'!$A$2:$L$223,6,FALSE)/VLOOKUP(Z6,'BD LUB'!$A$2:$L$223,8,FALSE)) -> 2.2249678 | AB6: =IF(AND(VLOOKUP(Z6,'BD LUB'!$A$2:$L$223,11,FALSE)="PASADO",VLOOKUP(Z6,'BD LUB'!$A$2:$L$223,12,FALSE)="PASADO"),1,IF(OR(AND(VLOOKUP(Z6,'BD LUB'!$A$2:$L$223,11,FALSE)="PASADO",VLOOKUP(Z6,'BD LUB'!$A$2:$L$223,12,FALSE)="PRÓXIMO"),AND(VLOOKUP(Z6,'BD LUB'!$A$2:$L$223,11,FALSE)="PRÓXIMO",VLOOKUP(Z6,'BD LUB'!$A$2:$L$223,12,FALSE)="PASADO")),2,IF(OR(AND(VLOOKUP(Z6,'BD LUB'!$A$2:$L$223,11,FALSE)="PASADO",VLOOKUP(Z6,'BD LUB'!$A$2:$L$223,12,FALSE)="VIGENTE"),AND(VLOOKUP(Z6,'BD LUB'!$A$2:$L$223,11,FALSE)="VIGENTE",VLOOKUP(Z6,'BD LUB'!$A$2:$L$223,12,FALSE)="PASADO")),3,IF(AND(VLOOKUP(Z6,'BD LUB'!$A$2:$L$223,11,FALSE)="PRÓXIMO",VLOOKUP(Z6,'BD LUB'!$A$2:$L$223,12,FALSE)="PRÓXIMO"),4,IF(OR(AND(VLOOKUP(Z6,'BD LUB'!$A$2:$L$223,11,FALSE)="PRÓXIMO",VLOOKUP(Z6,'BD LUB'!$A$2:$L$223,12,FALSE)="VIGENTE"),AND(VLOOKUP(Z6,'BD LUB'!$A$2:$L$223,11,FALSE)="VIGENTE",VLOOKUP(Z6,'BD LUB'!$A$2:$L$223,12,FALSE)="PRÓXIMO")),5,IF(AND(VLOOKUP(Z6,'BD LUB'!$A$2:$L$223,11,FALSE)="VIGENTE",VLOOKUP(Z6,'BD LUB'!$A$2:$L$223,12,FALSE)="VIGENTE"),6,"No definido")))))) -> 1 | AC6: =IFERROR(__xludf.DUMMYFUNCTION("""COMPUTED_VALUE"""),2276.0) -> 2276 | AD6: =IF(VLOOKUP(AC6,'BD LUB'!$A$2:$C$223,3,FALSE)=$AH$20,AC6&" MED",IF(VLOOKUP(AC6,'BD LUB'!$A$2:$C$223,3,FALSE)=$AH$19,AC6&" MAY",IF(VLOOKUP(AC6,'BD LUB'!$A$2:$C$223,3,FALSE)=$AH$18,AC6&" RN",IF(VLOOKUP(AC6,'BD LUB'!$A$2:$C$223,3,FALSE)=$AH$17,AC6&" COPQUI",IF(VLOOKUP(AC6,'BD LUB'!$A$2:$C$223,3,FALSE)=$AH$16,AC6&" CEJ",IF(VLOOKUP(AC6,'BD LUB'!$A$2:$C$223,3,FALSE)=$AH$15,AC6&" BULT",IF(VLOOKUP(AC6,'BD LUB'!$A$2:$C$223,3,FALSE)=$AH$14,AC6&" COP",IF(VLOOKUP(AC6,'BD LUB'!$A$2:$C$223,3,FALSE)=$AH$13,AC6&" RIO",IF(VLOOKUP(AC6,'BD LUB'!$A$2:$C$223,3,FALSE)=$AH$21,AC6&" APART","Dato no encontrado"))))))))) -> 2276 MED | AJ6: 3 | AK6: =IFERROR(__xludf.DUMMYFUNCTION("""COMPUTED_VALUE"""),46660.0) -> 46660 | AL6: =IFERROR(__xludf.DUMMYFUNCTION("""COMPUTED_VALUE"""),"02-Medellin") -> 02-Medellin | AM6: =IFERROR(__xludf.DUMMYFUNCTION("""COMPUTED_VALUE"""),160.0) -> 160 | AP6: 3 | AQ6: =IFERROR(__xludf.DUMMYFUNCTION("""COMPUTED_VALUE"""),46660.0) -> 46660 | AR6: =IFERROR(__xludf.DUMMYFUNCTION("""COMPUTED_VALUE"""),"02-Medellin") -> 02-Medellin | AS6: =IFERROR(__xludf.DUMMYFUNCTION("""COMPUTED_VALUE"""),160.0) -> 160 | AV6: 3
B7: 4 | C7: =IFERROR(__xludf.DUMMYFUNCTION("""COMPUTED_VALUE"""),976.0) -> 976 | D7: =IFERROR(__xludf.DUMMYFUNCTION("""COMPUTED_VALUE"""),46047.0) -> 46047 | E7: =IFERROR(__xludf.DUMMYFUNCTION("""COMPUTED_VALUE"""),"02-Medellin") -> 02-Medellin | H7: =IFERROR(__xludf.DUMMYFUNCTION("""COMPUTED_VALUE"""),"#N/A") -> #N/A | I7: =IF(OR(H7="PASADO",H7="PRÓXIMO"), IF(AND(NOT(ISERROR(MATCH(C7,$T$4:$T$195,0))),NOT(ISERROR(MATCH(C7,$U$4:$U$195,0)))),"HECHO",IF(NOT(ISERROR(MATCH(C7,$U$4:$U$195,0))),"PEDIDO","NO PEDIDO")),"-") -> - | K7: 4 | L7: =IFERROR(__xludf.DUMMYFUNCTION("""COMPUTED_VALUE"""),976.0) -> 976 | M7: =IFERROR(__xludf.DUMMYFUNCTION("""COMPUTED_VALUE"""),46047.0) -> 46047 | N7: =IFERROR(__xludf.DUMMYFUNCTION("""COMPUTED_VALUE"""),"02-Medellin") -> 02-Medellin | Q7: =IFERROR(__xludf.DUMMYFUNCTION("""COMPUTED_VALUE"""),"#N/A") -> #N/A | T7: =CALENDARIO!D19 -> 3282 | U7: =CALENDARIO!C19 -> 2201 | W7: =IFERROR(__xludf.DUMMYFUNCTION("""COMPUTED_VALUE"""),464.0) -> 464 | X7: =(VLOOKUP(W7,'BD LUB'!$A$2:$L$223,5,FALSE)/VLOOKUP(W7,'BD LUB'!$A$2:$L$223,7,FALSE))+(VLOOKUP(W7,'BD LUB'!$A$2:$L$223,6,FALSE)/VLOOKUP(W7,'BD LUB'!$A$2:$L$223,8,FALSE)) -> 1.18678 | Y7: =IF(AND(VLOOKUP(W7,'BD LUB'!$A$2:$L$223,11,FALSE)="PASADO",VLOOKUP(W7,'BD LUB'!$A$2:$L$223,12,FALSE)="PASADO"),1,IF(OR(AND(VLOOKUP(W7,'BD LUB'!$A$2:$L$223,11,FALSE)="PASADO",VLOOKUP(W7,'BD LUB'!$A$2:$L$223,12,FALSE)="PRÓXIMO"),AND(VLOOKUP(W7,'BD LUB'!$A$2:$L$223,11,FALSE)="PRÓXIMO",VLOOKUP(W7,'BD LUB'!$A$2:$L$223,12,FALSE)="PASADO")),2,IF(OR(AND(VLOOKUP(W7,'BD LUB'!$A$2:$L$223,11,FALSE)="PASADO",VLOOKUP(W7,'BD LUB'!$A$2:$L$223,12,FALSE)="VIGENTE"),AND(VLOOKUP(W7,'BD LUB'!$A$2:$L$223,11,FALSE)="VIGENTE",VLOOKUP(W7,'BD LUB'!$A$2:$L$223,12,FALSE)="PASADO")),3,IF(AND(VLOOKUP(W7,'BD LUB'!$A$2:$L$223,11,FALSE)="PRÓXIMO",VLOOKUP(W7,'BD LUB'!$A$2:$L$223,12,FALSE)="PRÓXIMO"),4,IF(OR(AND(VLOOKUP(W7,'BD LUB'!$A$2:$L$223,11,FALSE)="PRÓXIMO",VLOOKUP(W7,'BD LUB'!$A$2:$L$223,12,FALSE)="VIGENTE"),AND(VLOOKUP(W7,'BD LUB'!$A$2:$L$223,11,FALSE)="VIGENTE",VLOOKUP(W7,'BD LUB'!$A$2:$L$223,12,FALSE)="PRÓXIMO")),5,IF(AND(VLOOKUP(W7,'BD LUB'!$A$2:$L$223,11,FALSE)="VIGENTE",VLOOKUP(W7,'BD LUB'!$A$2:$L$223,12,FALSE)="VIGENTE"),6,"No definido")))))) -> 5 | Z7: =IFERROR(__xludf.DUMMYFUNCTION("""COMPUTED_VALUE"""),2673.0) -> 2673 | AA7: =(VLOOKUP(Z7,'BD LUB'!$A$2:$L$223,5,FALSE)/VLOOKUP(Z7,'BD LUB'!$A$2:$L$223,7,FALSE))+(VLOOKUP(Z7,'BD LUB'!$A$2:$L$223,6,FALSE)/VLOOKUP(Z7,'BD LUB'!$A$2:$L$223,8,FALSE)) -> 1.8868367 | AB7: =IF(AND(VLOOKUP(Z7,'BD LUB'!$A$2:$L$223,11,FALSE)="PASADO",VLOOKUP(Z7,'BD LUB'!$A$2:$L$223,12,FALSE)="PASADO"),1,IF(OR(AND(VLOOKUP(Z7,'BD LUB'!$A$2:$L$223,11,FALSE)="PASADO",VLOOKUP(Z7,'BD LUB'!$A$2:$L$223,12,FALSE)="PRÓXIMO"),AND(VLOOKUP(Z7,'BD LUB'!$A$2:$L$223,11,FALSE)="PRÓXIMO",VLOOKUP(Z7,'BD LUB'!$A$2:$L$223,12,FALSE)="PASADO")),2,IF(OR(AND(VLOOKUP(Z7,'BD LUB'!$A$2:$L$223,11,FALSE)="PASADO",VLOOKUP(Z7,'BD LUB'!$A$2:$L$223,12,FALSE)="VIGENTE"),AND(VLOOKUP(Z7,'BD LUB'!$A$2:$L$223,11,FALSE)="VIGENTE",VLOOKUP(Z7,'BD LUB'!$A$2:$L$223,12,FALSE)="PASADO")),3,IF(AND(VLOOKUP(Z7,'BD LUB'!$A$2:$L$223,11,FALSE)="PRÓXIMO",VLOOKUP(Z7,'BD LUB'!$A$2:$L$223,12,FALSE)="PRÓXIMO"),4,IF(OR(AND(VLOOKUP(Z7,'BD LUB'!$A$2:$L$223,11,FALSE)="PRÓXIMO",VLOOKUP(Z7,'BD LUB'!$A$2:$L$223,12,FALSE)="VIGENTE"),AND(VLOOKUP(Z7,'BD LUB'!$A$2:$L$223,11,FALSE)="VIGENTE",VLOOKUP(Z7,'BD LUB'!$A$2:$L$223,12,FALSE)="PRÓXIMO")),5,IF(AND(VLOOKUP(Z7,'BD LUB'!$A$2:$L$223,11,FALSE)="VIGENTE",VLOOKUP(Z7,'BD LUB'!$A$2:$L$223,12,FALSE)="VIGENTE"),6,"No definido")))))) -> 3 | AC7: =IFERROR(__xludf.DUMMYFUNCTION("""COMPUTED_VALUE"""),2334.0) -> 2334 | AD7: =IF(VLOOKUP(AC7,'BD LUB'!$A$2:$C$223,3,FALSE)=$AH$20,AC7&" MED",IF(VLOOKUP(AC7,'BD LUB'!$A$2:$C$223,3,FALSE)=$AH$19,AC7&" MAY",IF(VLOOKUP(AC7,'BD LUB'!$A$2:$C$223,3,FALSE)=$AH$18,AC7&" RN",IF(VLOOKUP(AC7,'BD LUB'!$A$2:$C$223,3,FALSE)=$AH$17,AC7&" COPQUI",IF(VLOOKUP(AC7,'BD LUB'!$A$2:$C$223,3,FALSE)=$AH$16,AC7&" CEJ",IF(VLOOKUP(AC7,'BD LUB'!$A$2:$C$223,3,FALSE)=$AH$15,AC7&" BULT",IF(VLOOKUP(AC7,'BD LUB'!$A$2:$C$223,3,FALSE)=$AH$14,AC7&" COP",IF(VLOOKUP(AC7,'BD LUB'!$A$2:$C$223,3,FALSE)=$AH$13,AC7&" RIO",IF(VLOOKUP(AC7,'BD LUB'!$A$2:$C$223,3,FALSE)=$AH$21,AC7&" APART","Dato no encontrado"))))))))) -> 2334 APART | AJ7: 4 | AK7: =IFERROR(__xludf.DUMMYFUNCTION("""COMPUTED_VALUE"""),46318.0) -> 46318 | AL7: =IFERROR(__xludf.DUMMYFUNCTION("""COMPUTED_VALUE"""),"MAYORCA") -> MAYORCA | AM7: =IFERROR(__xludf.DUMMYFUNCTION("""COMPUTED_VALUE"""),160.0) -> 160 | AP7: 4 | AQ7: =IFERROR(__xludf.DUMMYFUNCTION("""COMPUTED_VALUE"""),46318.0) -> 46318 | AR7: =IFERROR(__xludf.DUMMYFUNCTION("""COMPUTED_VALUE"""),"MAYORCA") -> MAYORCA | AS7: =IFERROR(__xludf.DUMMYFUNCTION("""COMPUTED_VALUE"""),160.0) -> 160 | AV7: 4
B8: 5 | H8: =IFERROR(__xludf.DUMMYFUNCTION("""COMPUTED_VALUE"""),"#N/A") -> #N/A | I8: =IF(OR(H8="PASADO",H8="PRÓXIMO"), IF(AND(NOT(ISERROR(MATCH(C8,$T$4:$T$195,0))),NOT(ISERROR(MATCH(C8,$U$4:$U$195,0)))),"HECHO",IF(NOT(ISERROR(MATCH(C8,$U$4:$U$195,0))),"PEDIDO","NO PEDIDO")),"-") -> - | K8: 5 | Q8: =IFERROR(__xludf.DUMMYFUNCTION("""COMPUTED_VALUE"""),"#N/A") -> #N/A | T8: =CALENDARIO!D20 -> 2845 | U8: =CALENDARIO!C20 -> 2437 | W8: =IFERROR(__xludf.DUMMYFUNCTION("""COMPUTED_VALUE"""),2394.0) -> 2394 | X8: =(VLOOKUP(W8,'BD LUB'!$A$2:$L$223,5,FALSE)/VLOOKUP(W8,'BD LUB'!$A$2:$L$223,7,FALSE))+(VLOOKUP(W8,'BD LUB'!$A$2:$L$223,6,FALSE)/VLOOKUP(W8,'BD LUB'!$A$2:$L$223,8,FALSE)) -> 1.4558467 | Y8: =IF(AND(VLOOKUP(W8,'BD LUB'!$A$2:$L$223,11,FALSE)="PASADO",VLOOKUP(W8,'BD LUB'!$A$2:$L$223,12,FALSE)="PASADO"),1,IF(OR(AND(VLOOKUP(W8,'BD LUB'!$A$2:$L$223,11,FALSE)="PASADO",VLOOKUP(W8,'BD LUB'!$A$2:$L$223,12,FALSE)="PRÓXIMO"),AND(VLOOKUP(W8,'BD LUB'!$A$2:$L$223,11,FALSE)="PRÓXIMO",VLOOKUP(W8,'BD LUB'!$A$2:$L$223,12,FALSE)="PASADO")),2,IF(OR(AND(VLOOKUP(W8,'BD LUB'!$A$2:$L$223,11,FALSE)="PASADO",VLOOKUP(W8,'BD LUB'!$A$2:$L$223,12,FALSE)="VIGENTE"),AND(VLOOKUP(W8,'BD LUB'!$A$2:$L$223,11,FALSE)="VIGENTE",VLOOKUP(W8,'BD LUB'!$A$2:$L$223,12,FALSE)="PASADO")),3,IF(AND(VLOOKUP(W8,'BD LUB'!$A$2:$L$223,11,FALSE)="PRÓXIMO",VLOOKUP(W8,'BD LUB'!$A$2:$L$223,12,FALSE)="PRÓXIMO"),4,IF(OR(AND(VLOOKUP(W8,'BD LUB'!$A$2:$L$223,11,FALSE)="PRÓXIMO",VLOOKUP(W8,'BD LUB'!$A$2:$L$223,12,FALSE)="VIGENTE"),AND(VLOOKUP(W8,'BD LUB'!$A$2:$L$223,11,FALSE)="VIGENTE",VLOOKUP(W8,'BD LUB'!$A$2:$L$223,12,FALSE)="PRÓXIMO")),5,IF(AND(VLOOKUP(W8,'BD LUB'!$A$2:$L$223,11,FALSE)="VIGENTE",VLOOKUP(W8,'BD LUB'!$A$2:$L$223,12,FALSE)="VIGENTE"),6,"No definido")))))) -> 5 | Z8: =IFERROR(__xludf.DUMMYFUNCTION("""COMPUTED_VALUE"""),2424.0) -> 2424 | AA8: =(VLOOKUP(Z8,'BD LUB'!$A$2:$L$223,5,FALSE)/VLOOKUP(Z8,'BD LUB'!$A$2:$L$223,7,FALSE))+(VLOOKUP(Z8,'BD LUB'!$A$2:$L$223,6,FALSE)/VLOOKUP(Z8,'BD LUB'!$A$2:$L$223,8,FALSE)) -> 1.9363 | AB8: =IF(AND(VLOOKUP(Z8,'BD LUB'!$A$2:$L$223,11,FALSE)="PASADO",VLOOKUP(Z8,'BD LUB'!$A$2:$L$223,12,FALSE)="PASADO"),1,IF(OR(AND(VLOOKUP(Z8,'BD LUB'!$A$2:$L$223,11,FALSE)="PASADO",VLOOKUP(Z8,'BD LUB'!$A$2:$L$223,12,FALSE)="PRÓXIMO"),AND(VLOOKUP(Z8,'BD LUB'!$A$2:$L$223,11,FALSE)="PRÓXIMO",VLOOKUP(Z8,'BD LUB'!$A$2:$L$223,12,FALSE)="PASADO")),2,IF(OR(AND(VLOOKUP(Z8,'BD LUB'!$A$2:$L$223,11,FALSE)="PASADO",VLOOKUP(Z8,'BD LUB'!$A$2:$L$223,12,FALSE)="VIGENTE"),AND(VLOOKUP(Z8,'BD LUB'!$A$2:$L$223,11,FALSE)="VIGENTE",VLOOKUP(Z8,'BD LUB'!$A$2:$L$223,12,FALSE)="PASADO")),3,IF(AND(VLOOKUP(Z8,'BD LUB'!$A$2:$L$223,11,FALSE)="PRÓXIMO",VLOOKUP(Z8,'BD LUB'!$A$2:$L$223,12,FALSE)="PRÓXIMO"),4,IF(OR(AND(VLOOKUP(Z8,'BD LUB'!$A$2:$L$223,11,FALSE)="PRÓXIMO",VLOOKUP(Z8,'BD LUB'!$A$2:$L$223,12,FALSE)="VIGENTE"),AND(VLOOKUP(Z8,'BD LUB'!$A$2:$L$223,11,FALSE)="VIGENTE",VLOOKUP(Z8,'BD LUB'!$A$2:$L$223,12,FALSE)="PRÓXIMO")),5,IF(AND(VLOOKUP(Z8,'BD LUB'!$A$2:$L$223,11,FALSE)="VIGENTE",VLOOKUP(Z8,'BD LUB'!$A$2:$L$223,12,FALSE)="VIGENTE"),6,"No definido")))))) -> 3 | AC8: =IFERROR(__xludf.DUMMYFUNCTION("""COMPUTED_VALUE"""),2392.0) -> 2392 | AD8: =IF(VLOOKUP(AC8,'BD LUB'!$A$2:$C$223,3,FALSE)=$AH$20,AC8&" MED",IF(VLOOKUP(AC8,'BD LUB'!$A$2:$C$223,3,FALSE)=$AH$19,AC8&" MAY",IF(VLOOKUP(AC8,'BD LUB'!$A$2:$C$223,3,FALSE)=$AH$18,AC8&" RN",IF(VLOOKUP(AC8,'BD LUB'!$A$2:$C$223,3,FALSE)=$AH$17,AC8&" COPQUI",IF(VLOOKUP(AC8,'BD LUB'!$A$2:$C$223,3,FALSE)=$AH$16,AC8&" CEJ",IF(VLOOKUP(AC8,'BD LUB'!$A$2:$C$223,3,FALSE)=$AH$15,AC8&" BULT",IF(VLOOKUP(AC8,'BD LUB'!$A$2:$C$223,3,FALSE)=$AH$14,AC8&" COP",IF(VLOOKUP(AC8,'BD LUB'!$A$2:$C$223,3,FALSE)=$AH$13,AC8&" RIO",IF(VLOOKUP(AC8,'BD LUB'!$A$2:$C$223,3,FALSE)=$AH$21,AC8&" APART","Dato no encontrado"))))))))) -> 2392 MED | AJ8: 5 | AK8: =IFERROR(__xludf.DUMMYFUNCTION("""COMPUTED_VALUE"""),46668.0) -> 46668 | AL8: =IFERROR(__xludf.DUMMYFUNCTION("""COMPUTED_VALUE"""),"02-Medellin") -> 02-Medellin | AM8: =IFERROR(__xludf.DUMMYFUNCTION("""COMPUTED_VALUE"""),154.0) -> 154 | AP8: 5 | AQ8: =IFERROR(__xludf.DUMMYFUNCTION("""COMPUTED_VALUE"""),46668.0) -> 46668 | AR8: =IFERROR(__xludf.DUMMYFUNCTION("""COMPUTED_VALUE"""),"02-Medellin") -> 02-Medellin | AS8: =IFERROR(__xludf.DUMMYFUNCTION("""COMPUTED_VALUE"""),154.0) -> 154 | AV8: 5
B9: 6 | C9: =IFERROR(__xludf.DUMMYFUNCTION("""COMPUTED_VALUE"""),2392.0) -> 2392 | D9: =IFERROR(__xludf.DUMMYFUNCTION("""COMPUTED_VALUE"""),46548.0) -> 46548 | E9: =IFERROR(__xludf.DUMMYFUNCTION("""COMPUTED_VALUE"""),"02-Medellin") -> 02-Medellin | F9: =IFERROR(__xludf.DUMMYFUNCTION("""COMPUTED_VALUE"""),45980.0) -> 45980 | G9: =IFERROR(__xludf.DUMMYFUNCTION("""COMPUTED_VALUE"""),-56.0) -> -56 | H9: =IFERROR(__xludf.DUMMYFUNCTION("""COMPUTED_VALUE"""),"PASADO") -> PASADO | I9: =IF(OR(H9="PASADO",H9="PRÓXIMO"), IF(AND(NOT(ISERROR(MATCH(C9,$T$4:$T$195,0))),NOT(ISERROR(MATCH(C9,$U$4:$U$195,0)))),"HECHO",IF(NOT(ISERROR(MATCH(C9,$U$4:$U$195,0))),"PEDIDO","NO PEDIDO")),"-") -> PEDIDO | K9: 6 | L9: =IFERROR(__xludf.DUMMYFUNCTION("""COMPUTED_VALUE"""),2880.0) -> 2880 | M9: =IFERROR(__xludf.DUMMYFUNCTION("""COMPUTED_VALUE"""),46226.0) -> 46226 | N9: =IFERROR(__xludf.DUMMYFUNCTION("""COMPUTED_VALUE"""),"MAYORCA") -> MAYORCA | O9: =IFERROR(__xludf.DUMMYFUNCTION("""COMPUTED_VALUE"""),46041.0) -> 46041 | P9: =IFERROR(__xludf.DUMMYFUNCTION("""COMPUTED_VALUE"""),-11147.0) -> -11147 | Q9: =IFERROR(__xludf.DUMMYFUNCTION("""COMPUTED_VALUE"""),"PASADO") -> PASADO | R9: =IF(OR(Q9="PASADO",Q9="PRÓXIMO"), IF(AND(NOT(ISERROR(MATCH(L9,$T$4:$T$195,0))),NOT(ISERROR(MATCH(L9,$U$4:$U$195,0)))),"HECHO",IF(NOT(ISERROR(MATCH(L9,$U$4:$U$195,0))),"PEDIDO","NO PEDIDO")),"-") -> HECHO | T9: =CALENDARIO!D21 -> 3202 | U9: =CALENDARIO!C21 -> 2671 | W9: =IFERROR(__xludf.DUMMYFUNCTION("""COMPUTED_VALUE"""),2275.0) -> 2275 | X9: =(VLOOKUP(W9,'BD LUB'!$A$2:$L$223,5,FALSE)/VLOOKUP(W9,'BD LUB'!$A$2:$L$223,7,FALSE))+(VLOOKUP(W9,'BD LUB'!$A$2:$L$223,6,FALSE)/VLOOKUP(W9,'BD LUB'!$A$2:$L$223,8,FALSE)) -> 1.2668667 | Y9: =IF(AND(VLOOKUP(W9,'BD LUB'!$A$2:$L$223,11,FALSE)="PASADO",VLOOKUP(W9,'BD LUB'!$A$2:$L$223,12,FALSE)="PASADO"),1,IF(OR(AND(VLOOKUP(W9,'BD LUB'!$A$2:$L$223,11,FALSE)="PASADO",VLOOKUP(W9,'BD LUB'!$A$2:$L$223,12,FALSE)="PRÓXIMO"),AND(VLOOKUP(W9,'BD LUB'!$A$2:$L$223,11,FALSE)="PRÓXIMO",VLOOKUP(W9,'BD LUB'!$A$2:$L$223,12,FALSE)="PASADO")),2,IF(OR(AND(VLOOKUP(W9,'BD LUB'!$A$2:$L$223,11,FALSE)="PASADO",VLOOKUP(W9,'BD LUB'!$A$2:$L$223,12,FALSE)="VIGENTE"),AND(VLOOKUP(W9,'BD LUB'!$A$2:$L$223,11,FALSE)="VIGENTE",VLOOKUP(W9,'BD LUB'!$A$2:$L$223,12,FALSE)="PASADO")),3,IF(AND(VLOOKUP(W9,'BD LUB'!$A$2:$L$223,11,FALSE)="PRÓXIMO",VLOOKUP(W9,'BD LUB'!$A$2:$L$223,12,FALSE)="PRÓXIMO"),4,IF(OR(AND(VLOOKUP(W9,'BD LUB'!$A$2:$L$223,11,FALSE)="PRÓXIMO",VLOOKUP(W9,'BD LUB'!$A$2:$L$223,12,FALSE)="VIGENTE"),AND(VLOOKUP(W9,'BD LUB'!$A$2:$L$223,11,FALSE)="VIGENTE",VLOOKUP(W9,'BD LUB'!$A$2:$L$223,12,FALSE)="PRÓXIMO")),5,IF(AND(VLOOKUP(W9,'BD LUB'!$A$2:$L$223,11,FALSE)="VIGENTE",VLOOKUP(W9,'BD LUB'!$A$2:$L$223,12,FALSE)="VIGENTE"),6,"No definido")))))) -> 5 | Z9: =IFERROR(__xludf.DUMMYFUNCTION("""COMPUTED_VALUE"""),2681.0) -> 2681 | AA9: =(VLOOKUP(Z9,'BD LUB'!$A$2:$L$223,5,FALSE)/VLOOKUP(Z9,'BD LUB'!$A$2:$L$223,7,FALSE))+(VLOOKUP(Z9,'BD LUB'!$A$2:$L$223,6,FALSE)/VLOOKUP(Z9,'BD LUB'!$A$2:$L$223,8,FALSE)) -> 2.2235189 | AB9: =IF(AND(VLOOKUP(Z9,'BD LUB'!$A$2:$L$223,11,FALSE)="PASADO",VLOOKUP(Z9,'BD LUB'!$A$2:$L$223,12,FALSE)="PASADO"),1,IF(OR(AND(VLOOKUP(Z9,'BD LUB'!$A$2:$L$223,11,FALSE)="PASADO",VLOOKUP(Z9,'BD LUB'!$A$2:$L$223,12,FALSE)="PRÓXIMO"),AND(VLOOKUP(Z9,'BD LUB'!$A$2:$L$223,11,FALSE)="PRÓXIMO",VLOOKUP(Z9,'BD LUB'!$A$2:$L$223,12,FALSE)="PASADO")),2,IF(OR(AND(VLOOKUP(Z9,'BD LUB'!$A$2:$L$223,11,FALSE)="PASADO",VLOOKUP(Z9,'BD LUB'!$A$2:$L$223,12,FALSE)="VIGENTE"),AND(VLOOKUP(Z9,'BD LUB'!$A$2:$L$223,11,FALSE)="VIGENTE",VLOOKUP(Z9,'BD LUB'!$A$2:$L$223,12,FALSE)="PASADO")),3,IF(AND(VLOOKUP(Z9,'BD LUB'!$A$2:$L$223,11,FALSE)="PRÓXIMO",VLOOKUP(Z9,'BD LUB'!$A$2:$L$223,12,FALSE)="PRÓXIMO"),4,IF(OR(AND(VLOOKUP(Z9,'BD LUB'!$A$2:$L$223,11,FALSE)="PRÓXIMO",VLOOKUP(Z9,'BD LUB'!$A$2:$L$223,12,FALSE)="VIGENTE"),AND(VLOOKUP(Z9,'BD LUB'!$A$2:$L$223,11,FALSE)="VIGENTE",VLOOKUP(Z9,'BD LUB'!$A$2:$L$223,12,FALSE)="PRÓXIMO")),5,IF(AND(VLOOKUP(Z9,'BD LUB'!$A$2:$L$223,11,FALSE)="VIGENTE",VLOOKUP(Z9,'BD LUB'!$A$2:$L$223,12,FALSE)="VIGENTE"),6,"No definido")))))) -> 1 | AC9: =IFERROR(__xludf.DUMMYFUNCTION("""COMPUTED_VALUE"""),3283.0) -> 3283 | AD9: =IF(VLOOKUP(AC9,'BD LUB'!$A$2:$C$223,3,FALSE)=$AH$20,AC9&" MED",IF(VLOOKUP(AC9,'BD LUB'!$A$2:$C$223,3,FALSE)=$AH$19,AC9&" MAY",IF(VLOOKUP(AC9,'BD LUB'!$A$2:$C$223,3,FALSE)=$AH$18,AC9&" RN",IF(VLOOKUP(AC9,'BD LUB'!$A$2:$C$223,3,FALSE)=$AH$17,AC9&" COPQUI",IF(VLOOKUP(AC9,'BD LUB'!$A$2:$C$223,3,FALSE)=$AH$16,AC9&" CEJ",IF(VLOOKUP(AC9,'BD LUB'!$A$2:$C$223,3,FALSE)=$AH$15,AC9&" BULT",IF(VLOOKUP(AC9,'BD LUB'!$A$2:$C$223,3,FALSE)=$AH$14,AC9&" COP",IF(VLOOKUP(AC9,'BD LUB'!$A$2:$C$223,3,FALSE)=$AH$13,AC9&" RIO",IF(VLOOKUP(AC9,'BD LUB'!$A$2:$C$223,3,FALSE)=$AH$21,AC9&" APART","Dato no encontrado"))))))))) -> 3283 MED | AJ9: 6 | AK9: =IFERROR(__xludf.DUMMYFUNCTION("""COMPUTED_VALUE"""),46654.0) -> 46654 | AL9: =IFERROR(__xludf.DUMMYFUNCTION("""COMPUTED_VALUE"""),"31-Copacabana") -> 31-Copacabana | AM9: =IFERROR(__xludf.DUMMYFUNCTION("""COMPUTED_VALUE"""),154.0) -> 154 | AP9: 6 | AQ9: =IFERROR(__xludf.DUMMYFUNCTION("""COMPUTED_VALUE"""),46654.0) -> 46654 | AR9: =IFERROR(__xludf.DUMMYFUNCTION("""COMPUTED_VALUE"""),"31-Copacabana") -> 31-Copacabana | AS9: =IFERROR(__xludf.DUMMYFUNCTION("""COMPUTED_VALUE"""),154.0) -> 154 | AV9: 6
B10: 7 | C10: =IFERROR(__xludf.DUMMYFUNCTION("""COMPUTED_VALUE"""),2201.0) -> 2201 | D10: =IFERROR(__xludf.DUMMYFUNCTION("""COMPUTED_VALUE"""),46543.0) -> 46543 | E10: =IFERROR(__xludf.DUMMYFUNCTION("""COMPUTED_VALUE"""),"02-Medellin") -> 02-Medellin | F10: =IFERROR(__xludf.DUMMYFUNCTION("""COMPUTED_VALUE"""),45986.0) -> 45986 | G10: =IFERROR(__xludf.DUMMYFUNCTION("""COMPUTED_VALUE"""),-50.0) -> -50 | H10: =IFERROR(__xludf.DUMMYFUNCTION("""COMPUTED_VALUE"""),"PASADO") -> PASADO | I10: =IF(OR(H10="PASADO",H10="PRÓXIMO"), IF(AND(NOT(ISERROR(MATCH(C10,$T$4:$T$195,0))),NOT(ISERROR(MATCH(C10,$U$4:$U$195,0)))),"HECHO",IF(NOT(ISERROR(MATCH(C10,$U$4:$U$195,0))),"PEDIDO","NO PEDIDO")),"-") -> HECHO | K10: 7 | L10: =IFERROR(__xludf.DUMMYFUNCTION("""COMPUTED_VALUE"""),2425.0) -> 2425 | M10: =IFERROR(__xludf.DUMMYFUNCTION("""COMPUTED_VALUE"""),46477.0) -> 46477 | N10: =IFERROR(__xludf.DUMMYFUNCTION("""COMPUTED_VALUE"""),"BULTOS") -> BULTOS | O10: =IFERROR(__xludf.DUMMYFUNCTION("""COMPUTED_VALUE"""),46027.0) -> 46027 | P10: =IFERROR(__xludf.DUMMYFUNCTION("""COMPUTED_VALUE"""),-2668.0) -> -2668 | Q10: =IFERROR(__xludf.DUMMYFUNCTION("""COMPUTED_VALUE"""),"PASADO") -> PASADO | R10: =IF(OR(Q10="PASADO",Q10="PRÓXIMO"), IF(AND(NOT(ISERROR(MATCH(L10,$T$4:$T$195,0))),NOT(ISERROR(MATCH(L10,$U$4:$U$195,0)))),"HECHO",IF(NOT(ISERROR(MATCH(L10,$U$4:$U$195,0))),"PEDIDO","NO PEDIDO")),"-") -> HECHO | T10: =CALENDARIO!D22 -> 3280 | U10: =CALENDARIO!C22 -> 2484 | W10: =IFERROR(__xludf.DUMMYFUNCTION("""COMPUTED_VALUE"""),2887.0) -> 2887 | X10: =(VLOOKUP(W10,'BD LUB'!$A$2:$L$223,5,FALSE)/VLOOKUP(W10,'BD LUB'!$A$2:$L$223,7,FALSE))+(VLOOKUP(W10,'BD LUB'!$A$2:$L$223,6,FALSE)/VLOOKUP(W10,'BD LUB'!$A$2:$L$223,8,FALSE)) -> 1.5437556 | Y10: =IF(AND(VLOOKUP(W10,'BD LUB'!$A$2:$L$223,11,FALSE)="PASADO",VLOOKUP(W10,'BD LUB'!$A$2:$L$223,12,FALSE)="PASADO"),1,IF(OR(AND(VLOOKUP(W10,'BD LUB'!$A$2:$L$223,11,FALSE)="PASADO",VLOOKUP(W10,'BD LUB'!$A$2:$L$223,12,FALSE)="PRÓXIMO"),AND(VLOOKUP(W10,'BD LUB'!$A$2:$L$223,11,FALSE)="PRÓXIMO",VLOOKUP(W10,'BD LUB'!$A$2:$L$223,12,FALSE)="PASADO")),2,IF(OR(AND(VLOOKUP(W10,'BD LUB'!$A$2:$L$223,11,FALSE)="PASADO",VLOOKUP(W10,'BD LUB'!$A$2:$L$223,12,FALSE)="VIGENTE"),AND(VLOOKUP(W10,'BD LUB'!$A$2:$L$223,11,FALSE)="VIGENTE",VLOOKUP(W10,'BD LUB'!$A$2:$L$223,12,FALSE)="PASADO")),3,IF(AND(VLOOKUP(W10,'BD LUB'!$A$2:$L$223,11,FALSE)="PRÓXIMO",VLOOKUP(W10,'BD LUB'!$A$2:$L$223,12,FALSE)="PRÓXIMO"),4,IF(OR(AND(VLOOKUP(W10,'BD LUB'!$A$2:$L$223,11,FALSE)="PRÓXIMO",VLOOKUP(W10,'BD LUB'!$A$2:$L$223,12,FALSE)="VIGENTE"),AND(VLOOKUP(W10,'BD LUB'!$A$2:$L$223,11,FALSE)="VIGENTE",VLOOKUP(W10,'BD LUB'!$A$2:$L$223,12,FALSE)="PRÓXIMO")),5,IF(AND(VLOOKUP(W10,'BD LUB'!$A$2:$L$223,11,FALSE)="VIGENTE",VLOOKUP(W10,'BD LUB'!$A$2:$L$223,12,FALSE)="VIGENTE"),6,"No definido")))))) -> 5 | Z10: =IFERROR(__xludf.DUMMYFUNCTION("""COMPUTED_VALUE"""),2334.0) -> 2334 | AA10: =(VLOOKUP(Z10,'BD LUB'!$A$2:$L$223,5,FALSE)/VLOOKUP(Z10,'BD LUB'!$A$2:$L$223,7,FALSE))+(VLOOKUP(Z10,'BD LUB'!$A$2:$L$223,6,FALSE)/VLOOKUP(Z10,'BD LUB'!$A$2:$L$223,8,FALSE)) -> 2.1444333 | AB10: =IF(AND(VLOOKUP(Z10,'BD LUB'!$A$2:$L$223,11,FALSE)="PASADO",VLOOKUP(Z10,'BD LUB'!$A$2:$L$223,12,FALSE)="PASADO"),1,IF(OR(AND(VLOOKUP(Z10,'BD LUB'!$A$2:$L$223,11,FALSE)="PASADO",VLOOKUP(Z10,'BD LUB'!$A$2:$L$223,12,FALSE)="PRÓXIMO"),AND(VLOOKUP(Z10,'BD LUB'!$A$2:$L$223,11,FALSE)="PRÓXIMO",VLOOKUP(Z10,'BD LUB'!$A$2:$L$223,12,FALSE)="PASADO")),2,IF(OR(AND(VLOOKUP(Z10,'BD LUB'!$A$2:$L$223,11,FALSE)="PASADO",VLOOKUP(Z10,'BD LUB'!$A$2:$L$223,12,FALSE)="VIGENTE"),AND(VLOOKUP(Z10,'BD LUB'!$A$2:$L$223,11,FALSE)="VIGENTE",VLOOKUP(Z10,'BD LUB'!$A$2:$L$223,12,FALSE)="PASADO")),3,IF(AND(VLOOKUP(Z10,'BD LUB'!$A$2:$L$223,11,FALSE)="PRÓXIMO",VLOOKUP(Z10,'BD LUB'!$A$2:$L$223,12,FALSE)="PRÓXIMO"),4,IF(OR(AND(VLOOKUP(Z10,'BD LUB'!$A$2:$L$223,11,FALSE)="PRÓXIMO",VLOOKUP(Z10,'BD LUB'!$A$2:$L$223,12,FALSE)="VIGENTE"),AND(VLOOKUP(Z10,'BD LUB'!$A$2:$L$223,11,FALSE)="VIGENTE",VLOOKUP(Z10,'BD LUB'!$A$2:$L$223,12,FALSE)="PRÓXIMO")),5,IF(AND(VLOOKUP(Z10,'BD LUB'!$A$2:$L$223,11,FALSE)="VIGENTE",VLOOKUP(Z10,'BD LUB'!$A$2:$L$223,12,FALSE)="VIGENTE"),6,"No definido")))))) -> 1 | AC10: =IFERROR(__xludf.DUMMYFUNCTION("""COMPUTED_VALUE"""),2188.0) -> 2188 | AD10: =IF(VLOOKUP(AC10,'BD LUB'!$A$2:$C$223,3,FALSE)=$AH$20,AC10&" MED",IF(VLOOKUP(AC10,'BD LUB'!$A$2:$C$223,3,FALSE)=$AH$19,AC10&" MAY",IF(VLOOKUP(AC10,'BD LUB'!$A$2:$C$223,3,FALSE)=$AH$18,AC10&" RN",IF(VLOOKUP(AC10,'BD LUB'!$A$2:$C$223,3,FALSE)=$AH$17,AC10&" COPQUI",IF(VLOOKUP(AC10,'BD LUB'!$A$2:$C$223,3,FALSE)=$AH$16,AC10&" CEJ",IF(VLOOKUP(AC10,'BD LUB'!$A$2:$C$223,3,FALSE)=$AH$15,AC10&" BULT",IF(VLOOKUP(AC10,'BD LUB'!$A$2:$C$223,3,FALSE)=$AH$14,AC10&" COP",IF(VLOOKUP(AC10,'BD LUB'!$A$2:$C$223,3,FALSE)=$AH$13,AC10&" RIO",IF(VLOOKUP(AC10,'BD LUB'!$A$2:$C$223,3,FALSE)=$AH$21,AC10&" APART","Dato no encontrado"))))))))) -> 2188 BULT | AJ10: 7 | AK10: =IFERROR(__xludf.DUMMYFUNCTION("""COMPUTED_VALUE"""),46318.0) -> 46318 | AL10: =IFERROR(__xludf.DUMMYFUNCTION("""COMPUTED_VALUE"""),"02-Medellin") -> 02-Medellin | AM10: =IFERROR(__xludf.DUMMYFUNCTION("""COMPUTED_VALUE"""),154.0) -> 154 | AP10: 7 | AQ10: =IFERROR(__xludf.DUMMYFUNCTION("""COMPUTED_VALUE"""),46318.0) -> 46318 | AR10: =IFERROR(__xludf.DUMMYFUNCTION("""COMPUTED_VALUE"""),"02-Medellin") -> 02-Medellin | AS10: =IFERROR(__xludf.DUMMYFUNCTION("""COMPUTED_VALUE"""),154.0) -> 154 | AV10: 7
B11: 8 | C11: =IFERROR(__xludf.DUMMYFUNCTION("""COMPUTED_VALUE"""),2276.0) -> 2276 | D11: =IFERROR(__xludf.DUMMYFUNCTION("""COMPUTED_VALUE"""),46366.0) -> 46366 | E11: =IFERROR(__xludf.DUMMYFUNCTION("""COMPUTED_VALUE"""),"02-Medellin") -> 02-Medellin | F11: =IFERROR(__xludf.DUMMYFUNCTION("""COMPUTED_VALUE"""),46001.0) -> 46001 | G11: =IFERROR(__xludf.DUMMYFUNCTION("""COMPUTED_VALUE"""),-35.0) -> -35 | H11: =IFERROR(__xludf.DUMMYFUNCTION("""COMPUTED_VALUE"""),"PASADO") -> PASADO | I11: =IF(OR(H11="PASADO",H11="PRÓXIMO"), IF(AND(NOT(ISERROR(MATCH(C11,$T$4:$T$195,0))),NOT(ISERROR(MATCH(C11,$U$4:$U$195,0)))),"HECHO",IF(NOT(ISERROR(MATCH(C11,$U$4:$U$195,0))),"PEDIDO","NO PEDIDO")),"-") -> PEDIDO | K11: 8 | L11: =IFERROR(__xludf.DUMMYFUNCTION("""COMPUTED_VALUE"""),2896.0) -> 2896 | M11: =IFERROR(__xludf.DUMMYFUNCTION("""COMPUTED_VALUE"""),46242.0) -> 46242 | N11: =IFERROR(__xludf.DUMMYFUNCTION("""COMPUTED_VALUE"""),"02-Medellin") -> 02-Medellin | O11: =IFERROR(__xludf.DUMMYFUNCTION("""COMPUTED_VALUE"""),46156.0) -> 46156 | P11: =IFERROR(__xludf.DUMMYFUNCTION("""COMPUTED_VALUE"""),-1966.0) -> -1966 | Q11: =IFERROR(__xludf.DUMMYFUNCTION("""COMPUTED_VALUE"""),"PASADO") -> PASADO | R11: =IF(OR(Q11="PASADO",Q11="PRÓXIMO"), IF(AND(NOT(ISERROR(MATCH(L11,$T$4:$T$195,0))),NOT(ISERROR(MATCH(L11,$U$4:$U$195,0)))),"HECHO",IF(NOT(ISERROR(MATCH(L11,$U$4:$U$195,0))),"PEDIDO","NO PEDIDO")),"-") -> HECHO | T11: =CALENDARIO!D23 -> 2198 | U11: =CALENDARIO!C23 -> 2681 | W11: =IFERROR(__xludf.DUMMYFUNCTION("""COMPUTED_VALUE"""),2200.0) -> 2200 | X11: =(VLOOKUP(W11,'BD LUB'!$A$2:$L$223,5,FALSE)/VLOOKUP(W11,'BD LUB'!$A$2:$L$223,7,FALSE))+(VLOOKUP(W11,'BD LUB'!$A$2:$L$223,6,FALSE)/VLOOKUP(W11,'BD LUB'!$A$2:$L$223,8,FALSE)) -> 1.7762856 | Y11: =IF(AND(VLOOKUP(W11,'BD LUB'!$A$2:$L$223,11,FALSE)="PASADO",VLOOKUP(W11,'BD LUB'!$A$2:$L$223,12,FALSE)="PASADO"),1,IF(OR(AND(VLOOKUP(W11,'BD LUB'!$A$2:$L$223,11,FALSE)="PASADO",VLOOKUP(W11,'BD LUB'!$A$2:$L$223,12,FALSE)="PRÓXIMO"),AND(VLOOKUP(W11,'BD LUB'!$A$2:$L$223,11,FALSE)="PRÓXIMO",VLOOKUP(W11,'BD LUB'!$A$2:$L$223,12,FALSE)="PASADO")),2,IF(OR(AND(VLOOKUP(W11,'BD LUB'!$A$2:$L$223,11,FALSE)="PASADO",VLOOKUP(W11,'BD LUB'!$A$2:$L$223,12,FALSE)="VIGENTE"),AND(VLOOKUP(W11,'BD LUB'!$A$2:$L$223,11,FALSE)="VIGENTE",VLOOKUP(W11,'BD LUB'!$A$2:$L$223,12,FALSE)="PASADO")),3,IF(AND(VLOOKUP(W11,'BD LUB'!$A$2:$L$223,11,FALSE)="PRÓXIMO",VLOOKUP(W11,'BD LUB'!$A$2:$L$223,12,FALSE)="PRÓXIMO"),4,IF(OR(AND(VLOOKUP(W11,'BD LUB'!$A$2:$L$223,11,FALSE)="PRÓXIMO",VLOOKUP(W11,'BD LUB'!$A$2:$L$223,12,FALSE)="VIGENTE"),AND(VLOOKUP(W11,'BD LUB'!$A$2:$L$223,11,FALSE)="VIGENTE",VLOOKUP(W11,'BD LUB'!$A$2:$L$223,12,FALSE)="PRÓXIMO")),5,IF(AND(VLOOKUP(W11,'BD LUB'!$A$2:$L$223,11,FALSE)="VIGENTE",VLOOKUP(W11,'BD LUB'!$A$2:$L$223,12,FALSE)="VIGENTE"),6,"No definido")))))) -> 5 | Z11: =IFERROR(__xludf.DUMMYFUNCTION("""COMPUTED_VALUE"""),661.0) -> 661 | AA11: =(VLOOKUP(Z11,'BD LUB'!$A$2:$L$223,5,FALSE)/VLOOKUP(Z11,'BD LUB'!$A$2:$L$223,7,FALSE))+(VLOOKUP(Z11,'BD LUB'!$A$2:$L$223,6,FALSE)/VLOOKUP(Z11,'BD LUB'!$A$2:$L$223,8,FALSE)) -> 1.30455 | AB11: =IF(AND(VLOOKUP(Z11,'BD LUB'!$A$2:$L$223,11,FALSE)="PASADO",VLOOKUP(Z11,'BD LUB'!$A$2:$L$223,12,FALSE)="PASADO"),1,IF(OR(AND(VLOOKUP(Z11,'BD LUB'!$A$2:$L$223,11,FALSE)="PASADO",VLOOKUP(Z11,'BD LUB'!$A$2:$L$223,12,FALSE)="PRÓXIMO"),AND(VLOOKUP(Z11,'BD LUB'!$A$2:$L$223,11,FALSE)="PRÓXIMO",VLOOKUP(Z11,'BD LUB'!$A$2:$L$223,12,FALSE)="PASADO")),2,IF(OR(AND(VLOOKUP(Z11,'BD LUB'!$A$2:$L$223,11,FALSE)="PASADO",VLOOKUP(Z11,'BD LUB'!$A$2:$L$223,12,FALSE)="VIGENTE"),AND(VLOOKUP(Z11,'BD LUB'!$A$2:$L$223,11,FALSE)="VIGENTE",VLOOKUP(Z11,'BD LUB'!$A$2:$L$223,12,FALSE)="PASADO")),3,IF(AND(VLOOKUP(Z11,'BD LUB'!$A$2:$L$223,11,FALSE)="PRÓXIMO",VLOOKUP(Z11,'BD LUB'!$A$2:$L$223,12,FALSE)="PRÓXIMO"),4,IF(OR(AND(VLOOKUP(Z11,'BD LUB'!$A$2:$L$223,11,FALSE)="PRÓXIMO",VLOOKUP(Z11,'BD LUB'!$A$2:$L$223,12,FALSE)="VIGENTE"),AND(VLOOKUP(Z11,'BD LUB'!$A$2:$L$223,11,FALSE)="VIGENTE",VLOOKUP(Z11,'BD LUB'!$A$2:$L$223,12,FALSE)="PRÓXIMO")),5,IF(AND(VLOOKUP(Z11,'BD LUB'!$A$2:$L$223,11,FALSE)="VIGENTE",VLOOKUP(Z11,'BD LUB'!$A$2:$L$223,12,FALSE)="VIGENTE"),6,"No definido")))))) -> 3 | AC11: =IFERROR(__xludf.DUMMYFUNCTION("""COMPUTED_VALUE"""),2484.0) -> 2484 | AD11: =IF(VLOOKUP(AC11,'BD LUB'!$A$2:$C$223,3,FALSE)=$AH$20,AC11&" MED",IF(VLOOKUP(AC11,'BD LUB'!$A$2:$C$223,3,FALSE)=$AH$19,AC11&" MAY",IF(VLOOKUP(AC11,'BD LUB'!$A$2:$C$223,3,FALSE)=$AH$18,AC11&" RN",IF(VLOOKUP(AC11,'BD LUB'!$A$2:$C$223,3,FALSE)=$AH$17,AC11&" COPQUI",IF(VLOOKUP(AC11,'BD LUB'!$A$2:$C$223,3,FALSE)=$AH$16,AC11&" CEJ",IF(VLOOKUP(AC11,'BD LUB'!$A$2:$C$223,3,FALSE)=$AH$15,AC11&" BULT",IF(VLOOKUP(AC11,'BD LUB'!$A$2:$C$223,3,FALSE)=$AH$14,AC11&" COP",IF(VLOOKUP(AC11,'BD LUB'!$A$2:$C$223,3,FALSE)=$AH$13,AC11&" RIO",IF(VLOOKUP(AC11,'BD LUB'!$A$2:$C$223,3,FALSE)=$AH$21,AC11&" APART","Dato no encontrado"))))))))) -> 2484 MAY | AJ11: 8 | AK11: =IFERROR(__xludf.DUMMYFUNCTION("""COMPUTED_VALUE"""),46668.0) -> 46668 | AL11: =IFERROR(__xludf.DUMMYFUNCTION("""COMPUTED_VALUE"""),"02-Medellin") -> 02-Medellin | AM11: =IFERROR(__xludf.DUMMYFUNCTION("""COMPUTED_VALUE"""),146.0) -> 146 | AP11: 8 | AQ11: =IFERROR(__xludf.DUMMYFUNCTION("""COMPUTED_VALUE"""),46668.0) -> 46668 | AR11: =IFERROR(__xludf.DUMMYFUNCTION("""COMPUTED_VALUE"""),"02-Medellin") -> 02-Medellin | AS11: =IFERROR(__xludf.DUMMYFUNCTION("""COMPUTED_VALUE"""),146.0) -> 146 | AV11: 8
B12: 9 | C12: =IFERROR(__xludf.DUMMYFUNCTION("""COMPUTED_VALUE"""),2671.0) -> 2671 | D12: =IFERROR(__xludf.DUMMYFUNCTION("""COMPUTED_VALUE"""),46507.0) -> 46507 | E12: =IFERROR(__xludf.DUMMYFUNCTION("""COMPUTED_VALUE"""),"MAYORCA") -> MAYORCA | F12: =IFERROR(__xludf.DUMMYFUNCTION("""COMPUTED_VALUE"""),46004.0) -> 46004 | G12: =IFERROR(__xludf.DUMMYFUNCTION("""COMPUTED_VALUE"""),-32.0) -> -32 | H12: =IFERROR(__xludf.DUMMYFUNCTION("""COMPUTED_VALUE"""),"PASADO") -> PASADO | I12: =IF(OR(H12="PASADO",H12="PRÓXIMO"), IF(AND(NOT(ISERROR(MATCH(C12,$T$4:$T$195,0))),NOT(ISERROR(MATCH(C12,$U$4:$U$195,0)))),"HECHO",IF(NOT(ISERROR(MATCH(C12,$U$4:$U$195,0))),"PEDIDO","NO PEDIDO")),"-") -> PEDIDO | K12: 9 | L12: =IFERROR(__xludf.DUMMYFUNCTION("""COMPUTED_VALUE"""),2469.0) -> 2469 | M12: =IFERROR(__xludf.DUMMYFUNCTION("""COMPUTED_VALUE"""),46292.0) -> 46292 | N12: =IFERROR(__xludf.DUMMYFUNCTION("""COMPUTED_VALUE"""),"31-Copacabana QUIMICOS") -> 31-Copacabana QUIMICOS | O12: =IFERROR(__xludf.DUMMYFUNCTION("""COMPUTED_VALUE"""),46062.0) -> 46062 | P12: =IFERROR(__xludf.DUMMYFUNCTION("""COMPUTED_VALUE"""),-1881.2000000000007) -> -1881.2 | Q12: =IFERROR(__xludf.DUMMYFUNCTION("""COMPUTED_VALUE"""),"PASADO") -> PASADO | R12: =IF(OR(Q12="PASADO",Q12="PRÓXIMO"), IF(AND(NOT(ISERROR(MATCH(L12,$T$4:$T$195,0))),NOT(ISERROR(MATCH(L12,$U$4:$U$195,0)))),"HECHO",IF(NOT(ISERROR(MATCH(L12,$U$4:$U$195,0))),"PEDIDO","NO PEDIDO")),"-") -> PEDIDO | T12: =CALENDARIO!D24 -> 2572 | U12: =CALENDARIO!C24 -> 2276 | W12: =IFERROR(__xludf.DUMMYFUNCTION("""COMPUTED_VALUE"""),2847.0) -> 2847 | X12: =(VLOOKUP(W12,'BD LUB'!$A$2:$L$223,5,FALSE)/VLOOKUP(W12,'BD LUB'!$A$2:$L$223,7,FALSE))+(VLOOKUP(W12,'BD LUB'!$A$2:$L$223,6,FALSE)/VLOOKUP(W12,'BD LUB'!$A$2:$L$223,8,FALSE)) -> 1.3699111 | Y12: =IF(AND(VLOOKUP(W12,'BD LUB'!$A$2:$L$223,11,FALSE)="PASADO",VLOOKUP(W12,'BD LUB'!$A$2:$L$223,12,FALSE)="PASADO"),1,IF(OR(AND(VLOOKUP(W12,'BD LUB'!$A$2:$L$223,11,FALSE)="PASADO",VLOOKUP(W12,'BD LUB'!$A$2:$L$223,12,FALSE)="PRÓXIMO"),AND(VLOOKUP(W12,'BD LUB'!$A$2:$L$223,11,FALSE)="PRÓXIMO",VLOOKUP(W12,'BD LUB'!$A$2:$L$223,12,FALSE)="PASADO")),2,IF(OR(AND(VLOOKUP(W12,'BD LUB'!$A$2:$L$223,11,FALSE)="PASADO",VLOOKUP(W12,'BD LUB'!$A$2:$L$223,12,FALSE)="VIGENTE"),AND(VLOOKUP(W12,'BD LUB'!$A$2:$L$223,11,FALSE)="VIGENTE",VLOOKUP(W12,'BD LUB'!$A$2:$L$223,12,FALSE)="PASADO")),3,IF(AND(VLOOKUP(W12,'BD LUB'!$A$2:$L$223,11,FALSE)="PRÓXIMO",VLOOKUP(W12,'BD LUB'!$A$2:$L$223,12,FALSE)="PRÓXIMO"),4,IF(OR(AND(VLOOKUP(W12,'BD LUB'!$A$2:$L$223,11,FALSE)="PRÓXIMO",VLOOKUP(W12,'BD LUB'!$A$2:$L$223,12,FALSE)="VIGENTE"),AND(VLOOKUP(W12,'BD LUB'!$A$2:$L$223,11,FALSE)="VIGENTE",VLOOKUP(W12,'BD LUB'!$A$2:$L$223,12,FALSE)="PRÓXIMO")),5,IF(AND(VLOOKUP(W12,'BD LUB'!$A$2:$L$223,11,FALSE)="VIGENTE",VLOOKUP(W12,'BD LUB'!$A$2:$L$223,12,FALSE)="VIGENTE"),6,"No definido")))))) -> 5 | Z12: =IFERROR(__xludf.DUMMYFUNCTION("""COMPUTED_VALUE"""),495.0) -> 495 | AA12: =(VLOOKUP(Z12,'BD LUB'!$A$2:$L$223,5,FALSE)/VLOOKUP(Z12,'BD LUB'!$A$2:$L$223,7,FALSE))+(VLOOKUP(Z12,'BD LUB'!$A$2:$L$223,6,FALSE)/VLOOKUP(Z12,'BD LUB'!$A$2:$L$223,8,FALSE)) -> 1.5310456 | AB12: =IF(AND(VLOOKUP(Z12,'BD LUB'!$A$2:$L$223,11,FALSE)="PASADO",VLOOKUP(Z12,'BD LUB'!$A$2:$L$223,12,FALSE)="PASADO"),1,IF(OR(AND(VLOOKUP(Z12,'BD LUB'!$A$2:$L$223,11,FALSE)="PASADO",VLOOKUP(Z12,'BD LUB'!$A$2:$L$223,12,FALSE)="PRÓXIMO"),AND(VLOOKUP(Z12,'BD LUB'!$A$2:$L$223,11,FALSE)="PRÓXIMO",VLOOKUP(Z12,'BD LUB'!$A$2:$L$223,12,FALSE)="PASADO")),2,IF(OR(AND(VLOOKUP(Z12,'BD LUB'!$A$2:$L$223,11,FALSE)="PASADO",VLOOKUP(Z12,'BD LUB'!$A$2:$L$223,12,FALSE)="VIGENTE"),AND(VLOOKUP(Z12,'BD LUB'!$A$2:$L$223,11,FALSE)="VIGENTE",VLOOKUP(Z12,'BD LUB'!$A$2:$L$223,12,FALSE)="PASADO")),3,IF(AND(VLOOKUP(Z12,'BD LUB'!$A$2:$L$223,11,FALSE)="PRÓXIMO",VLOOKUP(Z12,'BD LUB'!$A$2:$L$223,12,FALSE)="PRÓXIMO"),4,IF(OR(AND(VLOOKUP(Z12,'BD LUB'!$A$2:$L$223,11,FALSE)="PRÓXIMO",VLOOKUP(Z12,'BD LUB'!$A$2:$L$223,12,FALSE)="VIGENTE"),AND(VLOOKUP(Z12,'BD LUB'!$A$2:$L$223,11,FALSE)="VIGENTE",VLOOKUP(Z12,'BD LUB'!$A$2:$L$223,12,FALSE)="PRÓXIMO")),5,IF(AND(VLOOKUP(Z12,'BD LUB'!$A$2:$L$223,11,FALSE)="VIGENTE",VLOOKUP(Z12,'BD LUB'!$A$2:$L$223,12,FALSE)="VIGENTE"),6,"No definido")))))) -> 3 | AC12: =IFERROR(__xludf.DUMMYFUNCTION("""COMPUTED_VALUE"""),3198.0) -> 3198 | AD12: =IF(VLOOKUP(AC12,'BD LUB'!$A$2:$C$223,3,FALSE)=$AH$20,AC12&" MED",IF(VLOOKUP(AC12,'BD LUB'!$A$2:$C$223,3,FALSE)=$AH$19,AC12&" MAY",IF(VLOOKUP(AC12,'BD LUB'!$A$2:$C$223,3,FALSE)=$AH$18,AC12&" RN",IF(VLOOKUP(AC12,'BD LUB'!$A$2:$C$223,3,FALSE)=$AH$17,AC12&" COPQUI",IF(VLOOKUP(AC12,'BD LUB'!$A$2:$C$223,3,FALSE)=$AH$16,AC12&" CEJ",IF(VLOOKUP(AC12,'BD LUB'!$A$2:$C$223,3,FALSE)=$AH$15,AC12&" BULT",IF(VLOOKUP(AC12,'BD LUB'!$A$2:$C$223,3,FALSE)=$AH$14,AC12&" COP",IF(VLOOKUP(AC12,'BD LUB'!$A$2:$C$223,3,FALSE)=$AH$13,AC12&" RIO",IF(VLOOKUP(AC12,'BD LUB'!$A$2:$C$223,3,FALSE)=$AH$21,AC12&" APART","Dato no encontrado"))))))))) -> 3198 COP | AJ12: 9 | AK12: =IFERROR(__xludf.DUMMYFUNCTION("""COMPUTED_VALUE"""),46668.0) -> 46668 | AL12: =IFERROR(__xludf.DUMMYFUNCTION("""COMPUTED_VALUE"""),"02-Medellin") -> 02-Medellin | AM12: =IFERROR(__xludf.DUMMYFUNCTION("""COMPUTED_VALUE"""),146.0) -> 146 | AP12: 9 | AQ12: =IFERROR(__xludf.DUMMYFUNCTION("""COMPUTED_VALUE"""),46668.0) -> 46668 | AR12: =IFERROR(__xludf.DUMMYFUNCTION("""COMPUTED_VALUE"""),"02-Medellin") -> 02-Medellin | AS12: =IFERROR(__xludf.DUMMYFUNCTION("""COMPUTED_VALUE"""),146.0) -> 146 | AV12: 9
B13: 10 | C13: =IFERROR(__xludf.DUMMYFUNCTION("""COMPUTED_VALUE"""),2673.0) -> 2673 | D13: =IFERROR(__xludf.DUMMYFUNCTION("""COMPUTED_VALUE"""),46516.0) -> 46516 | E13: =IFERROR(__xludf.DUMMYFUNCTION("""COMPUTED_VALUE"""),"02-Medellin") -> 02-Medellin | F13: =IFERROR(__xludf.DUMMYFUNCTION("""COMPUTED_VALUE"""),46006.0) -> 46006 | G13: =IFERROR(__xludf.DUMMYFUNCTION("""COMPUTED_VALUE"""),-30.0) -> -30 | H13: =IFERROR(__xludf.DUMMYFUNCTION("""COMPUTED_VALUE"""),"PASADO") -> PASADO | I13: =IF(OR(H13="PASADO",H13="PRÓXIMO"), IF(AND(NOT(ISERROR(MATCH(C13,$T$4:$T$195,0))),NOT(ISERROR(MATCH(C13,$U$4:$U$195,0)))),"HECHO",IF(NOT(ISERROR(MATCH(C13,$U$4:$U$195,0))),"PEDIDO","NO PEDIDO")),"-") -> PEDIDO | K13: 10 | L13: =IFERROR(__xludf.DUMMYFUNCTION("""COMPUTED_VALUE"""),2681.0) -> 2681 | M13: =IFERROR(__xludf.DUMMYFUNCTION("""COMPUTED_VALUE"""),46514.0) -> 46514 | N13: =IFERROR(__xludf.DUMMYFUNCTION("""COMPUTED_VALUE"""),"27-Apartado") -> 27-Apartado | O13: =IFERROR(__xludf.DUMMYFUNCTION("""COMPUTED_VALUE"""),46029.0) -> 46029 | P13: =IFERROR(__xludf.DUMMYFUNCTION("""COMPUTED_VALUE"""),-1846.2999999999993) -> -1846.3 | Q13: =IFERROR(__xludf.DUMMYFUNCTION("""COMPUTED_VALUE"""),"PASADO") -> PASADO | R13: =IF(OR(Q13="PASADO",Q13="PRÓXIMO"), IF(AND(NOT(ISERROR(MATCH(L13,$T$4:$T$195,0))),NOT(ISERROR(MATCH(L13,$U$4:$U$195,0)))),"HECHO",IF(NOT(ISERROR(MATCH(L13,$U$4:$U$195,0))),"PEDIDO","NO PEDIDO")),"-") -> PEDIDO | T13: =CALENDARIO!D25 -> 3275 | U13: =CALENDARIO!C25 -> 2188 | W13: =IFERROR(__xludf.DUMMYFUNCTION("""COMPUTED_VALUE"""),2892.0) -> 2892 | X13: =(VLOOKUP(W13,'BD LUB'!$A$2:$L$223,5,FALSE)/VLOOKUP(W13,'BD LUB'!$A$2:$L$223,7,FALSE))+(VLOOKUP(W13,'BD LUB'!$A$2:$L$223,6,FALSE)/VLOOKUP(W13,'BD LUB'!$A$2:$L$223,8,FALSE)) -> 1.3871556 | Y13: =IF(AND(VLOOKUP(W13,'BD LUB'!$A$2:$L$223,11,FALSE)="PASADO",VLOOKUP(W13,'BD LUB'!$A$2:$L$223,12,FALSE)="PASADO"),1,IF(OR(AND(VLOOKUP(W13,'BD LUB'!$A$2:$L$223,11,FALSE)="PASADO",VLOOKUP(W13,'BD LUB'!$A$2:$L$223,12,FALSE)="PRÓXIMO"),AND(VLOOKUP(W13,'BD LUB'!$A$2:$L$223,11,FALSE)="PRÓXIMO",VLOOKUP(W13,'BD LUB'!$A$2:$L$223,12,FALSE)="PASADO")),2,IF(OR(AND(VLOOKUP(W13,'BD LUB'!$A$2:$L$223,11,FALSE)="PASADO",VLOOKUP(W13,'BD LUB'!$A$2:$L$223,12,FALSE)="VIGENTE"),AND(VLOOKUP(W13,'BD LUB'!$A$2:$L$223,11,FALSE)="VIGENTE",VLOOKUP(W13,'BD LUB'!$A$2:$L$223,12,FALSE)="PASADO")),3,IF(AND(VLOOKUP(W13,'BD LUB'!$A$2:$L$223,11,FALSE)="PRÓXIMO",VLOOKUP(W13,'BD LUB'!$A$2:$L$223,12,FALSE)="PRÓXIMO"),4,IF(OR(AND(VLOOKUP(W13,'BD LUB'!$A$2:$L$223,11,FALSE)="PRÓXIMO",VLOOKUP(W13,'BD LUB'!$A$2:$L$223,12,FALSE)="VIGENTE"),AND(VLOOKUP(W13,'BD LUB'!$A$2:$L$223,11,FALSE)="VIGENTE",VLOOKUP(W13,'BD LUB'!$A$2:$L$223,12,FALSE)="PRÓXIMO")),5,IF(AND(VLOOKUP(W13,'BD LUB'!$A$2:$L$223,11,FALSE)="VIGENTE",VLOOKUP(W13,'BD LUB'!$A$2:$L$223,12,FALSE)="VIGENTE"),6,"No definido")))))) -> 5 | Z13: =IFERROR(__xludf.DUMMYFUNCTION("""COMPUTED_VALUE"""),481.0) -> 481 | AA13: =(VLOOKUP(Z13,'BD LUB'!$A$2:$L$223,5,FALSE)/VLOOKUP(Z13,'BD LUB'!$A$2:$L$223,7,FALSE))+(VLOOKUP(Z13,'BD LUB'!$A$2:$L$223,6,FALSE)/VLOOKUP(Z13,'BD LUB'!$A$2:$L$223,8,FALSE)) -> 1.5732733 | AB13: =IF(AND(VLOOKUP(Z13,'BD LUB'!$A$2:$L$223,11,FALSE)="PASADO",VLOOKUP(Z13,'BD LUB'!$A$2:$L$223,12,FALSE)="PASADO"),1,IF(OR(AND(VLOOKUP(Z13,'BD LUB'!$A$2:$L$223,11,FALSE)="PASADO",VLOOKUP(Z13,'BD LUB'!$A$2:$L$223,12,FALSE)="PRÓXIMO"),AND(VLOOKUP(Z13,'BD LUB'!$A$2:$L$223,11,FALSE)="PRÓXIMO",VLOOKUP(Z13,'BD LUB'!$A$2:$L$223,12,FALSE)="PASADO")),2,IF(OR(AND(VLOOKUP(Z13,'BD LUB'!$A$2:$L$223,11,FALSE)="PASADO",VLOOKUP(Z13,'BD LUB'!$A$2:$L$223,12,FALSE)="VIGENTE"),AND(VLOOKUP(Z13,'BD LUB'!$A$2:$L$223,11,FALSE)="VIGENTE",VLOOKUP(Z13,'BD LUB'!$A$2:$L$223,12,FALSE)="PASADO")),3,IF(AND(VLOOKUP(Z13,'BD LUB'!$A$2:$L$223,11,FALSE)="PRÓXIMO",VLOOKUP(Z13,'BD LUB'!$A$2:$L$223,12,FALSE)="PRÓXIMO"),4,IF(OR(AND(VLOOKUP(Z13,'BD LUB'!$A$2:$L$223,11,FALSE)="PRÓXIMO",VLOOKUP(Z13,'BD LUB'!$A$2:$L$223,12,FALSE)="VIGENTE"),AND(VLOOKUP(Z13,'BD LUB'!$A$2:$L$223,11,FALSE)="VIGENTE",VLOOKUP(Z13,'BD LUB'!$A$2:$L$223,12,FALSE)="PRÓXIMO")),5,IF(AND(VLOOKUP(Z13,'BD LUB'!$A$2:$L$223,11,FALSE)="VIGENTE",VLOOKUP(Z13,'BD LUB'!$A$2:$L$223,12,FALSE)="VIGENTE"),6,"No definido")))))) -> 5 | AC13: =IFERROR(__xludf.DUMMYFUNCTION("""COMPUTED_VALUE"""),2469.0) -> 2469 | AD13: =IF(VLOOKUP(AC13,'BD LUB'!$A$2:$C$223,3,FALSE)=$AH$20,AC13&" MED",IF(VLOOKUP(AC13,'BD LUB'!$A$2:$C$223,3,FALSE)=$AH$19,AC13&" MAY",IF(VLOOKUP(AC13,'BD LUB'!$A$2:$C$223,3,FALSE)=$AH$18,AC13&" RN",IF(VLOOKUP(AC13,'BD LUB'!$A$2:$C$223,3,FALSE)=$AH$17,AC13&" COPQUI",IF(VLOOKUP(AC13,'BD LUB'!$A$2:$C$223,3,FALSE)=$AH$16,AC13&" CEJ",IF(VLOOKUP(AC13,'BD LUB'!$A$2:$C$223,3,FALSE)=$AH$15,AC13&" BULT",IF(VLOOKUP(AC13,'BD LUB'!$A$2:$C$223,3,FALSE)=$AH$14,AC13&" COP",IF(VLOOKUP(AC13,'BD LUB'!$A$2:$C$223,3,FALSE)=$AH$13,AC13&" RIO",IF(VLOOKUP(AC13,'BD LUB'!$A$2:$C$223,3,FALSE)=$AH$21,AC13&" APART","Dato no encontrado"))))))))) -> 2469 COPQUI | AH13: 24-Rionegro | AJ13: 10 | AK13: =IFERROR(__xludf.DUMMYFUNCTION("""COMPUTED_VALUE"""),46318.0) -> 46318 | AL13: =IFERROR(__xludf.DUMMYFUNCTION("""COMPUTED_VALUE"""),"02-Medellin") -> 02-Medellin | AM13: =IFERROR(__xludf.DUMMYFUNCTION("""COMPUTED_VALUE"""),146.0) -> 146 | AP13: 10 | AQ13: =IFERROR(__xludf.DUMMYFUNCTION("""COMPUTED_VALUE"""),46318.0) -> 46318 | AR13: =IFERROR(__xludf.DUMMYFUNCTION("""COMPUTED_VALUE"""),"02-Medellin") -> 02-Medellin | AS13: =IFERROR(__xludf.DUMMYFUNCTION("""COMPUTED_VALUE"""),146.0) -> 146 | AV13: 10
B14: 11 | C14: =IFERROR(__xludf.DUMMYFUNCTION("""COMPUTED_VALUE"""),2437.0) -> 2437 | D14: =IFERROR(__xludf.DUMMYFUNCTION("""COMPUTED_VALUE"""),46528.0) -> 46528 | E14: =IFERROR(__xludf.DUMMYFUNCTION("""COMPUTED_VALUE"""),"02-Medellin") -> 02-Medellin | F14: =IFERROR(__xludf.DUMMYFUNCTION("""COMPUTED_VALUE"""),46006.0) -> 46006 | G14: =IFERROR(__xludf.DUMMYFUNCTION("""COMPUTED_VALUE"""),-30.0) -> -30 | H14: =IFERROR(__xludf.DUMMYFUNCTION("""COMPUTED_VALUE"""),"PASADO") -> PASADO | I14: =IF(OR(H14="PASADO",H14="PRÓXIMO"), IF(AND(NOT(ISERROR(MATCH(C14,$T$4:$T$195,0))),NOT(ISERROR(MATCH(C14,$U$4:$U$195,0)))),"HECHO",IF(NOT(ISERROR(MATCH(C14,$U$4:$U$195,0))),"PEDIDO","NO PEDIDO")),"-") -> HECHO | K14: 11 | L14: =IFERROR(__xludf.DUMMYFUNCTION("""COMPUTED_VALUE"""),2842.0) -> 2842 | M14: =IFERROR(__xludf.DUMMYFUNCTION("""COMPUTED_VALUE"""),46562.0) -> 46562 | N14: =IFERROR(__xludf.DUMMYFUNCTION("""COMPUTED_VALUE"""),"24-Rionegro") -> 24-Rionegro | O14: =IFERROR(__xludf.DUMMYFUNCTION("""COMPUTED_VALUE"""),46139.0) -> 46139 | P14: =IFERROR(__xludf.DUMMYFUNCTION("""COMPUTED_VALUE"""),-1687.0) -> -1687 | Q14: =IFERROR(__xludf.DUMMYFUNCTION("""COMPUTED_VALUE"""),"PASADO") -> PASADO | R14: =IF(OR(Q14="PASADO",Q14="PRÓXIMO"), IF(AND(NOT(ISERROR(MATCH(L14,$T$4:$T$195,0))),NOT(ISERROR(MATCH(L14,$U$4:$U$195,0)))),"HECHO",IF(NOT(ISERROR(MATCH(L14,$U$4:$U$195,0))),"PEDIDO","NO PEDIDO")),"-") -> PEDIDO | T14: =CALENDARIO!D26 -> 3284 | U14: =CALENDARIO!C26 -> 2469 | W14: =IFERROR(__xludf.DUMMYFUNCTION("""COMPUTED_VALUE"""),2891.0) -> 2891 | X14: =(VLOOKUP(W14,'BD LUB'!$A$2:$L$223,5,FALSE)/VLOOKUP(W14,'BD LUB'!$A$2:$L$223,7,FALSE))+(VLOOKUP(W14,'BD LUB'!$A$2:$L$223,6,FALSE)/VLOOKUP(W14,'BD LUB'!$A$2:$L$223,8,FALSE)) -> 1.5141556 | Y14: =IF(AND(VLOOKUP(W14,'BD LUB'!$A$2:$L$223,11,FALSE)="PASADO",VLOOKUP(W14,'BD LUB'!$A$2:$L$223,12,FALSE)="PASADO"),1,IF(OR(AND(VLOOKUP(W14,'BD LUB'!$A$2:$L$223,11,FALSE)="PASADO",VLOOKUP(W14,'BD LUB'!$A$2:$L$223,12,FALSE)="PRÓXIMO"),AND(VLOOKUP(W14,'BD LUB'!$A$2:$L$223,11,FALSE)="PRÓXIMO",VLOOKUP(W14,'BD LUB'!$A$2:$L$223,12,FALSE)="PASADO")),2,IF(OR(AND(VLOOKUP(W14,'BD LUB'!$A$2:$L$223,11,FALSE)="PASADO",VLOOKUP(W14,'BD LUB'!$A$2:$L$223,12,FALSE)="VIGENTE"),AND(VLOOKUP(W14,'BD LUB'!$A$2:$L$223,11,FALSE)="VIGENTE",VLOOKUP(W14,'BD LUB'!$A$2:$L$223,12,FALSE)="PASADO")),3,IF(AND(VLOOKUP(W14,'BD LUB'!$A$2:$L$223,11,FALSE)="PRÓXIMO",VLOOKUP(W14,'BD LUB'!$A$2:$L$223,12,FALSE)="PRÓXIMO"),4,IF(OR(AND(VLOOKUP(W14,'BD LUB'!$A$2:$L$223,11,FALSE)="PRÓXIMO",VLOOKUP(W14,'BD LUB'!$A$2:$L$223,12,FALSE)="VIGENTE"),AND(VLOOKUP(W14,'BD LUB'!$A$2:$L$223,11,FALSE)="VIGENTE",VLOOKUP(W14,'BD LUB'!$A$2:$L$223,12,FALSE)="PRÓXIMO")),5,IF(AND(VLOOKUP(W14,'BD LUB'!$A$2:$L$223,11,FALSE)="VIGENTE",VLOOKUP(W14,'BD LUB'!$A$2:$L$223,12,FALSE)="VIGENTE"),6,"No definido")))))) -> 5 | Z14: =IFERROR(__xludf.DUMMYFUNCTION("""COMPUTED_VALUE"""),2643.0) -> 2643 | AA14: =(VLOOKUP(Z14,'BD LUB'!$A$2:$L$223,5,FALSE)/VLOOKUP(Z14,'BD LUB'!$A$2:$L$223,7,FALSE))+(VLOOKUP(Z14,'BD LUB'!$A$2:$L$223,6,FALSE)/VLOOKUP(Z14,'BD LUB'!$A$2:$L$223,8,FALSE)) -> 1.5930444 | AB14: =IF(AND(VLOOKUP(Z14,'BD LUB'!$A$2:$L$223,11,FALSE)="PASADO",VLOOKUP(Z14,'BD LUB'!$A$2:$L$223,12,FALSE)="PASADO"),1,IF(OR(AND(VLOOKUP(Z14,'BD LUB'!$A$2:$L$223,11,FALSE)="PASADO",VLOOKUP(Z14,'BD LUB'!$A$2:$L$223,12,FALSE)="PRÓXIMO"),AND(VLOOKUP(Z14,'BD LUB'!$A$2:$L$223,11,FALSE)="PRÓXIMO",VLOOKUP(Z14,'BD LUB'!$A$2:$L$223,12,FALSE)="PASADO")),2,IF(OR(AND(VLOOKUP(Z14,'BD LUB'!$A$2:$L$223,11,FALSE)="PASADO",VLOOKUP(Z14,'BD LUB'!$A$2:$L$223,12,FALSE)="VIGENTE"),AND(VLOOKUP(Z14,'BD LUB'!$A$2:$L$223,11,FALSE)="VIGENTE",VLOOKUP(Z14,'BD LUB'!$A$2:$L$223,12,FALSE)="PASADO")),3,IF(AND(VLOOKUP(Z14,'BD LUB'!$A$2:$L$223,11,FALSE)="PRÓXIMO",VLOOKUP(Z14,'BD LUB'!$A$2:$L$223,12,FALSE)="PRÓXIMO"),4,IF(OR(AND(VLOOKUP(Z14,'BD LUB'!$A$2:$L$223,11,FALSE)="PRÓXIMO",VLOOKUP(Z14,'BD LUB'!$A$2:$L$223,12,FALSE)="VIGENTE"),AND(VLOOKUP(Z14,'BD LUB'!$A$2:$L$223,11,FALSE)="VIGENTE",VLOOKUP(Z14,'BD LUB'!$A$2:$L$223,12,FALSE)="PRÓXIMO")),5,IF(AND(VLOOKUP(Z14,'BD LUB'!$A$2:$L$223,11,FALSE)="VIGENTE",VLOOKUP(Z14,'BD LUB'!$A$2:$L$223,12,FALSE)="VIGENTE"),6,"No definido")))))) -> 5 | AC14: =IFERROR(__xludf.DUMMYFUNCTION("""COMPUTED_VALUE"""),2663.0) -> 2663 | AD14: =IF(VLOOKUP(AC14,'BD LUB'!$A$2:$C$223,3,FALSE)=$AH$20,AC14&" MED",IF(VLOOKUP(AC14,'BD LUB'!$A$2:$C$223,3,FALSE)=$AH$19,AC14&" MAY",IF(VLOOKUP(AC14,'BD LUB'!$A$2:$C$223,3,FALSE)=$AH$18,AC14&" RN",IF(VLOOKUP(AC14,'BD LUB'!$A$2:$C$223,3,FALSE)=$AH$17,AC14&" COPQUI",IF(VLOOKUP(AC14,'BD LUB'!$A$2:$C$223,3,FALSE)=$AH$16,AC14&" CEJ",IF(VLOOKUP(AC14,'BD LUB'!$A$2:$C$223,3,FALSE)=$AH$15,AC14&" BULT",IF(VLOOKUP(AC14,'BD LUB'!$A$2:$C$223,3,FALSE)=$AH$14,AC14&" COP",IF(VLOOKUP(AC14,'BD LUB'!$A$2:$C$223,3,FALSE)=$AH$13,AC14&" RIO",IF(VLOOKUP(AC14,'BD LUB'!$A$2:$C$223,3,FALSE)=$AH$21,AC14&" APART","Dato no encontrado"))))))))) -> 2663 RIO | AH14: 31-Copacabana | AJ14: 11 | AK14: =IFERROR(__xludf.DUMMYFUNCTION("""COMPUTED_VALUE"""),46668.0) -> 46668 | AL14: =IFERROR(__xludf.DUMMYFUNCTION("""COMPUTED_VALUE"""),"02-Medellin") -> 02-Medellin | AM14: =IFERROR(__xludf.DUMMYFUNCTION("""COMPUTED_VALUE"""),138.0) -> 138 | AN14: =IFERROR(__xludf.DUMMYFUNCTION("""COMPUTED_VALUE"""),700.0) -> 700 | AP14: 11 | AQ14: =IFERROR(__xludf.DUMMYFUNCTION("""COMPUTED_VALUE"""),46668.0) -> 46668 | AR14: =IFERROR(__xludf.DUMMYFUNCTION("""COMPUTED_VALUE"""),"02-Medellin") -> 02-Medellin | AS14: =IFERROR(__xludf.DUMMYFUNCTION("""COMPUTED_VALUE"""),138.0) -> 138 | AT14: =IFERROR(__xludf.DUMMYFUNCTION("""COMPUTED_VALUE"""),700.0) -> 700 | AV14: 11
B15: 12 | C15: =IFERROR(__xludf.DUMMYFUNCTION("""COMPUTED_VALUE"""),2230.0) -> 2230 | D15: =IFERROR(__xludf.DUMMYFUNCTION("""COMPUTED_VALUE"""),46570.0) -> 46570 | E15: =IFERROR(__xludf.DUMMYFUNCTION("""COMPUTED_VALUE"""),"02-Medellin") -> 02-Medellin | F15: =IFERROR(__xludf.DUMMYFUNCTION("""COMPUTED_VALUE"""),46008.0) -> 46008 | G15: =IFERROR(__xludf.DUMMYFUNCTION("""COMPUTED_VALUE"""),-28.0) -> -28 | H15: =IFERROR(__xludf.DUMMYFUNCTION("""COMPUTED_VALUE"""),"PASADO") -> PASADO | I15: =IF(OR(H15="PASADO",H15="PRÓXIMO"), IF(AND(NOT(ISERROR(MATCH(C15,$T$4:$T$195,0))),NOT(ISERROR(MATCH(C15,$U$4:$U$195,0)))),"HECHO",IF(NOT(ISERROR(MATCH(C15,$U$4:$U$195,0))),"PEDIDO","NO PEDIDO")),"-") -> HECHO | K15: 12 | L15: =IFERROR(__xludf.DUMMYFUNCTION("""COMPUTED_VALUE"""),2663.0) -> 2663 | M15: =IFERROR(__xludf.DUMMYFUNCTION("""COMPUTED_VALUE"""),46493.0) -> 46493 | N15: =IFERROR(__xludf.DUMMYFUNCTION("""COMPUTED_VALUE"""),"24-Rionegro") -> 24-Rionegro | O15: =IFERROR(__xludf.DUMMYFUNCTION("""COMPUTED_VALUE"""),46056.0) -> 46056 | P15: =IFERROR(__xludf.DUMMYFUNCTION("""COMPUTED_VALUE"""),-1436.1000000000004) -> -1436.1 | Q15: =IFERROR(__xludf.DUMMYFUNCTION("""COMPUTED_VALUE"""),"PASADO") -> PASADO | R15: =IF(OR(Q15="PASADO",Q15="PRÓXIMO"), IF(AND(NOT(ISERROR(MATCH(L15,$T$4:$T$195,0))),NOT(ISERROR(MATCH(L15,$U$4:$U$195,0)))),"HECHO",IF(NOT(ISERROR(MATCH(L15,$U$4:$U$195,0))),"PEDIDO","NO PEDIDO")),"-") -> PEDIDO | T15: =CALENDARIO!D27 -> 2572 | U15: =CALENDARIO!C27 -> 3283 | W15: =IFERROR(__xludf.DUMMYFUNCTION("""COMPUTED_VALUE"""),2908.0) -> 2908 | X15: =(VLOOKUP(W15,'BD LUB'!$A$2:$L$223,5,FALSE)/VLOOKUP(W15,'BD LUB'!$A$2:$L$223,7,FALSE))+(VLOOKUP(W15,'BD LUB'!$A$2:$L$223,6,FALSE)/VLOOKUP(W15,'BD LUB'!$A$2:$L$223,8,FALSE)) -> 1.3164 | Y15: =IF(AND(VLOOKUP(W15,'BD LUB'!$A$2:$L$223,11,FALSE)="PASADO",VLOOKUP(W15,'BD LUB'!$A$2:$L$223,12,FALSE)="PASADO"),1,IF(OR(AND(VLOOKUP(W15,'BD LUB'!$A$2:$L$223,11,FALSE)="PASADO",VLOOKUP(W15,'BD LUB'!$A$2:$L$223,12,FALSE)="PRÓXIMO"),AND(VLOOKUP(W15,'BD LUB'!$A$2:$L$223,11,FALSE)="PRÓXIMO",VLOOKUP(W15,'BD LUB'!$A$2:$L$223,12,FALSE)="PASADO")),2,IF(OR(AND(VLOOKUP(W15,'BD LUB'!$A$2:$L$223,11,FALSE)="PASADO",VLOOKUP(W15,'BD LUB'!$A$2:$L$223,12,FALSE)="VIGENTE"),AND(VLOOKUP(W15,'BD LUB'!$A$2:$L$223,11,FALSE)="VIGENTE",VLOOKUP(W15,'BD LUB'!$A$2:$L$223,12,FALSE)="PASADO")),3,IF(AND(VLOOKUP(W15,'BD LUB'!$A$2:$L$223,11,FALSE)="PRÓXIMO",VLOOKUP(W15,'BD LUB'!$A$2:$L$223,12,FALSE)="PRÓXIMO"),4,IF(OR(AND(VLOOKUP(W15,'BD LUB'!$A$2:$L$223,11,FALSE)="PRÓXIMO",VLOOKUP(W15,'BD LUB'!$A$2:$L$223,12,FALSE)="VIGENTE"),AND(VLOOKUP(W15,'BD LUB'!$A$2:$L$223,11,FALSE)="VIGENTE",VLOOKUP(W15,'BD LUB'!$A$2:$L$223,12,FALSE)="PRÓXIMO")),5,IF(AND(VLOOKUP(W15,'BD LUB'!$A$2:$L$223,11,FALSE)="VIGENTE",VLOOKUP(W15,'BD LUB'!$A$2:$L$223,12,FALSE)="VIGENTE"),6,"No definido")))))) -> 5 | Z15: =IFERROR(__xludf.DUMMYFUNCTION("""COMPUTED_VALUE"""),2640.0) -> 2640 | AA15: =(VLOOKUP(Z15,'BD LUB'!$A$2:$L$223,5,FALSE)/VLOOKUP(Z15,'BD LUB'!$A$2:$L$223,7,FALSE))+(VLOOKUP(Z15,'BD LUB'!$A$2:$L$223,6,FALSE)/VLOOKUP(Z15,'BD LUB'!$A$2:$L$223,8,FALSE)) -> 1.4219444 | AB15: =IF(AND(VLOOKUP(Z15,'BD LUB'!$A$2:$L$223,11,FALSE)="PASADO",VLOOKUP(Z15,'BD LUB'!$A$2:$L$223,12,FALSE)="PASADO"),1,IF(OR(AND(VLOOKUP(Z15,'BD LUB'!$A$2:$L$223,11,FALSE)="PASADO",VLOOKUP(Z15,'BD LUB'!$A$2:$L$223,12,FALSE)="PRÓXIMO"),AND(VLOOKUP(Z15,'BD LUB'!$A$2:$L$223,11,FALSE)="PRÓXIMO",VLOOKUP(Z15,'BD LUB'!$A$2:$L$223,12,FALSE)="PASADO")),2,IF(OR(AND(VLOOKUP(Z15,'BD LUB'!$A$2:$L$223,11,FALSE)="PASADO",VLOOKUP(Z15,'BD LUB'!$A$2:$L$223,12,FALSE)="VIGENTE"),AND(VLOOKUP(Z15,'BD LUB'!$A$2:$L$223,11,FALSE)="VIGENTE",VLOOKUP(Z15,'BD LUB'!$A$2:$L$223,12,FALSE)="PASADO")),3,IF(AND(VLOOKUP(Z15,'BD LUB'!$A$2:$L$223,11,FALSE)="PRÓXIMO",VLOOKUP(Z15,'BD LUB'!$A$2:$L$223,12,FALSE)="PRÓXIMO"),4,IF(OR(AND(VLOOKUP(Z15,'BD LUB'!$A$2:$L$223,11,FALSE)="PRÓXIMO",VLOOKUP(Z15,'BD LUB'!$A$2:$L$223,12,FALSE)="VIGENTE"),AND(VLOOKUP(Z15,'BD LUB'!$A$2:$L$223,11,FALSE)="VIGENTE",VLOOKUP(Z15,'BD LUB'!$A$2:$L$223,12,FALSE)="PRÓXIMO")),5,IF(AND(VLOOKUP(Z15,'BD LUB'!$A$2:$L$223,11,FALSE)="VIGENTE",VLOOKUP(Z15,'BD LUB'!$A$2:$L$223,12,FALSE)="VIGENTE"),6,"No definido")))))) -> 5 | AC15: =IFERROR(__xludf.DUMMYFUNCTION("""COMPUTED_VALUE"""),2424.0) -> 2424 | AD15: =IF(VLOOKUP(AC15,'BD LUB'!$A$2:$C$223,3,FALSE)=$AH$20,AC15&" MED",IF(VLOOKUP(AC15,'BD LUB'!$A$2:$C$223,3,FALSE)=$AH$19,AC15&" MAY",IF(VLOOKUP(AC15,'BD LUB'!$A$2:$C$223,3,FALSE)=$AH$18,AC15&" RN",IF(VLOOKUP(AC15,'BD LUB'!$A$2:$C$223,3,FALSE)=$AH$17,AC15&" COPQUI",IF(VLOOKUP(AC15,'BD LUB'!$A$2:$C$223,3,FALSE)=$AH$16,AC15&" CEJ",IF(VLOOKUP(AC15,'BD LUB'!$A$2:$C$223,3,FALSE)=$AH$15,AC15&" BULT",IF(VLOOKUP(AC15,'BD LUB'!$A$2:$C$223,3,FALSE)=$AH$14,AC15&" COP",IF(VLOOKUP(AC15,'BD LUB'!$A$2:$C$223,3,FALSE)=$AH$13,AC15&" RIO",IF(VLOOKUP(AC15,'BD LUB'!$A$2:$C$223,3,FALSE)=$AH$21,AC15&" APART","Dato no encontrado"))))))))) -> 2424 MED | AH15: BULTOS | AJ15: 12 | AK15: =IFERROR(__xludf.DUMMYFUNCTION("""COMPUTED_VALUE"""),46668.0) -> 46668 | AL15: =IFERROR(__xludf.DUMMYFUNCTION("""COMPUTED_VALUE"""),"02-Medellin") -> 02-Medellin | AM15: =IFERROR(__xludf.DUMMYFUNCTION("""COMPUTED_VALUE"""),138.0) -> 138 | AP15: 12 | AQ15: =IFERROR(__xludf.DUMMYFUNCTION("""COMPUTED_VALUE"""),46668.0) -> 46668 | AR15: =IFERROR(__xludf.DUMMYFUNCTION("""COMPUTED_VALUE"""),"02-Medellin") -> 02-Medellin | AS15: =IFERROR(__xludf.DUMMYFUNCTION("""COMPUTED_VALUE"""),138.0) -> 138 | AV15: 12
B16: 13 | C16: =IFERROR(__xludf.DUMMYFUNCTION("""COMPUTED_VALUE"""),2424.0) -> 2424 | D16: =IFERROR(__xludf.DUMMYFUNCTION("""COMPUTED_VALUE"""),46528.0) -> 46528 | E16: =IFERROR(__xludf.DUMMYFUNCTION("""COMPUTED_VALUE"""),"02-Medellin") -> 02-Medellin | F16: =IFERROR(__xludf.DUMMYFUNCTION("""COMPUTED_VALUE"""),46009.0) -> 46009 | G16: =IFERROR(__xludf.DUMMYFUNCTION("""COMPUTED_VALUE"""),-27.0) -> -27 | H16: =IFERROR(__xludf.DUMMYFUNCTION("""COMPUTED_VALUE"""),"PASADO") -> PASADO | I16: =IF(OR(H16="PASADO",H16="PRÓXIMO"), IF(AND(NOT(ISERROR(MATCH(C16,$T$4:$T$195,0))),NOT(ISERROR(MATCH(C16,$U$4:$U$195,0)))),"HECHO",IF(NOT(ISERROR(MATCH(C16,$U$4:$U$195,0))),"PEDIDO","NO PEDIDO")),"-") -> PEDIDO | K16: 13 | L16: =IFERROR(__xludf.DUMMYFUNCTION("""COMPUTED_VALUE"""),2910.0) -> 2910 | M16: =IFERROR(__xludf.DUMMYFUNCTION("""COMPUTED_VALUE"""),46275.0) -> 46275 | N16: =IFERROR(__xludf.DUMMYFUNCTION("""COMPUTED_VALUE"""),"24-Rionegro") -> 24-Rionegro | O16: =IFERROR(__xludf.DUMMYFUNCTION("""COMPUTED_VALUE"""),46112.0) -> 46112 | P16: =IFERROR(__xludf.DUMMYFUNCTION("""COMPUTED_VALUE"""),-1394.0) -> -1394 | Q16: =IFERROR(__xludf.DUMMYFUNCTION("""COMPUTED_VALUE"""),"PASADO") -> PASADO | R16: =IF(OR(Q16="PASADO",Q16="PRÓXIMO"), IF(AND(NOT(ISERROR(MATCH(L16,$T$4:$T$195,0))),NOT(ISERROR(MATCH(L16,$U$4:$U$195,0)))),"HECHO",IF(NOT(ISERROR(MATCH(L16,$U$4:$U$195,0))),"PEDIDO","NO PEDIDO")),"-") -> PEDIDO | T16: =CALENDARIO!D28 -> 3251 | U16: =CALENDARIO!C28 -> 2903 | W16: =IFERROR(__xludf.DUMMYFUNCTION("""COMPUTED_VALUE"""),2895.0) -> 2895 | X16: =(VLOOKUP(W16,'BD LUB'!$A$2:$L$223,5,FALSE)/VLOOKUP(W16,'BD LUB'!$A$2:$L$223,7,FALSE))+(VLOOKUP(W16,'BD LUB'!$A$2:$L$223,6,FALSE)/VLOOKUP(W16,'BD LUB'!$A$2:$L$223,8,FALSE)) -> 1.1959333 | Y16: =IF(AND(VLOOKUP(W16,'BD LUB'!$A$2:$L$223,11,FALSE)="PASADO",VLOOKUP(W16,'BD LUB'!$A$2:$L$223,12,FALSE)="PASADO"),1,IF(OR(AND(VLOOKUP(W16,'BD LUB'!$A$2:$L$223,11,FALSE)="PASADO",VLOOKUP(W16,'BD LUB'!$A$2:$L$223,12,FALSE)="PRÓXIMO"),AND(VLOOKUP(W16,'BD LUB'!$A$2:$L$223,11,FALSE)="PRÓXIMO",VLOOKUP(W16,'BD LUB'!$A$2:$L$223,12,FALSE)="PASADO")),2,IF(OR(AND(VLOOKUP(W16,'BD LUB'!$A$2:$L$223,11,FALSE)="PASADO",VLOOKUP(W16,'BD LUB'!$A$2:$L$223,12,FALSE)="VIGENTE"),AND(VLOOKUP(W16,'BD LUB'!$A$2:$L$223,11,FALSE)="VIGENTE",VLOOKUP(W16,'BD LUB'!$A$2:$L$223,12,FALSE)="PASADO")),3,IF(AND(VLOOKUP(W16,'BD LUB'!$A$2:$L$223,11,FALSE)="PRÓXIMO",VLOOKUP(W16,'BD LUB'!$A$2:$L$223,12,FALSE)="PRÓXIMO"),4,IF(OR(AND(VLOOKUP(W16,'BD LUB'!$A$2:$L$223,11,FALSE)="PRÓXIMO",VLOOKUP(W16,'BD LUB'!$A$2:$L$223,12,FALSE)="VIGENTE"),AND(VLOOKUP(W16,'BD LUB'!$A$2:$L$223,11,FALSE)="VIGENTE",VLOOKUP(W16,'BD LUB'!$A$2:$L$223,12,FALSE)="PRÓXIMO")),5,IF(AND(VLOOKUP(W16,'BD LUB'!$A$2:$L$223,11,FALSE)="VIGENTE",VLOOKUP(W16,'BD LUB'!$A$2:$L$223,12,FALSE)="VIGENTE"),6,"No definido")))))) -> 5 | Z16: =IFERROR(__xludf.DUMMYFUNCTION("""COMPUTED_VALUE"""),2354.0) -> 2354 | AA16: =(VLOOKUP(Z16,'BD LUB'!$A$2:$L$223,5,FALSE)/VLOOKUP(Z16,'BD LUB'!$A$2:$L$223,7,FALSE))+(VLOOKUP(Z16,'BD LUB'!$A$2:$L$223,6,FALSE)/VLOOKUP(Z16,'BD LUB'!$A$2:$L$223,8,FALSE)) -> 1.6943644 | AB16: =IF(AND(VLOOKUP(Z16,'BD LUB'!$A$2:$L$223,11,FALSE)="PASADO",VLOOKUP(Z16,'BD LUB'!$A$2:$L$223,12,FALSE)="PASADO"),1,IF(OR(AND(VLOOKUP(Z16,'BD LUB'!$A$2:$L$223,11,FALSE)="PASADO",VLOOKUP(Z16,'BD LUB'!$A$2:$L$223,12,FALSE)="PRÓXIMO"),AND(VLOOKUP(Z16,'BD LUB'!$A$2:$L$223,11,FALSE)="PRÓXIMO",VLOOKUP(Z16,'BD LUB'!$A$2:$L$223,12,FALSE)="PASADO")),2,IF(OR(AND(VLOOKUP(Z16,'BD LUB'!$A$2:$L$223,11,FALSE)="PASADO",VLOOKUP(Z16,'BD LUB'!$A$2:$L$223,12,FALSE)="VIGENTE"),AND(VLOOKUP(Z16,'BD LUB'!$A$2:$L$223,11,FALSE)="VIGENTE",VLOOKUP(Z16,'BD LUB'!$A$2:$L$223,12,FALSE)="PASADO")),3,IF(AND(VLOOKUP(Z16,'BD LUB'!$A$2:$L$223,11,FALSE)="PRÓXIMO",VLOOKUP(Z16,'BD LUB'!$A$2:$L$223,12,FALSE)="PRÓXIMO"),4,IF(OR(AND(VLOOKUP(Z16,'BD LUB'!$A$2:$L$223,11,FALSE)="PRÓXIMO",VLOOKUP(Z16,'BD LUB'!$A$2:$L$223,12,FALSE)="VIGENTE"),AND(VLOOKUP(Z16,'BD LUB'!$A$2:$L$223,11,FALSE)="VIGENTE",VLOOKUP(Z16,'BD LUB'!$A$2:$L$223,12,FALSE)="PRÓXIMO")),5,IF(AND(VLOOKUP(Z16,'BD LUB'!$A$2:$L$223,11,FALSE)="VIGENTE",VLOOKUP(Z16,'BD LUB'!$A$2:$L$223,12,FALSE)="VIGENTE"),6,"No definido")))))) -> 5 | AC16: =IFERROR(__xludf.DUMMYFUNCTION("""COMPUTED_VALUE"""),2460.0) -> 2460 | AD16: =IF(VLOOKUP(AC16,'BD LUB'!$A$2:$C$223,3,FALSE)=$AH$20,AC16&" MED",IF(VLOOKUP(AC16,'BD LUB'!$A$2:$C$223,3,FALSE)=$AH$19,AC16&" MAY",IF(VLOOKUP(AC16,'BD LUB'!$A$2:$C$223,3,FALSE)=$AH$18,AC16&" RN",IF(VLOOKUP(AC16,'BD LUB'!$A$2:$C$223,3,FALSE)=$AH$17,AC16&" COPQUI",IF(VLOOKUP(AC16,'BD LUB'!$A$2:$C$223,3,FALSE)=$AH$16,AC16&" CEJ",IF(VLOOKUP(AC16,'BD LUB'!$A$2:$C$223,3,FALSE)=$AH$15,AC16&" BULT",IF(VLOOKUP(AC16,'BD LUB'!$A$2:$C$223,3,FALSE)=$AH$14,AC16&" COP",IF(VLOOKUP(AC16,'BD LUB'!$A$2:$C$223,3,FALSE)=$AH$13,AC16&" RIO",IF(VLOOKUP(AC16,'BD LUB'!$A$2:$C$223,3,FALSE)=$AH$21,AC16&" APART","Dato no encontrado"))))))))) -> 2460 BULT | AH16: 38-La ceja | AJ16: 13 | AK16: =IFERROR(__xludf.DUMMYFUNCTION("""COMPUTED_VALUE"""),46653.0) -> 46653 | AL16: =IFERROR(__xludf.DUMMYFUNCTION("""COMPUTED_VALUE"""),"02-Medellin") -> 02-Medellin | AM16: =IFERROR(__xludf.DUMMYFUNCTION("""COMPUTED_VALUE"""),138.0) -> 138 | AP16: 13 | AQ16: =IFERROR(__xludf.DUMMYFUNCTION("""COMPUTED_VALUE"""),46653.0) -> 46653 | AR16: =IFERROR(__xludf.DUMMYFUNCTION("""COMPUTED_VALUE"""),"02-Medellin") -> 02-Medellin | AS16: =IFERROR(__xludf.DUMMYFUNCTION("""COMPUTED_VALUE"""),138.0) -> 138 | AV16: 13
B17: 14 | C17: =IFERROR(__xludf.DUMMYFUNCTION("""COMPUTED_VALUE"""),2450.0) -> 2450 | D17: =IFERROR(__xludf.DUMMYFUNCTION("""COMPUTED_VALUE"""),46290.0) -> 46290 | E17: =IFERROR(__xludf.DUMMYFUNCTION("""COMPUTED_VALUE"""),"MAYORCA") -> MAYORCA | F17: =IFERROR(__xludf.DUMMYFUNCTION("""COMPUTED_VALUE"""),46027.0) -> 46027 | G17: =IFERROR(__xludf.DUMMYFUNCTION("""COMPUTED_VALUE"""),-9.0) -> -9 | H17: =IFERROR(__xludf.DUMMYFUNCTION("""COMPUTED_VALUE"""),"PASADO") -> PASADO | I17: =IF(OR(H17="PASADO",H17="PRÓXIMO"), IF(AND(NOT(ISERROR(MATCH(C17,$T$4:$T$195,0))),NOT(ISERROR(MATCH(C17,$U$4:$U$195,0)))),"HECHO",IF(NOT(ISERROR(MATCH(C17,$U$4:$U$195,0))),"PEDIDO","NO PEDIDO")),"-") -> HECHO | K17: 14 | L17: =IFERROR(__xludf.DUMMYFUNCTION("""COMPUTED_VALUE"""),2877.0) -> 2877 | M17: =IFERROR(__xludf.DUMMYFUNCTION("""COMPUTED_VALUE"""),46226.0) -> 46226 | N17: =IFERROR(__xludf.DUMMYFUNCTION("""COMPUTED_VALUE"""),"MAYORCA") -> MAYORCA | O17: =IFERROR(__xludf.DUMMYFUNCTION("""COMPUTED_VALUE"""),46135.0) -> 46135 | P17: =IFERROR(__xludf.DUMMYFUNCTION("""COMPUTED_VALUE"""),-1344.0) -> -1344 | Q17: =IFERROR(__xludf.DUMMYFUNCTION("""COMPUTED_VALUE"""),"PASADO") -> PASADO | R17: =IF(OR(Q17="PASADO",Q17="PRÓXIMO"), IF(AND(NOT(ISERROR(MATCH(L17,$T$4:$T$195,0))),NOT(ISERROR(MATCH(L17,$U$4:$U$195,0)))),"HECHO",IF(NOT(ISERROR(MATCH(L17,$U$4:$U$195,0))),"PEDIDO","NO PEDIDO")),"-") -> HECHO | T17: =CALENDARIO!D29 -> 2682 | U17: =CALENDARIO!C29 -> 2424 | W17: =IFERROR(__xludf.DUMMYFUNCTION("""COMPUTED_VALUE"""),3213.0) -> 3213 | X17: =(VLOOKUP(W17,'BD LUB'!$A$2:$L$223,5,FALSE)/VLOOKUP(W17,'BD LUB'!$A$2:$L$223,7,FALSE))+(VLOOKUP(W17,'BD LUB'!$A$2:$L$223,6,FALSE)/VLOOKUP(W17,'BD LUB'!$A$2:$L$223,8,FALSE)) -> 1.5560444 | Y17: =IF(AND(VLOOKUP(W17,'BD LUB'!$A$2:$L$223,11,FALSE)="PASADO",VLOOKUP(W17,'BD LUB'!$A$2:$L$223,12,FALSE)="PASADO"),1,IF(OR(AND(VLOOKUP(W17,'BD LUB'!$A$2:$L$223,11,FALSE)="PASADO",VLOOKUP(W17,'BD LUB'!$A$2:$L$223,12,FALSE)="PRÓXIMO"),AND(VLOOKUP(W17,'BD LUB'!$A$2:$L$223,11,FALSE)="PRÓXIMO",VLOOKUP(W17,'BD LUB'!$A$2:$L$223,12,FALSE)="PASADO")),2,IF(OR(AND(VLOOKUP(W17,'BD LUB'!$A$2:$L$223,11,FALSE)="PASADO",VLOOKUP(W17,'BD LUB'!$A$2:$L$223,12,FALSE)="VIGENTE"),AND(VLOOKUP(W17,'BD LUB'!$A$2:$L$223,11,FALSE)="VIGENTE",VLOOKUP(W17,'BD LUB'!$A$2:$L$223,12,FALSE)="PASADO")),3,IF(AND(VLOOKUP(W17,'BD LUB'!$A$2:$L$223,11,FALSE)="PRÓXIMO",VLOOKUP(W17,'BD LUB'!$A$2:$L$223,12,FALSE)="PRÓXIMO"),4,IF(OR(AND(VLOOKUP(W17,'BD LUB'!$A$2:$L$223,11,FALSE)="PRÓXIMO",VLOOKUP(W17,'BD LUB'!$A$2:$L$223,12,FALSE)="VIGENTE"),AND(VLOOKUP(W17,'BD LUB'!$A$2:$L$223,11,FALSE)="VIGENTE",VLOOKUP(W17,'BD LUB'!$A$2:$L$223,12,FALSE)="PRÓXIMO")),5,IF(AND(VLOOKUP(W17,'BD LUB'!$A$2:$L$223,11,FALSE)="VIGENTE",VLOOKUP(W17,'BD LUB'!$A$2:$L$223,12,FALSE)="VIGENTE"),6,"No definido")))))) -> 5 | Z17: =IFERROR(__xludf.DUMMYFUNCTION("""COMPUTED_VALUE"""),487.0) -> 487 | AA17: =(VLOOKUP(Z17,'BD LUB'!$A$2:$L$223,5,FALSE)/VLOOKUP(Z17,'BD LUB'!$A$2:$L$223,7,FALSE))+(VLOOKUP(Z17,'BD LUB'!$A$2:$L$223,6,FALSE)/VLOOKUP(Z17,'BD LUB'!$A$2:$L$223,8,FALSE)) -> 1.6356644 | AB17: =IF(AND(VLOOKUP(Z17,'BD LUB'!$A$2:$L$223,11,FALSE)="PASADO",VLOOKUP(Z17,'BD LUB'!$A$2:$L$223,12,FALSE)="PASADO"),1,IF(OR(AND(VLOOKUP(Z17,'BD LUB'!$A$2:$L$223,11,FALSE)="PASADO",VLOOKUP(Z17,'BD LUB'!$A$2:$L$223,12,FALSE)="PRÓXIMO"),AND(VLOOKUP(Z17,'BD LUB'!$A$2:$L$223,11,FALSE)="PRÓXIMO",VLOOKUP(Z17,'BD LUB'!$A$2:$L$223,12,FALSE)="PASADO")),2,IF(OR(AND(VLOOKUP(Z17,'BD LUB'!$A$2:$L$223,11,FALSE)="PASADO",VLOOKUP(Z17,'BD LUB'!$A$2:$L$223,12,FALSE)="VIGENTE"),AND(VLOOKUP(Z17,'BD LUB'!$A$2:$L$223,11,FALSE)="VIGENTE",VLOOKUP(Z17,'BD LUB'!$A$2:$L$223,12,FALSE)="PASADO")),3,IF(AND(VLOOKUP(Z17,'BD LUB'!$A$2:$L$223,11,FALSE)="PRÓXIMO",VLOOKUP(Z17,'BD LUB'!$A$2:$L$223,12,FALSE)="PRÓXIMO"),4,IF(OR(AND(VLOOKUP(Z17,'BD LUB'!$A$2:$L$223,11,FALSE)="PRÓXIMO",VLOOKUP(Z17,'BD LUB'!$A$2:$L$223,12,FALSE)="VIGENTE"),AND(VLOOKUP(Z17,'BD LUB'!$A$2:$L$223,11,FALSE)="VIGENTE",VLOOKUP(Z17,'BD LUB'!$A$2:$L$223,12,FALSE)="PRÓXIMO")),5,IF(AND(VLOOKUP(Z17,'BD LUB'!$A$2:$L$223,11,FALSE)="VIGENTE",VLOOKUP(Z17,'BD LUB'!$A$2:$L$223,12,FALSE)="VIGENTE"),6,"No definido")))))) -> 5 | AC17: =IFERROR(__xludf.DUMMYFUNCTION("""COMPUTED_VALUE"""),2673.0) -> 2673 | AD17: =IF(VLOOKUP(AC17,'BD LUB'!$A$2:$C$223,3,FALSE)=$AH$20,AC17&" MED",IF(VLOOKUP(AC17,'BD LUB'!$A$2:$C$223,3,FALSE)=$AH$19,AC17&" MAY",IF(VLOOKUP(AC17,'BD LUB'!$A$2:$C$223,3,FALSE)=$AH$18,AC17&" RN",IF(VLOOKUP(AC17,'BD LUB'!$A$2:$C$223,3,FALSE)=$AH$17,AC17&" COPQUI",IF(VLOOKUP(AC17,'BD LUB'!$A$2:$C$223,3,FALSE)=$AH$16,AC17&" CEJ",IF(VLOOKUP(AC17,'BD LUB'!$A$2:$C$223,3,FALSE)=$AH$15,AC17&" BULT",IF(VLOOKUP(AC17,'BD LUB'!$A$2:$C$223,3,FALSE)=$AH$14,AC17&" COP",IF(VLOOKUP(AC17,'BD LUB'!$A$2:$C$223,3,FALSE)=$AH$13,AC17&" RIO",IF(VLOOKUP(AC17,'BD LUB'!$A$2:$C$223,3,FALSE)=$AH$21,AC17&" APART","Dato no encontrado"))))))))) -> 2673 MED | AH17: 31-Copacabana QUIMICOS | AJ17: 14 | AK17: =IFERROR(__xludf.DUMMYFUNCTION("""COMPUTED_VALUE"""),46275.0) -> 46275 | AL17: =IFERROR(__xludf.DUMMYFUNCTION("""COMPUTED_VALUE"""),"02-Medellin") -> 02-Medellin | AM17: =IFERROR(__xludf.DUMMYFUNCTION("""COMPUTED_VALUE"""),132.0) -> 132 | AP17: 14 | AQ17: =IFERROR(__xludf.DUMMYFUNCTION("""COMPUTED_VALUE"""),46275.0) -> 46275 | AR17: =IFERROR(__xludf.DUMMYFUNCTION("""COMPUTED_VALUE"""),"02-Medellin") -> 02-Medellin | AS17: =IFERROR(__xludf.DUMMYFUNCTION("""COMPUTED_VALUE"""),132.0) -> 132 | AV17: 14
B18: 15 | C18: =IFERROR(__xludf.DUMMYFUNCTION("""COMPUTED_VALUE"""),2425.0) -> 2425 | D18: =IFERROR(__xludf.DUMMYFUNCTION("""COMPUTED_VALUE"""),46477.0) -> 46477 | E18: =IFERROR(__xludf.DUMMYFUNCTION("""COMPUTED_VALUE"""),"BULTOS") -> BULTOS | F18: =IFERROR(__xludf.DUMMYFUNCTION("""COMPUTED_VALUE"""),46027.0) -> 46027 | G18: =IFERROR(__xludf.DUMMYFUNCTION("""COMPUTED_VALUE"""),-9.0) -> -9 | H18: =IFERROR(__xludf.DUMMYFUNCTION("""COMPUTED_VALUE"""),"PASADO") -> PASADO | I18: =IF(OR(H18="PASADO",H18="PRÓXIMO"), IF(AND(NOT(ISERROR(MATCH(C18,$T$4:$T$195,0))),NOT(ISERROR(MATCH(C18,$U$4:$U$195,0)))),"HECHO",IF(NOT(ISERROR(MATCH(C18,$U$4:$U$195,0))),"PEDIDO","NO PEDIDO")),"-") -> HECHO | K18: 15 | L18: =IFERROR(__xludf.DUMMYFUNCTION("""COMPUTED_VALUE"""),3283.0) -> 3283 | M18: =IFERROR(__xludf.DUMMYFUNCTION("""COMPUTED_VALUE"""),46668.0) -> 46668 | N18: =IFERROR(__xludf.DUMMYFUNCTION("""COMPUTED_VALUE"""),"02-Medellin") -> 02-Medellin | O18: =IFERROR(__xludf.DUMMYFUNCTION("""COMPUTED_VALUE"""),46062.0) -> 46062 | P18: =IFERROR(__xludf.DUMMYFUNCTION("""COMPUTED_VALUE"""),-1291.0) -> -1291 | Q18: =IFERROR(__xludf.DUMMYFUNCTION("""COMPUTED_VALUE"""),"PASADO") -> PASADO | R18: =IF(OR(Q18="PASADO",Q18="PRÓXIMO"), IF(AND(NOT(ISERROR(MATCH(L18,$T$4:$T$195,0))),NOT(ISERROR(MATCH(L18,$U$4:$U$195,0)))),"HECHO",IF(NOT(ISERROR(MATCH(L18,$U$4:$U$195,0))),"PEDIDO","NO PEDIDO")),"-") -> PEDIDO | T18: =CALENDARIO!D30 -> 2926 | U18: =CALENDARIO!C30 -> 2673 | X18: =(VLOOKUP(W18,'BD LUB'!$A$2:$L$223,5,FALSE)/VLOOKUP(W18,'BD LUB'!$A$2:$L$223,7,FALSE))+(VLOOKUP(W18,'BD LUB'!$A$2:$L$223,6,FALSE)/VLOOKUP(W18,'BD LUB'!$A$2:$L$223,8,FALSE)) -> #N/A | Y18: =IF(AND(VLOOKUP(W18,'BD LUB'!$A$2:$L$223,11,FALSE)="PASADO",VLOOKUP(W18,'BD LUB'!$A$2:$L$223,12,FALSE)="PASADO"),1,IF(OR(AND(VLOOKUP(W18,'BD LUB'!$A$2:$L$223,11,FALSE)="PASADO",VLOOKUP(W18,'BD LUB'!$A$2:$L$223,12,FALSE)="PRÓXIMO"),AND(VLOOKUP(W18,'BD LUB'!$A$2:$L$223,11,FALSE)="PRÓXIMO",VLOOKUP(W18,'BD LUB'!$A$2:$L$223,12,FALSE)="PASADO")),2,IF(OR(AND(VLOOKUP(W18,'BD LUB'!$A$2:$L$223,11,FALSE)="PASADO",VLOOKUP(W18,'BD LUB'!$A$2:$L$223,12,FALSE)="VIGENTE"),AND(VLOOKUP(W18,'BD LUB'!$A$2:$L$223,11,FALSE)="VIGENTE",VLOOKUP(W18,'BD LUB'!$A$2:$L$223,12,FALSE)="PASADO")),3,IF(AND(VLOOKUP(W18,'BD LUB'!$A$2:$L$223,11,FALSE)="PRÓXIMO",VLOOKUP(W18,'BD LUB'!$A$2:$L$223,12,FALSE)="PRÓXIMO"),4,IF(OR(AND(VLOOKUP(W18,'BD LUB'!$A$2:$L$223,11,FALSE)="PRÓXIMO",VLOOKUP(W18,'BD LUB'!$A$2:$L$223,12,FALSE)="VIGENTE"),AND(VLOOKUP(W18,'BD LUB'!$A$2:$L$223,11,FALSE)="VIGENTE",VLOOKUP(W18,'BD LUB'!$A$2:$L$223,12,FALSE)="PRÓXIMO")),5,IF(AND(VLOOKUP(W18,'BD LUB'!$A$2:$L$223,11,FALSE)="VIGENTE",VLOOKUP(W18,'BD LUB'!$A$2:$L$223,12,FALSE)="VIGENTE"),6,"No definido")))))) -> #N/A | Z18: =IFERROR(__xludf.DUMMYFUNCTION("""COMPUTED_VALUE"""),2881.0) -> 2881 | AA18: =(VLOOKUP(Z18,'BD LUB'!$A$2:$L$223,5,FALSE)/VLOOKUP(Z18,'BD LUB'!$A$2:$L$223,7,FALSE))+(VLOOKUP(Z18,'BD LUB'!$A$2:$L$223,6,FALSE)/VLOOKUP(Z18,'BD LUB'!$A$2:$L$223,8,FALSE)) -> 1.7469889 | AB18: =IF(AND(VLOOKUP(Z18,'BD LUB'!$A$2:$L$223,11,FALSE)="PASADO",VLOOKUP(Z18,'BD LUB'!$A$2:$L$223,12,FALSE)="PASADO"),1,IF(OR(AND(VLOOKUP(Z18,'BD LUB'!$A$2:$L$223,11,FALSE)="PASADO",VLOOKUP(Z18,'BD LUB'!$A$2:$L$223,12,FALSE)="PRÓXIMO"),AND(VLOOKUP(Z18,'BD LUB'!$A$2:$L$223,11,FALSE)="PRÓXIMO",VLOOKUP(Z18,'BD LUB'!$A$2:$L$223,12,FALSE)="PASADO")),2,IF(OR(AND(VLOOKUP(Z18,'BD LUB'!$A$2:$L$223,11,FALSE)="PASADO",VLOOKUP(Z18,'BD LUB'!$A$2:$L$223,12,FALSE)="VIGENTE"),AND(VLOOKUP(Z18,'BD LUB'!$A$2:$L$223,11,FALSE)="VIGENTE",VLOOKUP(Z18,'BD LUB'!$A$2:$L$223,12,FALSE)="PASADO")),3,IF(AND(VLOOKUP(Z18,'BD LUB'!$A$2:$L$223,11,FALSE)="PRÓXIMO",VLOOKUP(Z18,'BD LUB'!$A$2:$L$223,12,FALSE)="PRÓXIMO"),4,IF(OR(AND(VLOOKUP(Z18,'BD LUB'!$A$2:$L$223,11,FALSE)="PRÓXIMO",VLOOKUP(Z18,'BD LUB'!$A$2:$L$223,12,FALSE)="VIGENTE"),AND(VLOOKUP(Z18,'BD LUB'!$A$2:$L$223,11,FALSE)="VIGENTE",VLOOKUP(Z18,'BD LUB'!$A$2:$L$223,12,FALSE)="PRÓXIMO")),5,IF(AND(VLOOKUP(Z18,'BD LUB'!$A$2:$L$223,11,FALSE)="VIGENTE",VLOOKUP(Z18,'BD LUB'!$A$2:$L$223,12,FALSE)="VIGENTE"),6,"No definido")))))) -> 5 | AC18: =IFERROR(__xludf.DUMMYFUNCTION("""COMPUTED_VALUE"""),2910.0) -> 2910 | AD18: =IF(VLOOKUP(AC18,'BD LUB'!$A$2:$C$223,3,FALSE)=$AH$20,AC18&" MED",IF(VLOOKUP(AC18,'BD LUB'!$A$2:$C$223,3,FALSE)=$AH$19,AC18&" MAY",IF(VLOOKUP(AC18,'BD LUB'!$A$2:$C$223,3,FALSE)=$AH$18,AC18&" RN",IF(VLOOKUP(AC18,'BD LUB'!$A$2:$C$223,3,FALSE)=$AH$17,AC18&" COPQUI",IF(VLOOKUP(AC18,'BD LUB'!$A$2:$C$223,3,FALSE)=$AH$16,AC18&" CEJ",IF(VLOOKUP(AC18,'BD LUB'!$A$2:$C$223,3,FALSE)=$AH$15,AC18&" BULT",IF(VLOOKUP(AC18,'BD LUB'!$A$2:$C$223,3,FALSE)=$AH$14,AC18&" COP",IF(VLOOKUP(AC18,'BD LUB'!$A$2:$C$223,3,FALSE)=$AH$13,AC18&" RIO",IF(VLOOKUP(AC18,'BD LUB'!$A$2:$C$223,3,FALSE)=$AH$21,AC18&" APART","Dato no encontrado"))))))))) -> 2910 RIO | AH18: RN | AJ18: 15 | AK18: =IFERROR(__xludf.DUMMYFUNCTION("""COMPUTED_VALUE"""),46242.0) -> 46242 | AL18: =IFERROR(__xludf.DUMMYFUNCTION("""COMPUTED_VALUE"""),"02-Medellin") -> 02-Medellin | AM18: =IFERROR(__xludf.DUMMYFUNCTION("""COMPUTED_VALUE"""),132.0) -> 132 | AP18: 15 | AQ18: =IFERROR(__xludf.DUMMYFUNCTION("""COMPUTED_VALUE"""),46242.0) -> 46242 | AR18: =IFERROR(__xludf.DUMMYFUNCTION("""COMPUTED_VALUE"""),"02-Medellin") -> 02-Medellin | AS18: =IFERROR(__xludf.DUMMYFUNCTION("""COMPUTED_VALUE"""),132.0) -> 132 | AV18: 15
B19: 16 | C19: =IFERROR(__xludf.DUMMYFUNCTION("""COMPUTED_VALUE"""),2198.0) -> 2198 | D19: =IFERROR(__xludf.DUMMYFUNCTION("""COMPUTED_VALUE"""),46515.0) -> 46515 | E19: =IFERROR(__xludf.DUMMYFUNCTION("""COMPUTED_VALUE"""),"02-Medellin") -> 02-Medellin | F19: =IFERROR(__xludf.DUMMYFUNCTION("""COMPUTED_VALUE"""),46028.0) -> 46028 | G19: =IFERROR(__xludf.DUMMYFUNCTION("""COMPUTED_VALUE"""),-8.0) -> -8 | H19: =IFERROR(__xludf.DUMMYFUNCTION("""COMPUTED_VALUE"""),"PASADO") -> PASADO | I19: =IF(OR(H19="PASADO",H19="PRÓXIMO"), IF(AND(NOT(ISERROR(MATCH(C19,$T$4:$T$195,0))),NOT(ISERROR(MATCH(C19,$U$4:$U$195,0)))),"HECHO",IF(NOT(ISERROR(MATCH(C19,$U$4:$U$195,0))),"PEDIDO","NO PEDIDO")),"-") -> HECHO | K19: 16 | L19: =IFERROR(__xludf.DUMMYFUNCTION("""COMPUTED_VALUE"""),2853.0) -> 2853 | M19: =IFERROR(__xludf.DUMMYFUNCTION("""COMPUTED_VALUE"""),46576.0) -> 46576 | N19: =IFERROR(__xludf.DUMMYFUNCTION("""COMPUTED_VALUE"""),"BULTOS") -> BULTOS | O19: =IFERROR(__xludf.DUMMYFUNCTION("""COMPUTED_VALUE"""),46109.0) -> 46109 | P19: =IFERROR(__xludf.DUMMYFUNCTION("""COMPUTED_VALUE"""),-1262.0) -> -1262 | Q19: =IFERROR(__xludf.DUMMYFUNCTION("""COMPUTED_VALUE"""),"PASADO") -> PASADO | R19: =IF(OR(Q19="PASADO",Q19="PRÓXIMO"), IF(AND(NOT(ISERROR(MATCH(L19,$T$4:$T$195,0))),NOT(ISERROR(MATCH(L19,$U$4:$U$195,0)))),"HECHO",IF(NOT(ISERROR(MATCH(L19,$U$4:$U$195,0))),"PEDIDO","NO PEDIDO")),"-") -> HECHO | T19: =CALENDARIO!D31 -> 2903 | U19: =CALENDARIO!C31 -> 3198 | X19: =(VLOOKUP(W19,'BD LUB'!$A$2:$L$223,5,FALSE)/VLOOKUP(W19,'BD LUB'!$A$2:$L$223,7,FALSE))+(VLOOKUP(W19,'BD LUB'!$A$2:$L$223,6,FALSE)/VLOOKUP(W19,'BD LUB'!$A$2:$L$223,8,FALSE)) -> #N/A | Y19: =IF(AND(VLOOKUP(W19,'BD LUB'!$A$2:$L$223,11,FALSE)="PASADO",VLOOKUP(W19,'BD LUB'!$A$2:$L$223,12,FALSE)="PASADO"),1,IF(OR(AND(VLOOKUP(W19,'BD LUB'!$A$2:$L$223,11,FALSE)="PASADO",VLOOKUP(W19,'BD LUB'!$A$2:$L$223,12,FALSE)="PRÓXIMO"),AND(VLOOKUP(W19,'BD LUB'!$A$2:$L$223,11,FALSE)="PRÓXIMO",VLOOKUP(W19,'BD LUB'!$A$2:$L$223,12,FALSE)="PASADO")),2,IF(OR(AND(VLOOKUP(W19,'BD LUB'!$A$2:$L$223,11,FALSE)="PASADO",VLOOKUP(W19,'BD LUB'!$A$2:$L$223,12,FALSE)="VIGENTE"),AND(VLOOKUP(W19,'BD LUB'!$A$2:$L$223,11,FALSE)="VIGENTE",VLOOKUP(W19,'BD LUB'!$A$2:$L$223,12,FALSE)="PASADO")),3,IF(AND(VLOOKUP(W19,'BD LUB'!$A$2:$L$223,11,FALSE)="PRÓXIMO",VLOOKUP(W19,'BD LUB'!$A$2:$L$223,12,FALSE)="PRÓXIMO"),4,IF(OR(AND(VLOOKUP(W19,'BD LUB'!$A$2:$L$223,11,FALSE)="PRÓXIMO",VLOOKUP(W19,'BD LUB'!$A$2:$L$223,12,FALSE)="VIGENTE"),AND(VLOOKUP(W19,'BD LUB'!$A$2:$L$223,11,FALSE)="VIGENTE",VLOOKUP(W19,'BD LUB'!$A$2:$L$223,12,FALSE)="PRÓXIMO")),5,IF(AND(VLOOKUP(W19,'BD LUB'!$A$2:$L$223,11,FALSE)="VIGENTE",VLOOKUP(W19,'BD LUB'!$A$2:$L$223,12,FALSE)="VIGENTE"),6,"No definido")))))) -> #N/A | Z19: =IFERROR(__xludf.DUMMYFUNCTION("""COMPUTED_VALUE"""),496.0) -> 496 | AA19: =(VLOOKUP(Z19,'BD LUB'!$A$2:$L$223,5,FALSE)/VLOOKUP(Z19,'BD LUB'!$A$2:$L$223,7,FALSE))+(VLOOKUP(Z19,'BD LUB'!$A$2:$L$223,6,FALSE)/VLOOKUP(Z19,'BD LUB'!$A$2:$L$223,8,FALSE)) -> 1.4086289 | AB19: =IF(AND(VLOOKUP(Z19,'BD LUB'!$A$2:$L$223,11,FALSE)="PASADO",VLOOKUP(Z19,'BD LUB'!$A$2:$L$223,12,FALSE)="PASADO"),1,IF(OR(AND(VLOOKUP(Z19,'BD LUB'!$A$2:$L$223,11,FALSE)="PASADO",VLOOKUP(Z19,'BD LUB'!$A$2:$L$223,12,FALSE)="PRÓXIMO"),AND(VLOOKUP(Z19,'BD LUB'!$A$2:$L$223,11,FALSE)="PRÓXIMO",VLOOKUP(Z19,'BD LUB'!$A$2:$L$223,12,FALSE)="PASADO")),2,IF(OR(AND(VLOOKUP(Z19,'BD LUB'!$A$2:$L$223,11,FALSE)="PASADO",VLOOKUP(Z19,'BD LUB'!$A$2:$L$223,12,FALSE)="VIGENTE"),AND(VLOOKUP(Z19,'BD LUB'!$A$2:$L$223,11,FALSE)="VIGENTE",VLOOKUP(Z19,'BD LUB'!$A$2:$L$223,12,FALSE)="PASADO")),3,IF(AND(VLOOKUP(Z19,'BD LUB'!$A$2:$L$223,11,FALSE)="PRÓXIMO",VLOOKUP(Z19,'BD LUB'!$A$2:$L$223,12,FALSE)="PRÓXIMO"),4,IF(OR(AND(VLOOKUP(Z19,'BD LUB'!$A$2:$L$223,11,FALSE)="PRÓXIMO",VLOOKUP(Z19,'BD LUB'!$A$2:$L$223,12,FALSE)="VIGENTE"),AND(VLOOKUP(Z19,'BD LUB'!$A$2:$L$223,11,FALSE)="VIGENTE",VLOOKUP(Z19,'BD LUB'!$A$2:$L$223,12,FALSE)="PRÓXIMO")),5,IF(AND(VLOOKUP(Z19,'BD LUB'!$A$2:$L$223,11,FALSE)="VIGENTE",VLOOKUP(Z19,'BD LUB'!$A$2:$L$223,12,FALSE)="VIGENTE"),6,"No definido")))))) -> 5 | AC19: =IFERROR(__xludf.DUMMYFUNCTION("""COMPUTED_VALUE"""),2921.0) -> 2921 | AD19: =IF(VLOOKUP(AC19,'BD LUB'!$A$2:$C$223,3,FALSE)=$AH$20,AC19&" MED",IF(VLOOKUP(AC19,'BD LUB'!$A$2:$C$223,3,FALSE)=$AH$19,AC19&" MAY",IF(VLOOKUP(AC19,'BD LUB'!$A$2:$C$223,3,FALSE)=$AH$18,AC19&" RN",IF(VLOOKUP(AC19,'BD LUB'!$A$2:$C$223,3,FALSE)=$AH$17,AC19&" COPQUI",IF(VLOOKUP(AC19,'BD LUB'!$A$2:$C$223,3,FALSE)=$AH$16,AC19&" CEJ",IF(VLOOKUP(AC19,'BD LUB'!$A$2:$C$223,3,FALSE)=$AH$15,AC19&" BULT",IF(VLOOKUP(AC19,'BD LUB'!$A$2:$C$223,3,FALSE)=$AH$14,AC19&" COP",IF(VLOOKUP(AC19,'BD LUB'!$A$2:$C$223,3,FALSE)=$AH$13,AC19&" RIO",IF(VLOOKUP(AC19,'BD LUB'!$A$2:$C$223,3,FALSE)=$AH$21,AC19&" APART","Dato no encontrado"))))))))) -> 2921 MAY | AH19: MAYORCA | AJ19: 16 | AK19: =IFERROR(__xludf.DUMMYFUNCTION("""COMPUTED_VALUE"""),46668.0) -> 46668 | AL19: =IFERROR(__xludf.DUMMYFUNCTION("""COMPUTED_VALUE"""),"02-Medellin") -> 02-Medellin | AM19: =IFERROR(__xludf.DUMMYFUNCTION("""COMPUTED_VALUE"""),130.0) -> 130 | AP19: 16 | AQ19: =IFERROR(__xludf.DUMMYFUNCTION("""COMPUTED_VALUE"""),46668.0) -> 46668 | AR19: =IFERROR(__xludf.DUMMYFUNCTION("""COMPUTED_VALUE"""),"02-Medellin") -> 02-Medellin | AS19: =IFERROR(__xludf.DUMMYFUNCTION("""COMPUTED_VALUE"""),130.0) -> 130 | AV19: 16
B20: 17 | C20: =IFERROR(__xludf.DUMMYFUNCTION("""COMPUTED_VALUE"""),2681.0) -> 2681 | D20: =IFERROR(__xludf.DUMMYFUNCTION("""COMPUTED_VALUE"""),46514.0) -> 46514 | E20: =IFERROR(__xludf.DUMMYFUNCTION("""COMPUTED_VALUE"""),"27-Apartado") -> 27-Apartado | F20: =IFERROR(__xludf.DUMMYFUNCTION("""COMPUTED_VALUE"""),46029.0) -> 46029 | G20: =IFERROR(__xludf.DUMMYFUNCTION("""COMPUTED_VALUE"""),-7.0) -> -7 | H20: =IFERROR(__xludf.DUMMYFUNCTION("""COMPUTED_VALUE"""),"PASADO") -> PASADO | I20: =IF(OR(H20="PASADO",H20="PRÓXIMO"), IF(AND(NOT(ISERROR(MATCH(C20,$T$4:$T$195,0))),NOT(ISERROR(MATCH(C20,$U$4:$U$195,0)))),"HECHO",IF(NOT(ISERROR(MATCH(C20,$U$4:$U$195,0))),"PEDIDO","NO PEDIDO")),"-") -> PEDIDO | K20: 17 | L20: =IFERROR(__xludf.DUMMYFUNCTION("""COMPUTED_VALUE"""),2882.0) -> 2882 | M20: =IFERROR(__xludf.DUMMYFUNCTION("""COMPUTED_VALUE"""),46233.0) -> 46233 | N20: =IFERROR(__xludf.DUMMYFUNCTION("""COMPUTED_VALUE"""),"38-La ceja") -> 38-La ceja | O20: =IFERROR(__xludf.DUMMYFUNCTION("""COMPUTED_VALUE"""),46139.0) -> 46139 | P20: =IFERROR(__xludf.DUMMYFUNCTION("""COMPUTED_VALUE"""),-1209.0) -> -1209 | Q20: =IFERROR(__xludf.DUMMYFUNCTION("""COMPUTED_VALUE"""),"PASADO") -> PASADO | R20: =IF(OR(Q20="PASADO",Q20="PRÓXIMO"), IF(AND(NOT(ISERROR(MATCH(L20,$T$4:$T$195,0))),NOT(ISERROR(MATCH(L20,$U$4:$U$195,0)))),"HECHO",IF(NOT(ISERROR(MATCH(L20,$U$4:$U$195,0))),"PEDIDO","NO PEDIDO")),"-") -> HECHO | T20: =CALENDARIO!D32 -> 2437 | U20: =CALENDARIO!C32 -> 2230 | X20: =(VLOOKUP(W20,'BD LUB'!$A$2:$L$223,5,FALSE)/VLOOKUP(W20,'BD LUB'!$A$2:$L$223,7,FALSE))+(VLOOKUP(W20,'BD LUB'!$A$2:$L$223,6,FALSE)/VLOOKUP(W20,'BD LUB'!$A$2:$L$223,8,FALSE)) -> #N/A | Y20: =IF(AND(VLOOKUP(W20,'BD LUB'!$A$2:$L$223,11,FALSE)="PASADO",VLOOKUP(W20,'BD LUB'!$A$2:$L$223,12,FALSE)="PASADO"),1,IF(OR(AND(VLOOKUP(W20,'BD LUB'!$A$2:$L$223,11,FALSE)="PASADO",VLOOKUP(W20,'BD LUB'!$A$2:$L$223,12,FALSE)="PRÓXIMO"),AND(VLOOKUP(W20,'BD LUB'!$A$2:$L$223,11,FALSE)="PRÓXIMO",VLOOKUP(W20,'BD LUB'!$A$2:$L$223,12,FALSE)="PASADO")),2,IF(OR(AND(VLOOKUP(W20,'BD LUB'!$A$2:$L$223,11,FALSE)="PASADO",VLOOKUP(W20,'BD LUB'!$A$2:$L$223,12,FALSE)="VIGENTE"),AND(VLOOKUP(W20,'BD LUB'!$A$2:$L$223,11,FALSE)="VIGENTE",VLOOKUP(W20,'BD LUB'!$A$2:$L$223,12,FALSE)="PASADO")),3,IF(AND(VLOOKUP(W20,'BD LUB'!$A$2:$L$223,11,FALSE)="PRÓXIMO",VLOOKUP(W20,'BD LUB'!$A$2:$L$223,12,FALSE)="PRÓXIMO"),4,IF(OR(AND(VLOOKUP(W20,'BD LUB'!$A$2:$L$223,11,FALSE)="PRÓXIMO",VLOOKUP(W20,'BD LUB'!$A$2:$L$223,12,FALSE)="VIGENTE"),AND(VLOOKUP(W20,'BD LUB'!$A$2:$L$223,11,FALSE)="VIGENTE",VLOOKUP(W20,'BD LUB'!$A$2:$L$223,12,FALSE)="PRÓXIMO")),5,IF(AND(VLOOKUP(W20,'BD LUB'!$A$2:$L$223,11,FALSE)="VIGENTE",VLOOKUP(W20,'BD LUB'!$A$2:$L$223,12,FALSE)="VIGENTE"),6,"No definido")))))) -> #N/A | Z20: =IFERROR(__xludf.DUMMYFUNCTION("""COMPUTED_VALUE"""),464.0) -> 464 | AA20: =(VLOOKUP(Z20,'BD LUB'!$A$2:$L$223,5,FALSE)/VLOOKUP(Z20,'BD LUB'!$A$2:$L$223,7,FALSE))+(VLOOKUP(Z20,'BD LUB'!$A$2:$L$223,6,FALSE)/VLOOKUP(Z20,'BD LUB'!$A$2:$L$223,8,FALSE)) -> 1.18678 | AB20: =IF(AND(VLOOKUP(Z20,'BD LUB'!$A$2:$L$223,11,FALSE)="PASADO",VLOOKUP(Z20,'BD LUB'!$A$2:$L$223,12,FALSE)="PASADO"),1,IF(OR(AND(VLOOKUP(Z20,'BD LUB'!$A$2:$L$223,11,FALSE)="PASADO",VLOOKUP(Z20,'BD LUB'!$A$2:$L$223,12,FALSE)="PRÓXIMO"),AND(VLOOKUP(Z20,'BD LUB'!$A$2:$L$223,11,FALSE)="PRÓXIMO",VLOOKUP(Z20,'BD LUB'!$A$2:$L$223,12,FALSE)="PASADO")),2,IF(OR(AND(VLOOKUP(Z20,'BD LUB'!$A$2:$L$223,11,FALSE)="PASADO",VLOOKUP(Z20,'BD LUB'!$A$2:$L$223,12,FALSE)="VIGENTE"),AND(VLOOKUP(Z20,'BD LUB'!$A$2:$L$223,11,FALSE)="VIGENTE",VLOOKUP(Z20,'BD LUB'!$A$2:$L$223,12,FALSE)="PASADO")),3,IF(AND(VLOOKUP(Z20,'BD LUB'!$A$2:$L$223,11,FALSE)="PRÓXIMO",VLOOKUP(Z20,'BD LUB'!$A$2:$L$223,12,FALSE)="PRÓXIMO"),4,IF(OR(AND(VLOOKUP(Z20,'BD LUB'!$A$2:$L$223,11,FALSE)="PRÓXIMO",VLOOKUP(Z20,'BD LUB'!$A$2:$L$223,12,FALSE)="VIGENTE"),AND(VLOOKUP(Z20,'BD LUB'!$A$2:$L$223,11,FALSE)="VIGENTE",VLOOKUP(Z20,'BD LUB'!$A$2:$L$223,12,FALSE)="PRÓXIMO")),5,IF(AND(VLOOKUP(Z20,'BD LUB'!$A$2:$L$223,11,FALSE)="VIGENTE",VLOOKUP(Z20,'BD LUB'!$A$2:$L$223,12,FALSE)="VIGENTE"),6,"No definido")))))) -> 5 | AC20: =IFERROR(__xludf.DUMMYFUNCTION("""COMPUTED_VALUE"""),2859.0) -> 2859 | AD20: =IF(VLOOKUP(AC20,'BD LUB'!$A$2:$C$223,3,FALSE)=$AH$20,AC20&" MED",IF(VLOOKUP(AC20,'BD LUB'!$A$2:$C$223,3,FALSE)=$AH$19,AC20&" MAY",IF(VLOOKUP(AC20,'BD LUB'!$A$2:$C$223,3,FALSE)=$AH$18,AC20&" RN",IF(VLOOKUP(AC20,'BD LUB'!$A$2:$C$223,3,FALSE)=$AH$17,AC20&" COPQUI",IF(VLOOKUP(AC20,'BD LUB'!$A$2:$C$223,3,FALSE)=$AH$16,AC20&" CEJ",IF(VLOOKUP(AC20,'BD LUB'!$A$2:$C$223,3,FALSE)=$AH$15,AC20&" BULT",IF(VLOOKUP(AC20,'BD LUB'!$A$2:$C$223,3,FALSE)=$AH$14,AC20&" COP",IF(VLOOKUP(AC20,'BD LUB'!$A$2:$C$223,3,FALSE)=$AH$13,AC20&" RIO",IF(VLOOKUP(AC20,'BD LUB'!$A$2:$C$223,3,FALSE)=$AH$21,AC20&" APART","Dato no encontrado"))))))))) -> 2859 MAY | AH20: 02-Medellin | AJ20: 17 | AK20: =IFERROR(__xludf.DUMMYFUNCTION("""COMPUTED_VALUE"""),46668.0) -> 46668 | AL20: =IFERROR(__xludf.DUMMYFUNCTION("""COMPUTED_VALUE"""),"02-Medellin") -> 02-Medellin | AM20: =IFERROR(__xludf.DUMMYFUNCTION("""COMPUTED_VALUE"""),129.0) -> 129 | AP20: 17 | AQ20: =IFERROR(__xludf.DUMMYFUNCTION("""COMPUTED_VALUE"""),46668.0) -> 46668 | AR20: =IFERROR(__xludf.DUMMYFUNCTION("""COMPUTED_VALUE"""),"02-Medellin") -> 02-Medellin | AS20: =IFERROR(__xludf.DUMMYFUNCTION("""COMPUTED_VALUE"""),129.0) -> 129 | AV20: 17
B21: 18 | C21: =IFERROR(__xludf.DUMMYFUNCTION("""COMPUTED_VALUE"""),2384.0) -> 2384 | D21: =IFERROR(__xludf.DUMMYFUNCTION("""COMPUTED_VALUE"""),46571.0) -> 46571 | E21: =IFERROR(__xludf.DUMMYFUNCTION("""COMPUTED_VALUE"""),"02-Medellin") -> 02-Medellin | F21: =IFERROR(__xludf.DUMMYFUNCTION("""COMPUTED_VALUE"""),46029.0) -> 46029 | G21: =IFERROR(__xludf.DUMMYFUNCTION("""COMPUTED_VALUE"""),-7.0) -> -7 | H21: =IFERROR(__xludf.DUMMYFUNCTION("""COMPUTED_VALUE"""),"PASADO") -> PASADO | I21: =IF(OR(H21="PASADO",H21="PRÓXIMO"), IF(AND(NOT(ISERROR(MATCH(C21,$T$4:$T$195,0))),NOT(ISERROR(MATCH(C21,$U$4:$U$195,0)))),"HECHO",IF(NOT(ISERROR(MATCH(C21,$U$4:$U$195,0))),"PEDIDO","NO PEDIDO")),"-") -> HECHO | K21: 18 | L21: =IFERROR(__xludf.DUMMYFUNCTION("""COMPUTED_VALUE"""),2188.0) -> 2188 | M21: =IFERROR(__xludf.DUMMYFUNCTION("""COMPUTED_VALUE"""),46375.0) -> 46375 | N21: =IFERROR(__xludf.DUMMYFUNCTION("""COMPUTED_VALUE"""),"BULTOS") -> BULTOS | O21: =IFERROR(__xludf.DUMMYFUNCTION("""COMPUTED_VALUE"""),46042.0) -> 46042 | P21: =IFERROR(__xludf.DUMMYFUNCTION("""COMPUTED_VALUE"""),-1139.8999999999996) -> -1139.9 | Q21: =IFERROR(__xludf.DUMMYFUNCTION("""COMPUTED_VALUE"""),"PASADO") -> PASADO | R21: =IF(OR(Q21="PASADO",Q21="PRÓXIMO"), IF(AND(NOT(ISERROR(MATCH(L21,$T$4:$T$195,0))),NOT(ISERROR(MATCH(L21,$U$4:$U$195,0)))),"HECHO",IF(NOT(ISERROR(MATCH(L21,$U$4:$U$195,0))),"PEDIDO","NO PEDIDO")),"-") -> PEDIDO | T21: =CALENDARIO!D33 -> 2384 | U21: =CALENDARIO!C33 -> 3282 | X21: =(VLOOKUP(W21,'BD LUB'!$A$2:$L$223,5,FALSE)/VLOOKUP(W21,'BD LUB'!$A$2:$L$223,7,FALSE))+(VLOOKUP(W21,'BD LUB'!$A$2:$L$223,6,FALSE)/VLOOKUP(W21,'BD LUB'!$A$2:$L$223,8,FALSE)) -> #N/A | Y21: =IF(AND(VLOOKUP(W21,'BD LUB'!$A$2:$L$223,11,FALSE)="PASADO",VLOOKUP(W21,'BD LUB'!$A$2:$L$223,12,FALSE)="PASADO"),1,IF(OR(AND(VLOOKUP(W21,'BD LUB'!$A$2:$L$223,11,FALSE)="PASADO",VLOOKUP(W21,'BD LUB'!$A$2:$L$223,12,FALSE)="PRÓXIMO"),AND(VLOOKUP(W21,'BD LUB'!$A$2:$L$223,11,FALSE)="PRÓXIMO",VLOOKUP(W21,'BD LUB'!$A$2:$L$223,12,FALSE)="PASADO")),2,IF(OR(AND(VLOOKUP(W21,'BD LUB'!$A$2:$L$223,11,FALSE)="PASADO",VLOOKUP(W21,'BD LUB'!$A$2:$L$223,12,FALSE)="VIGENTE"),AND(VLOOKUP(W21,'BD LUB'!$A$2:$L$223,11,FALSE)="VIGENTE",VLOOKUP(W21,'BD LUB'!$A$2:$L$223,12,FALSE)="PASADO")),3,IF(AND(VLOOKUP(W21,'BD LUB'!$A$2:$L$223,11,FALSE)="PRÓXIMO",VLOOKUP(W21,'BD LUB'!$A$2:$L$223,12,FALSE)="PRÓXIMO"),4,IF(OR(AND(VLOOKUP(W21,'BD LUB'!$A$2:$L$223,11,FALSE)="PRÓXIMO",VLOOKUP(W21,'BD LUB'!$A$2:$L$223,12,FALSE)="VIGENTE"),AND(VLOOKUP(W21,'BD LUB'!$A$2:$L$223,11,FALSE)="VIGENTE",VLOOKUP(W21,'BD LUB'!$A$2:$L$223,12,FALSE)="PRÓXIMO")),5,IF(AND(VLOOKUP(W21,'BD LUB'!$A$2:$L$223,11,FALSE)="VIGENTE",VLOOKUP(W21,'BD LUB'!$A$2:$L$223,12,FALSE)="VIGENTE"),6,"No definido")))))) -> #N/A | Z21: =IFERROR(__xludf.DUMMYFUNCTION("""COMPUTED_VALUE"""),2484.0) -> 2484 | AA21: =(VLOOKUP(Z21,'BD LUB'!$A$2:$L$223,5,FALSE)/VLOOKUP(Z21,'BD LUB'!$A$2:$L$223,7,FALSE))+(VLOOKUP(Z21,'BD LUB'!$A$2:$L$223,6,FALSE)/VLOOKUP(Z21,'BD LUB'!$A$2:$L$223,8,FALSE)) -> 2.0514067 | AB21: =IF(AND(VLOOKUP(Z21,'BD LUB'!$A$2:$L$223,11,FALSE)="PASADO",VLOOKUP(Z21,'BD LUB'!$A$2:$L$223,12,FALSE)="PASADO"),1,IF(OR(AND(VLOOKUP(Z21,'BD LUB'!$A$2:$L$223,11,FALSE)="PASADO",VLOOKUP(Z21,'BD LUB'!$A$2:$L$223,12,FALSE)="PRÓXIMO"),AND(VLOOKUP(Z21,'BD LUB'!$A$2:$L$223,11,FALSE)="PRÓXIMO",VLOOKUP(Z21,'BD LUB'!$A$2:$L$223,12,FALSE)="PASADO")),2,IF(OR(AND(VLOOKUP(Z21,'BD LUB'!$A$2:$L$223,11,FALSE)="PASADO",VLOOKUP(Z21,'BD LUB'!$A$2:$L$223,12,FALSE)="VIGENTE"),AND(VLOOKUP(Z21,'BD LUB'!$A$2:$L$223,11,FALSE)="VIGENTE",VLOOKUP(Z21,'BD LUB'!$A$2:$L$223,12,FALSE)="PASADO")),3,IF(AND(VLOOKUP(Z21,'BD LUB'!$A$2:$L$223,11,FALSE)="PRÓXIMO",VLOOKUP(Z21,'BD LUB'!$A$2:$L$223,12,FALSE)="PRÓXIMO"),4,IF(OR(AND(VLOOKUP(Z21,'BD LUB'!$A$2:$L$223,11,FALSE)="PRÓXIMO",VLOOKUP(Z21,'BD LUB'!$A$2:$L$223,12,FALSE)="VIGENTE"),AND(VLOOKUP(Z21,'BD LUB'!$A$2:$L$223,11,FALSE)="VIGENTE",VLOOKUP(Z21,'BD LUB'!$A$2:$L$223,12,FALSE)="PRÓXIMO")),5,IF(AND(VLOOKUP(Z21,'BD LUB'!$A$2:$L$223,11,FALSE)="VIGENTE",VLOOKUP(Z21,'BD LUB'!$A$2:$L$223,12,FALSE)="VIGENTE"),6,"No definido")))))) -> 2 | AC21: =IFERROR(__xludf.DUMMYFUNCTION("""COMPUTED_VALUE"""),2927.0) -> 2927 | AD21: =IF(VLOOKUP(AC21,'BD LUB'!$A$2:$C$223,3,FALSE)=$AH$20,AC21&" MED",IF(VLOOKUP(AC21,'BD LUB'!$A$2:$C$223,3,FALSE)=$AH$19,AC21&" MAY",IF(VLOOKUP(AC21,'BD LUB'!$A$2:$C$223,3,FALSE)=$AH$18,AC21&" RN",IF(VLOOKUP(AC21,'BD LUB'!$A$2:$C$223,3,FALSE)=$AH$17,AC21&" COPQUI",IF(VLOOKUP(AC21,'BD LUB'!$A$2:$C$223,3,FALSE)=$AH$16,AC21&" CEJ",IF(VLOOKUP(AC21,'BD LUB'!$A$2:$C$223,3,FALSE)=$AH$15,AC21&" BULT",IF(VLOOKUP(AC21,'BD LUB'!$A$2:$C$223,3,FALSE)=$AH$14,AC21&" COP",IF(VLOOKUP(AC21,'BD LUB'!$A$2:$C$223,3,FALSE)=$AH$13,AC21&" RIO",IF(VLOOKUP(AC21,'BD LUB'!$A$2:$C$223,3,FALSE)=$AH$21,AC21&" APART","Dato no encontrado"))))))))) -> 2927 MED | AH21: 27-Apartado | AJ21: 18 | AK21: =IFERROR(__xludf.DUMMYFUNCTION("""COMPUTED_VALUE"""),46661.0) -> 46661 | AL21: =IFERROR(__xludf.DUMMYFUNCTION("""COMPUTED_VALUE"""),"24-Rionegro") -> 24-Rionegro | AM21: =IFERROR(__xludf.DUMMYFUNCTION("""COMPUTED_VALUE"""),129.0) -> 129 | AP21: 18 | AQ21: =IFERROR(__xludf.DUMMYFUNCTION("""COMPUTED_VALUE"""),46661.0) -> 46661 | AR21: =IFERROR(__xludf.DUMMYFUNCTION("""COMPUTED_VALUE"""),"24-Rionegro") -> 24-Rionegro | AS21: =IFERROR(__xludf.DUMMYFUNCTION("""COMPUTED_VALUE"""),129.0) -> 129 | AV21: 18
B22: 19 | C22: =IFERROR(__xludf.DUMMYFUNCTION("""COMPUTED_VALUE"""),2339.0) -> 2339 | D22: =IFERROR(__xludf.DUMMYFUNCTION("""COMPUTED_VALUE"""),46572.0) -> 46572 | E22: =IFERROR(__xludf.DUMMYFUNCTION("""COMPUTED_VALUE"""),"02-Medellin") -> 02-Medellin | F22: =IFERROR(__xludf.DUMMYFUNCTION("""COMPUTED_VALUE"""),46029.0) -> 46029 | G22: =IFERROR(__xludf.DUMMYFUNCTION("""COMPUTED_VALUE"""),-7.0) -> -7 | H22: =IFERROR(__xludf.DUMMYFUNCTION("""COMPUTED_VALUE"""),"PASADO") -> PASADO | I22: =IF(OR(H22="PASADO",H22="PRÓXIMO"), IF(AND(NOT(ISERROR(MATCH(C22,$T$4:$T$195,0))),NOT(ISERROR(MATCH(C22,$U$4:$U$195,0)))),"HECHO",IF(NOT(ISERROR(MATCH(C22,$U$4:$U$195,0))),"PEDIDO","NO PEDIDO")),"-") -> HECHO | K22: 19 | L22: =IFERROR(__xludf.DUMMYFUNCTION("""COMPUTED_VALUE"""),2334.0) -> 2334 | M22: =IFERROR(__xludf.DUMMYFUNCTION("""COMPUTED_VALUE"""),46543.0) -> 46543 | N22: =IFERROR(__xludf.DUMMYFUNCTION("""COMPUTED_VALUE"""),"27-Apartado") -> 27-Apartado | O22: =IFERROR(__xludf.DUMMYFUNCTION("""COMPUTED_VALUE"""),46030.0) -> 46030 | P22: =IFERROR(__xludf.DUMMYFUNCTION("""COMPUTED_VALUE"""),-1111.0) -> -1111 | Q22: =IFERROR(__xludf.DUMMYFUNCTION("""COMPUTED_VALUE"""),"PASADO") -> PASADO | R22: =IF(OR(Q22="PASADO",Q22="PRÓXIMO"), IF(AND(NOT(ISERROR(MATCH(L22,$T$4:$T$195,0))),NOT(ISERROR(MATCH(L22,$U$4:$U$195,0)))),"HECHO",IF(NOT(ISERROR(MATCH(L22,$U$4:$U$195,0))),"PEDIDO","NO PEDIDO")),"-") -> PEDIDO | T22: =CALENDARIO!D34 -> 2853 | U22: =CALENDARIO!C34 -> 3280 | X22: =(VLOOKUP(W22,'BD LUB'!$A$2:$L$223,5,FALSE)/VLOOKUP(W22,'BD LUB'!$A$2:$L$223,7,FALSE))+(VLOOKUP(W22,'BD LUB'!$A$2:$L$223,6,FALSE)/VLOOKUP(W22,'BD LUB'!$A$2:$L$223,8,FALSE)) -> #N/A | Y22: =IF(AND(VLOOKUP(W22,'BD LUB'!$A$2:$L$223,11,FALSE)="PASADO",VLOOKUP(W22,'BD LUB'!$A$2:$L$223,12,FALSE)="PASADO"),1,IF(OR(AND(VLOOKUP(W22,'BD LUB'!$A$2:$L$223,11,FALSE)="PASADO",VLOOKUP(W22,'BD LUB'!$A$2:$L$223,12,FALSE)="PRÓXIMO"),AND(VLOOKUP(W22,'BD LUB'!$A$2:$L$223,11,FALSE)="PRÓXIMO",VLOOKUP(W22,'BD LUB'!$A$2:$L$223,12,FALSE)="PASADO")),2,IF(OR(AND(VLOOKUP(W22,'BD LUB'!$A$2:$L$223,11,FALSE)="PASADO",VLOOKUP(W22,'BD LUB'!$A$2:$L$223,12,FALSE)="VIGENTE"),AND(VLOOKUP(W22,'BD LUB'!$A$2:$L$223,11,FALSE)="VIGENTE",VLOOKUP(W22,'BD LUB'!$A$2:$L$223,12,FALSE)="PASADO")),3,IF(AND(VLOOKUP(W22,'BD LUB'!$A$2:$L$223,11,FALSE)="PRÓXIMO",VLOOKUP(W22,'BD LUB'!$A$2:$L$223,12,FALSE)="PRÓXIMO"),4,IF(OR(AND(VLOOKUP(W22,'BD LUB'!$A$2:$L$223,11,FALSE)="PRÓXIMO",VLOOKUP(W22,'BD LUB'!$A$2:$L$223,12,FALSE)="VIGENTE"),AND(VLOOKUP(W22,'BD LUB'!$A$2:$L$223,11,FALSE)="VIGENTE",VLOOKUP(W22,'BD LUB'!$A$2:$L$223,12,FALSE)="PRÓXIMO")),5,IF(AND(VLOOKUP(W22,'BD LUB'!$A$2:$L$223,11,FALSE)="VIGENTE",VLOOKUP(W22,'BD LUB'!$A$2:$L$223,12,FALSE)="VIGENTE"),6,"No definido")))))) -> #N/A | Z22: =IFERROR(__xludf.DUMMYFUNCTION("""COMPUTED_VALUE"""),2394.0) -> 2394 | AA22: =(VLOOKUP(Z22,'BD LUB'!$A$2:$L$223,5,FALSE)/VLOOKUP(Z22,'BD LUB'!$A$2:$L$223,7,FALSE))+(VLOOKUP(Z22,'BD LUB'!$A$2:$L$223,6,FALSE)/VLOOKUP(Z22,'BD LUB'!$A$2:$L$223,8,FALSE)) -> 1.4558467 | AB22: =IF(AND(VLOOKUP(Z22,'BD LUB'!$A$2:$L$223,11,FALSE)="PASADO",VLOOKUP(Z22,'BD LUB'!$A$2:$L$223,12,FALSE)="PASADO"),1,IF(OR(AND(VLOOKUP(Z22,'BD LUB'!$A$2:$L$223,11,FALSE)="PASADO",VLOOKUP(Z22,'BD LUB'!$A$2:$L$223,12,FALSE)="PRÓXIMO"),AND(VLOOKUP(Z22,'BD LUB'!$A$2:$L$223,11,FALSE)="PRÓXIMO",VLOOKUP(Z22,'BD LUB'!$A$2:$L$223,12,FALSE)="PASADO")),2,IF(OR(AND(VLOOKUP(Z22,'BD LUB'!$A$2:$L$223,11,FALSE)="PASADO",VLOOKUP(Z22,'BD LUB'!$A$2:$L$223,12,FALSE)="VIGENTE"),AND(VLOOKUP(Z22,'BD LUB'!$A$2:$L$223,11,FALSE)="VIGENTE",VLOOKUP(Z22,'BD LUB'!$A$2:$L$223,12,FALSE)="PASADO")),3,IF(AND(VLOOKUP(Z22,'BD LUB'!$A$2:$L$223,11,FALSE)="PRÓXIMO",VLOOKUP(Z22,'BD LUB'!$A$2:$L$223,12,FALSE)="PRÓXIMO"),4,IF(OR(AND(VLOOKUP(Z22,'BD LUB'!$A$2:$L$223,11,FALSE)="PRÓXIMO",VLOOKUP(Z22,'BD LUB'!$A$2:$L$223,12,FALSE)="VIGENTE"),AND(VLOOKUP(Z22,'BD LUB'!$A$2:$L$223,11,FALSE)="VIGENTE",VLOOKUP(Z22,'BD LUB'!$A$2:$L$223,12,FALSE)="PRÓXIMO")),5,IF(AND(VLOOKUP(Z22,'BD LUB'!$A$2:$L$223,11,FALSE)="VIGENTE",VLOOKUP(Z22,'BD LUB'!$A$2:$L$223,12,FALSE)="VIGENTE"),6,"No definido")))))) -> 5 | AC22: =IFERROR(__xludf.DUMMYFUNCTION("""COMPUTED_VALUE"""),2925.0) -> 2925 | AD22: =IF(VLOOKUP(AC22,'BD LUB'!$A$2:$C$223,3,FALSE)=$AH$20,AC22&" MED",IF(VLOOKUP(AC22,'BD LUB'!$A$2:$C$223,3,FALSE)=$AH$19,AC22&" MAY",IF(VLOOKUP(AC22,'BD LUB'!$A$2:$C$223,3,FALSE)=$AH$18,AC22&" RN",IF(VLOOKUP(AC22,'BD LUB'!$A$2:$C$223,3,FALSE)=$AH$17,AC22&" COPQUI",IF(VLOOKUP(AC22,'BD LUB'!$A$2:$C$223,3,FALSE)=$AH$16,AC22&" CEJ",IF(VLOOKUP(AC22,'BD LUB'!$A$2:$C$223,3,FALSE)=$AH$15,AC22&" BULT",IF(VLOOKUP(AC22,'BD LUB'!$A$2:$C$223,3,FALSE)=$AH$14,AC22&" COP",IF(VLOOKUP(AC22,'BD LUB'!$A$2:$C$223,3,FALSE)=$AH$13,AC22&" RIO",IF(VLOOKUP(AC22,'BD LUB'!$A$2:$C$223,3,FALSE)=$AH$21,AC22&" APART","Dato no encontrado"))))))))) -> 2925 MED | AJ22: 19 | AK22: =IFERROR(__xludf.DUMMYFUNCTION("""COMPUTED_VALUE"""),46318.0) -> 46318 | AL22: =IFERROR(__xludf.DUMMYFUNCTION("""COMPUTED_VALUE"""),"02-Medellin") -> 02-Medellin | AM22: =IFERROR(__xludf.DUMMYFUNCTION("""COMPUTED_VALUE"""),129.0) -> 129 | AP22: 19 | AQ22: =IFERROR(__xludf.DUMMYFUNCTION("""COMPUTED_VALUE"""),46318.0) -> 46318 | AR22: =IFERROR(__xludf.DUMMYFUNCTION("""COMPUTED_VALUE"""),"02-Medellin") -> 02-Medellin | AS22: =IFERROR(__xludf.DUMMYFUNCTION("""COMPUTED_VALUE"""),129.0) -> 129 | AV22: 19
B23: 20 | C23: =IFERROR(__xludf.DUMMYFUNCTION("""COMPUTED_VALUE"""),2334.0) -> 2334 | D23: =IFERROR(__xludf.DUMMYFUNCTION("""COMPUTED_VALUE"""),46543.0) -> 46543 | E23: =IFERROR(__xludf.DUMMYFUNCTION("""COMPUTED_VALUE"""),"27-Apartado") -> 27-Apartado | F23: =IFERROR(__xludf.DUMMYFUNCTION("""COMPUTED_VALUE"""),46030.0) -> 46030 | G23: =IFERROR(__xludf.DUMMYFUNCTION("""COMPUTED_VALUE"""),-6.0) -> -6 | H23: =IFERROR(__xludf.DUMMYFUNCTION("""COMPUTED_VALUE"""),"PASADO") -> PASADO | I23: =IF(OR(H23="PASADO",H23="PRÓXIMO"), IF(AND(NOT(ISERROR(MATCH(C23,$T$4:$T$195,0))),NOT(ISERROR(MATCH(C23,$U$4:$U$195,0)))),"HECHO",IF(NOT(ISERROR(MATCH(C23,$U$4:$U$195,0))),"PEDIDO","NO PEDIDO")),"-") -> PEDIDO | K23: 20 | L23: =IFERROR(__xludf.DUMMYFUNCTION("""COMPUTED_VALUE"""),2923.0) -> 2923 | M23: =IFERROR(__xludf.DUMMYFUNCTION("""COMPUTED_VALUE"""),46318.0) -> 46318 | N23: =IFERROR(__xludf.DUMMYFUNCTION("""COMPUTED_VALUE"""),"BULTOS") -> BULTOS | O23: =IFERROR(__xludf.DUMMYFUNCTION("""COMPUTED_VALUE"""),46135.0) -> 46135 | P23: =IFERROR(__xludf.DUMMYFUNCTION("""COMPUTED_VALUE"""),-969.0) -> -969 | Q23: =IFERROR(__xludf.DUMMYFUNCTION("""COMPUTED_VALUE"""),"PASADO") -> PASADO | R23: =IF(OR(Q23="PASADO",Q23="PRÓXIMO"), IF(AND(NOT(ISERROR(MATCH(L23,$T$4:$T$195,0))),NOT(ISERROR(MATCH(L23,$U$4:$U$195,0)))),"HECHO",IF(NOT(ISERROR(MATCH(L23,$U$4:$U$195,0))),"PEDIDO","NO PEDIDO")),"-") -> PEDIDO | T23: =CALENDARIO!D35 -> 650 | U23: =CALENDARIO!C35 -> 2911 | X23: =(VLOOKUP(W23,'BD LUB'!$A$2:$L$223,5,FALSE)/VLOOKUP(W23,'BD LUB'!$A$2:$L$223,7,FALSE))+(VLOOKUP(W23,'BD LUB'!$A$2:$L$223,6,FALSE)/VLOOKUP(W23,'BD LUB'!$A$2:$L$223,8,FALSE)) -> #N/A | Y23: =IF(AND(VLOOKUP(W23,'BD LUB'!$A$2:$L$223,11,FALSE)="PASADO",VLOOKUP(W23,'BD LUB'!$A$2:$L$223,12,FALSE)="PASADO"),1,IF(OR(AND(VLOOKUP(W23,'BD LUB'!$A$2:$L$223,11,FALSE)="PASADO",VLOOKUP(W23,'BD LUB'!$A$2:$L$223,12,FALSE)="PRÓXIMO"),AND(VLOOKUP(W23,'BD LUB'!$A$2:$L$223,11,FALSE)="PRÓXIMO",VLOOKUP(W23,'BD LUB'!$A$2:$L$223,12,FALSE)="PASADO")),2,IF(OR(AND(VLOOKUP(W23,'BD LUB'!$A$2:$L$223,11,FALSE)="PASADO",VLOOKUP(W23,'BD LUB'!$A$2:$L$223,12,FALSE)="VIGENTE"),AND(VLOOKUP(W23,'BD LUB'!$A$2:$L$223,11,FALSE)="VIGENTE",VLOOKUP(W23,'BD LUB'!$A$2:$L$223,12,FALSE)="PASADO")),3,IF(AND(VLOOKUP(W23,'BD LUB'!$A$2:$L$223,11,FALSE)="PRÓXIMO",VLOOKUP(W23,'BD LUB'!$A$2:$L$223,12,FALSE)="PRÓXIMO"),4,IF(OR(AND(VLOOKUP(W23,'BD LUB'!$A$2:$L$223,11,FALSE)="PRÓXIMO",VLOOKUP(W23,'BD LUB'!$A$2:$L$223,12,FALSE)="VIGENTE"),AND(VLOOKUP(W23,'BD LUB'!$A$2:$L$223,11,FALSE)="VIGENTE",VLOOKUP(W23,'BD LUB'!$A$2:$L$223,12,FALSE)="PRÓXIMO")),5,IF(AND(VLOOKUP(W23,'BD LUB'!$A$2:$L$223,11,FALSE)="VIGENTE",VLOOKUP(W23,'BD LUB'!$A$2:$L$223,12,FALSE)="VIGENTE"),6,"No definido")))))) -> #N/A | Z23: =IFERROR(__xludf.DUMMYFUNCTION("""COMPUTED_VALUE"""),2275.0) -> 2275 | AA23: =(VLOOKUP(Z23,'BD LUB'!$A$2:$L$223,5,FALSE)/VLOOKUP(Z23,'BD LUB'!$A$2:$L$223,7,FALSE))+(VLOOKUP(Z23,'BD LUB'!$A$2:$L$223,6,FALSE)/VLOOKUP(Z23,'BD LUB'!$A$2:$L$223,8,FALSE)) -> 1.2668667 | AB23: =IF(AND(VLOOKUP(Z23,'BD LUB'!$A$2:$L$223,11,FALSE)="PASADO",VLOOKUP(Z23,'BD LUB'!$A$2:$L$223,12,FALSE)="PASADO"),1,IF(OR(AND(VLOOKUP(Z23,'BD LUB'!$A$2:$L$223,11,FALSE)="PASADO",VLOOKUP(Z23,'BD LUB'!$A$2:$L$223,12,FALSE)="PRÓXIMO"),AND(VLOOKUP(Z23,'BD LUB'!$A$2:$L$223,11,FALSE)="PRÓXIMO",VLOOKUP(Z23,'BD LUB'!$A$2:$L$223,12,FALSE)="PASADO")),2,IF(OR(AND(VLOOKUP(Z23,'BD LUB'!$A$2:$L$223,11,FALSE)="PASADO",VLOOKUP(Z23,'BD LUB'!$A$2:$L$223,12,FALSE)="VIGENTE"),AND(VLOOKUP(Z23,'BD LUB'!$A$2:$L$223,11,FALSE)="VIGENTE",VLOOKUP(Z23,'BD LUB'!$A$2:$L$223,12,FALSE)="PASADO")),3,IF(AND(VLOOKUP(Z23,'BD LUB'!$A$2:$L$223,11,FALSE)="PRÓXIMO",VLOOKUP(Z23,'BD LUB'!$A$2:$L$223,12,FALSE)="PRÓXIMO"),4,IF(OR(AND(VLOOKUP(Z23,'BD LUB'!$A$2:$L$223,11,FALSE)="PRÓXIMO",VLOOKUP(Z23,'BD LUB'!$A$2:$L$223,12,FALSE)="VIGENTE"),AND(VLOOKUP(Z23,'BD LUB'!$A$2:$L$223,11,FALSE)="VIGENTE",VLOOKUP(Z23,'BD LUB'!$A$2:$L$223,12,FALSE)="PRÓXIMO")),5,IF(AND(VLOOKUP(Z23,'BD LUB'!$A$2:$L$223,11,FALSE)="VIGENTE",VLOOKUP(Z23,'BD LUB'!$A$2:$L$223,12,FALSE)="VIGENTE"),6,"No definido")))))) -> 5 | AC23: =IFERROR(__xludf.DUMMYFUNCTION("""COMPUTED_VALUE"""),2909.0) -> 2909 | AD23: =IF(VLOOKUP(AC23,'BD LUB'!$A$2:$C$223,3,FALSE)=$AH$20,AC23&" MED",IF(VLOOKUP(AC23,'BD LUB'!$A$2:$C$223,3,FALSE)=$AH$19,AC23&" MAY",IF(VLOOKUP(AC23,'BD LUB'!$A$2:$C$223,3,FALSE)=$AH$18,AC23&" RN",IF(VLOOKUP(AC23,'BD LUB'!$A$2:$C$223,3,FALSE)=$AH$17,AC23&" COPQUI",IF(VLOOKUP(AC23,'BD LUB'!$A$2:$C$223,3,FALSE)=$AH$16,AC23&" CEJ",IF(VLOOKUP(AC23,'BD LUB'!$A$2:$C$223,3,FALSE)=$AH$15,AC23&" BULT",IF(VLOOKUP(AC23,'BD LUB'!$A$2:$C$223,3,FALSE)=$AH$14,AC23&" COP",IF(VLOOKUP(AC23,'BD LUB'!$A$2:$C$223,3,FALSE)=$AH$13,AC23&" RIO",IF(VLOOKUP(AC23,'BD LUB'!$A$2:$C$223,3,FALSE)=$AH$21,AC23&" APART","Dato no encontrado"))))))))) -> 2909 MED | AJ23: 20 | AK23: =IFERROR(__xludf.DUMMYFUNCTION("""COMPUTED_VALUE"""),46661.0) -> 46661 | AL23: =IFERROR(__xludf.DUMMYFUNCTION("""COMPUTED_VALUE"""),"02-Medellin") -> 02-Medellin | AM23: =IFERROR(__xludf.DUMMYFUNCTION("""COMPUTED_VALUE"""),126.0) -> 126 | AP23: 20 | AQ23: =IFERROR(__xludf.DUMMYFUNCTION("""COMPUTED_VALUE"""),46661.0) -> 46661 | AR23: =IFERROR(__xludf.DUMMYFUNCTION("""COMPUTED_VALUE"""),"02-Medellin") -> 02-Medellin | AS23: =IFERROR(__xludf.DUMMYFUNCTION("""COMPUTED_VALUE"""),126.0) -> 126 | AV23: 20
